Lab07/SingleCycleControl.v
`timescale 1ns / 1ps

`define OPCODE_ANDREG 11'b10001010000
`define OPCODE_ORRREG 11'b10101010000
`define OPCODE_ADDREG 11'b10001011000
`define OPCODE_SUBREG 11'b11001011000

`define OPCODE_ADDIMM 11'b1001000100?
`define OPCODE_SUBIMM 11'b1101000100?

`define OPCODE_MOVZ   11'b110100101??

`define OPCODE_B      11'b000101?????
`define OPCODE_CBZ    11'b10110100???

`define OPCODE_LDUR   11'b11111000010
`define OPCODE_STUR   11'b11111000000

module SC_Control(
               output reg       Reg2Loc,
               output reg       ALUSrc,
               output reg       MemtoReg,
               output reg       RegWrite,
               output reg       MemRead,
               output reg       MemWrite,
               output reg       Branch,
               output reg       Uncondbranch,
               output reg [3:0] ALUOp,
               output reg [1:0] SignOp,
               input [10:0]     opcode
               );

    always @(opcode) begin
        // Default values (all zeros for undefined opcodes)
        Reg2Loc = 1'b0;
        ALUSrc = 1'b0;
        MemtoReg = 1'b0;
        RegWrite = 1'b0;
        MemRead = 1'b0;
        MemWrite = 1'b0;
        Branch = 1'b0;
        Uncondbranch = 1'b0;
        ALUOp = 4'b0000;
        SignOp = 2'b00;
        
        casez(opcode)
            // R-type instructions (register-register operations)
            `OPCODE_ADDREG: begin
                Reg2Loc = 1'b0;
                ALUSrc = 1'b0;
                MemtoReg = 1'b0;
                RegWrite = 1'b1;
                MemRead = 1'b0;
                MemWrite = 1'b0;
                Branch = 1'b0;
                Uncondbranch = 1'b0;
                ALUOp = 4'b0010;
                SignOp = 2'bXX;
            end
            
            `OPCODE_SUBREG: begin
                Reg2Loc = 1'b0;
                ALUSrc = 1'b0;
                MemtoReg = 1'b0;
                RegWrite = 1'b1;
                MemRead = 1'b0;
                MemWrite = 1'b0;
                Branch = 1'b0;
                Uncondbranch = 1'b0;
                ALUOp = 4'b0110;
                SignOp = 2'bXX;
            end
            
            `OPCODE_ANDREG: begin
                Reg2Loc = 1'b0;
                ALUSrc = 1'b0;
                MemtoReg = 1'b0;
                RegWrite = 1'b1;
                MemRead = 1'b0;
                MemWrite = 1'b0;
                Branch = 1'b0;
                Uncondbranch = 1'b0;
                ALUOp = 4'b0000;
                SignOp = 2'bXX;
            end
            
            `OPCODE_ORRREG: begin
                Reg2Loc = 1'b0;
                ALUSrc = 1'b0;
                MemtoReg = 1'b0;
                RegWrite = 1'b1;
                MemRead = 1'b0;
                MemWrite = 1'b0;
                Branch = 1'b0;
                Uncondbranch = 1'b0;
                ALUOp = 4'b0001;
                SignOp = 2'bXX;
            end
            
            `OPCODE_ADDIMM: begin
                Reg2Loc = 1'bX;
                ALUSrc = 1'b1;
                MemtoReg = 1'b0;
                RegWrite = 1'b1;
                MemRead = 1'b0;
                MemWrite = 1'b0;
                Branch = 1'b0;
                Uncondbranch = 1'b0;
                ALUOp = 4'b0010;
                SignOp = 2'b00;
            end
            
            `OPCODE_SUBIMM: begin
                Reg2Loc = 1'bX;
                ALUSrc = 1'b1;
                MemtoReg = 1'b0;
                RegWrite = 1'b1;
                MemRead = 1'b0;
                MemWrite = 1'b0;
                Branch = 1'b0;
                Uncondbranch = 1'b0;
                ALUOp = 4'b0110;
                SignOp = 2'b00;
            end
            
            `OPCODE_MOVZ: begin
                Reg2Loc = 1'bX;
                ALUSrc = 1'b1;
                MemtoReg = 1'b0;
                RegWrite = 1'b1;
                MemRead = 1'b0;
                MemWrite = 1'b0;
                Branch = 1'b0;
                Uncondbranch = 1'b0;
                ALUOp = 4'b0111;
                SignOp = 2'b00;  //or 10?
            end
            
            `OPCODE_LDUR: begin
                Reg2Loc = 1'bX;
                ALUSrc = 1'b1;
                MemtoReg = 1'b1;
                RegWrite = 1'b1;
                MemRead = 1'b1;
                MemWrite = 1'b0;
                Branch = 1'b0;
                Uncondbranch = 1'b0;
                ALUOp = 4'b0010;
                SignOp = 2'b01;
            end
            
            `OPCODE_STUR: begin
                Reg2Loc = 1'b1;
                ALUSrc = 1'b1;
                MemtoReg = 1'bX;
                RegWrite = 1'b0;
                MemRead = 1'b0;
                MemWrite = 1'b1;
                Branch = 1'b0;
                Uncondbranch = 1'b0;
                ALUOp = 4'b0010;
                SignOp = 2'b01;
            end
            
            `OPCODE_B: begin
                Reg2Loc = 1'bX;
                ALUSrc = 1'bX;
                MemtoReg = 1'bX;
                RegWrite = 1'b0;
                MemRead = 1'b0;
                MemWrite = 1'b0;
                Branch = 1'b0;
                Uncondbranch = 1'b1;
                ALUOp = 4'bXXXX;
                SignOp = 2'b11;
            end
            
            `OPCODE_CBZ: begin
                Reg2Loc = 1'b1;
                ALUSrc = 1'b0;
                MemtoReg = 1'bX;
                RegWrite = 1'b0;
                MemRead = 1'b0;
                MemWrite = 1'b0;
                Branch = 1'b1;
                Uncondbranch = 1'b0;
                ALUOp = 4'b0111;
                SignOp = 2'b10;
            end
            
            default: begin
                Reg2Loc = 1'b0;
                ALUSrc = 1'b0;
                MemtoReg = 1'b0;
                RegWrite = 1'b0;
                MemRead = 1'b0;
                MemWrite = 1'b0;
                Branch = 1'b0;
                Uncondbranch = 1'b0;
                ALUOp = 4'b0000;
                SignOp = 2'b00;
            end
        endcase
    end

endmodule

Lab07/SingleCycleControlTest.v
`timescale 1ns/1ps


module SC_Control_tb();


    // Testbench signals
    reg [10:0] opcode;
    wire Reg2Loc, ALUSrc, MemtoReg, RegWrite, MemRead, MemWrite, Branch, Uncondbranch;
    wire [3:0] ALUOp;
    wire [1:0] SignOp;
    
    // Test tracking
    integer test_num;
    integer errors;
    integer i;
    reg [10:0] random_opcode;
    
    // Instantiate the control unit
    SC_Control uut (
        .Reg2Loc(Reg2Loc),
        .ALUSrc(ALUSrc),
        .MemtoReg(MemtoReg),
        .RegWrite(RegWrite),
        .MemRead(MemRead),
        .MemWrite(MemWrite),
        .Branch(Branch),
        .Uncondbranch(Uncondbranch),
        .ALUOp(ALUOp),
        .SignOp(SignOp),
        .opcode(opcode)
    );
    
    // Task to check outputs against expected values
    task check_outputs;
        input [10:0] test_opcode;
        input exp_Reg2Loc, exp_ALUSrc, exp_MemtoReg, exp_RegWrite;
        input exp_MemRead, exp_MemWrite, exp_Branch, exp_Uncondbranch;
        input [3:0] exp_ALUOp;
        input [1:0] exp_SignOp;
        input [200*8:1] test_name;
        begin
            #1; // Wait for combinational logic to settle
            if (Reg2Loc !== exp_Reg2Loc || ALUSrc !== exp_ALUSrc || 
                MemtoReg !== exp_MemtoReg || RegWrite !== exp_RegWrite ||
                MemRead !== exp_MemRead || MemWrite !== exp_MemWrite ||
                Branch !== exp_Branch || Uncondbranch !== exp_Uncondbranch ||
                ALUOp !== exp_ALUOp || SignOp !== exp_SignOp) begin
                
                $display("ERROR: Test %0d - %s (opcode=11'b%b)", test_num, test_name, test_opcode);
                $display("  Expected: Reg2Loc=%b ALUSrc=%b MemtoReg=%b RegWrite=%b MemRead=%b MemWrite=%b Branch=%b Uncondbranch=%b ALUOp=%b SignOp=%b",
                         exp_Reg2Loc, exp_ALUSrc, exp_MemtoReg, exp_RegWrite, exp_MemRead, 
                         exp_MemWrite, exp_Branch, exp_Uncondbranch, exp_ALUOp, exp_SignOp);
                $display("  Got:      Reg2Loc=%b ALUSrc=%b MemtoReg=%b RegWrite=%b MemRead=%b MemWrite=%b Branch=%b Uncondbranch=%b ALUOp=%b SignOp=%b",
                         Reg2Loc, ALUSrc, MemtoReg, RegWrite, MemRead, 
                         MemWrite, Branch, Uncondbranch, ALUOp, SignOp);
                errors = errors + 1;
            end else begin
                $display("PASS: Test %0d - %s", test_num, test_name);
            end
            test_num = test_num + 1;
        end
    endtask
    
    initial begin
        // Initialize
        test_num = 0;
        errors = 0;
        opcode = 11'b0;
        
        // Create VCD dump file
        $dumpfile("sc_control_tb.vcd");
        $dumpvars(0, SC_Control_tb);
        
        $display("Starting SC_Control testbench...");
        $display("=====================================");
        
        // Test R-type instructions
        $display("\nTesting R-type instructions:");
        
        // ADD Register
        opcode = 11'b10001011000;
        check_outputs(opcode, 0, 0, 0, 1, 0, 0, 0, 0, 4'b0010, 2'bxx, "ADD Register");
        
        // SUB Register
        opcode = 11'b11001011000;
        check_outputs(opcode, 0, 0, 0, 1, 0, 0, 0, 0, 4'b0110, 2'bxx, "SUB Register");
        
        // AND Register
        opcode = 11'b10001010000;
        check_outputs(opcode, 0, 0, 0, 1, 0, 0, 0, 0, 4'b0000, 2'bxx, "AND Register");
        
        // ORR Register
        opcode = 11'b10101010000;
        check_outputs(opcode, 0, 0, 0, 1, 0, 0, 0, 0, 4'b0001, 2'bxx, "ORR Register");
        
        // Test I-type instructions with don't care bits
        $display("\nTesting I-type instructions (ADDIMM):");
        
        // ADDIMM - test both possibilities for bit 0 (don't care)
        for (i = 0; i < 2; i = i + 1) begin
            opcode = 11'b10010001000 | i;
            check_outputs(opcode, 1'bx, 1, 0, 1, 0, 0, 0, 0, 4'b0010, 2'b00, "ADD Immediate");
        end

        // SUBIMM - test both possibilities for bit 0 (don't care)
        for (i = 0; i < 2; i = i + 1) begin
            opcode = 11'b11010001000 | i;
            check_outputs(opcode, 1'bx, 1, 0, 1, 0, 0, 0, 0, 4'b0110, 2'b00, "SUB Immediate");
        end

        // MOVZ - test all 4 possibilities for bits [1:0] (don't cares)
        for (i = 0; i < 4; i = i + 1) begin
            opcode = 11'b11010010100 | i;
            check_outputs(opcode, 1'bx, 1, 0, 1, 0, 0, 0, 0, 4'b0111, 2'b00, "MOVZ");
        end

        // B (Unconditional) - test all 32 possibilities for bits [4:0] (don't cares)
        for (i = 0; i < 32; i = i + 1) begin
            opcode = 11'b00010100000 | i;
            check_outputs(opcode, 1'bx, 1'bx, 1'bx, 0, 0, 0, 0, 1, 4'bxxxx, 2'b11, "B (Unconditional)");
        end

        // CBZ - test all 8 possibilities for bits [2:0] (don't cares)
        for (i = 0; i < 8; i = i + 1) begin
            opcode = 11'b10110100000 | i;
            check_outputs(opcode, 1, 0, 1'bx, 0, 0, 0, 1, 0, 4'b0111, 2'b10, "CBZ");
        end

        // LDUR
        opcode = 11'b11111000010;
        check_outputs(opcode, 1'bx, 1, 1, 1, 1, 0, 0, 0, 4'b0010, 2'b01, "LDUR");

        // STUR
        opcode = 11'b11111000000;
        check_outputs(opcode, 1, 1, 1'bx, 0, 0, 1, 0, 0, 4'b0010, 2'b01, "STUR");
        
        $display("\nTesting undefined opcodes (should output all zeros):");
        
        // Test 10 random undefined opcodes
        // Using specific random values that don't match any defined opcodes
        random_opcode = 11'b00000000000; opcode = random_opcode;
        check_outputs(opcode, 0, 0, 0, 0, 0, 0, 0, 0, 4'b0000, 2'b00, "Undefined opcode 1");
        
        random_opcode = 11'b11111111111; opcode = random_opcode;
        check_outputs(opcode, 0, 0, 0, 0, 0, 0, 0, 0, 4'b0000, 2'b00, "Undefined opcode 2");
        
        random_opcode = 11'b01010101010; opcode = random_opcode;
        check_outputs(opcode, 0, 0, 0, 0, 0, 0, 0, 0, 4'b0000, 2'b00, "Undefined opcode 3");
        
        random_opcode = 11'b10101010101; opcode = random_opcode;
        check_outputs(opcode, 0, 0, 0, 0, 0, 0, 0, 0, 4'b0000, 2'b00, "Undefined opcode 4");
        
        random_opcode = 11'b00110011001; opcode = random_opcode;
        check_outputs(opcode, 0, 0, 0, 0, 0, 0, 0, 0, 4'b0000, 2'b00, "Undefined opcode 5");
        
        random_opcode = 11'b11001100110; opcode = random_opcode;
        check_outputs(opcode, 0, 0, 0, 0, 0, 0, 0, 0, 4'b0000, 2'b00, "Undefined opcode 6");
        
        random_opcode = 11'b00011100011; opcode = random_opcode;
        check_outputs(opcode, 0, 0, 0, 0, 0, 0, 0, 0, 4'b0000, 2'b00, "Undefined opcode 7");
        
        random_opcode = 11'b11100011100; opcode = random_opcode;
        check_outputs(opcode, 0, 0, 0, 0, 0, 0, 0, 0, 4'b0000, 2'b00, "Undefined opcode 8");
        
        random_opcode = 11'b01111110000; opcode = random_opcode;
        check_outputs(opcode, 0, 0, 0, 0, 0, 0, 0, 0, 4'b0000, 2'b00, "Undefined opcode 9");
        
        random_opcode = 11'b10000001111; opcode = random_opcode;
        check_outputs(opcode, 0, 0, 0, 0, 0, 0, 0, 0, 4'b0000, 2'b00, "Undefined opcode 10");
        
        // Display summary
        $display("\n=====================================");
        $display("Test Summary:");
        $display("  Total tests: %0d", test_num);
        $display("  Passed: %0d", test_num - errors);
        $display("  Failed: %0d", errors);
        
        if (errors == 0) begin
            $display("\nALL TESTS PASSED!");
        end else begin
            $display("\nSOME TESTS FAILED!");
        end
        
        $display("=====================================");
        
        // Finish simulation
        #10;
        $finish;
    end


endmodule

Lab07/sc_control_tb.vcd
$date
	Tue Oct 28 18:25:19 2025
$end
$version
	Icarus Verilog
$end
$timescale
	1ps
$end
$scope module SC_Control_tb $end
$var wire 1 ! Uncondbranch $end
$var wire 2 " SignOp [1:0] $end
$var wire 1 # RegWrite $end
$var wire 1 $ Reg2Loc $end
$var wire 1 % MemtoReg $end
$var wire 1 & MemWrite $end
$var wire 1 ' MemRead $end
$var wire 1 ( Branch $end
$var wire 1 ) ALUSrc $end
$var wire 4 * ALUOp [3:0] $end
$var reg 11 + opcode [10:0] $end
$var reg 11 , random_opcode [10:0] $end
$var integer 32 - errors [31:0] $end
$var integer 32 . i [31:0] $end
$var integer 32 / test_num [31:0] $end
$scope module uut $end
$var wire 11 0 opcode [10:0] $end
$var reg 4 1 ALUOp [3:0] $end
$var reg 1 ) ALUSrc $end
$var reg 1 ( Branch $end
$var reg 1 ' MemRead $end
$var reg 1 & MemWrite $end
$var reg 1 % MemtoReg $end
$var reg 1 $ Reg2Loc $end
$var reg 1 # RegWrite $end
$var reg 2 2 SignOp [1:0] $end
$var reg 1 ! Uncondbranch $end
$upscope $end
$scope task check_outputs $end
$var reg 4 3 exp_ALUOp [3:0] $end
$var reg 1 4 exp_ALUSrc $end
$var reg 1 5 exp_Branch $end
$var reg 1 6 exp_MemRead $end
$var reg 1 7 exp_MemWrite $end
$var reg 1 8 exp_MemtoReg $end
$var reg 1 9 exp_Reg2Loc $end
$var reg 1 : exp_RegWrite $end
$var reg 2 ; exp_SignOp [1:0] $end
$var reg 1 < exp_Uncondbranch $end
$var reg 1600 = test_name [1600:1] $end
$var reg 11 > test_opcode [10:0] $end
$upscope $end
$upscope $end
$enddefinitions $end
#0
$dumpvars
b10001011000 >
b10000010100010001000100001000000101001001100101011001110110100101110011011101000110010101110010 =
0<
bx ;
1:
09
08
07
06
05
04
b10 3
bx 2
b10 1
b10001011000 0
b0 /
bx .
b0 -
bx ,
b10001011000 +
b10 *
0)
0(
0'
0&
0%
0$
1#
bx "
0!
$end
#1000
bx "
bx 2
b110 *
b110 1
1#
b10100110101010101000010001000000101001001100101011001110110100101110011011101000110010101110010 =
b110 3
b11001011000 >
b11001011000 +
b11001011000 0
b1 /
#2000
bx "
bx 2
b0 *
b0 1
1#
b10000010100111001000100001000000101001001100101011001110110100101110011011101000110010101110010 =
b0 3
b10001010000 >
b10001010000 +
b10001010000 0
b10 /
#3000
b1 *
b1 1
bx "
bx 2
1#
b10011110101001001010010001000000101001001100101011001110110100101110011011101000110010101110010 =
b1 3
b10101010000 >
b10101010000 +
b10101010000 0
b11 /
#4000
1)
x$
b0 "
b0 2
b10 *
b10 1
1#
b1000001010001000100010000100000010010010110110101101101011001010110010001101001011000010111010001100101 =
b0 ;
b10 3
14
x9
b10010001000 >
b10010001000 +
b10010001000 0
b0 .
b100 /
#5000
b10 *
b10 1
1#
1)
x$
b10010001001 >
b10010001001 +
b10010001001 0
b1 .
b101 /
#6000
b110 *
b110 1
1#
1)
x$
b1010011010101010100001000100000010010010110110101101101011001010110010001101001011000010111010001100101 =
b110 3
b11010001000 >
b11010001000 +
b11010001000 0
b0 .
b110 /
#7000
b110 *
b110 1
1#
1)
x$
b11010001001 >
b11010001001 +
b11010001001 0
b1 .
b111 /
#8000
b111 *
b111 1
1#
1)
x$
b1001101010011110101011001011010 =
b111 3
b11010010100 >
b11010010100 +
b11010010100 0
b0 .
b1000 /
#9000
b111 *
b111 1
1#
1)
x$
b11010010101 >
b11010010101 +
b11010010101 0
b1 .
b1001 /
#10000
b111 *
b111 1
1#
1)
x$
b11010010110 >
b11010010110 +
b11010010110 0
b10 .
b1010 /
#11000
b111 *
b111 1
1#
1)
x$
b11010010111 >
b11010010111 +
b11010010111 0
b11 .
b1011 /
#12000
b11 "
b11 2
1!
x%
bx *
bx 1
0#
x)
x$
b100001000100000001010000101010101101110011000110110111101101110011001000110100101110100011010010110111101101110011000010110110000101001 =
b11 ;
bx 3
1<
0:
x8
x4
b10100000 >
b10100000 +
b10100000 0
b0 .
b1100 /
#13000
b11 "
b11 2
bx *
bx 1
1!
x%
x)
x$
b10100001 >
b10100001 +
b10100001 0
b1 .
b1101 /
#14000
b11 "
b11 2
bx *
bx 1
1!
x%
x)
x$
b10100010 >
b10100010 +
b10100010 0
b10 .
b1110 /
#15000
b11 "
b11 2
bx *
bx 1
1!
x%
x)
x$
b10100011 >
b10100011 +
b10100011 0
b11 .
b1111 /
#16000
b11 "
b11 2
bx *
bx 1
1!
x%
x)
x$
b10100100 >
b10100100 +
b10100100 0
b100 .
b10000 /
#17000
b11 "
b11 2
bx *
bx 1
1!
x%
x)
x$
b10100101 >
b10100101 +
b10100101 0
b101 .
b10001 /
#18000
b11 "
b11 2
bx *
bx 1
1!
x%
x)
x$
b10100110 >
b10100110 +
b10100110 0
b110 .
b10010 /
#19000
b11 "
b11 2
bx *
bx 1
1!
x%
x)
x$
b10100111 >
b10100111 +
b10100111 0
b111 .
b10011 /
#20000
b11 "
b11 2
bx *
bx 1
1!
x%
x)
x$
b10101000 >
b10101000 +
b10101000 0
b1000 .
b10100 /
#21000
b11 "
b11 2
bx *
bx 1
1!
x%
x)
x$
b10101001 >
b10101001 +
b10101001 0
b1001 .
b10101 /
#22000
b11 "
b11 2
bx *
bx 1
1!
x%
x)
x$
b10101010 >
b10101010 +
b10101010 0
b1010 .
b10110 /
#23000
b11 "
b11 2
bx *
bx 1
1!
x%
x)
x$
b10101011 >
b10101011 +
b10101011 0
b1011 .
b10111 /
#24000
b11 "
b11 2
bx *
bx 1
1!
x%
x)
x$
b10101100 >
b10101100 +
b10101100 0
b1100 .
b11000 /
#25000
b11 "
b11 2
bx *
bx 1
1!
x%
x)
x$
b10101101 >
b10101101 +
b10101101 0
b1101 .
b11001 /
#26000
b11 "
b11 2
bx *
bx 1
1!
x%
x)
x$
b10101110 >
b10101110 +
b10101110 0
b1110 .
b11010 /
#27000
b11 "
b11 2
bx *
bx 1
1!
x%
x)
x$
b10101111 >
b10101111 +
b10101111 0
b1111 .
b11011 /
#28000
b11 "
b11 2
bx *
bx 1
1!
x%
x)
x$
b10110000 >
b10110000 +
b10110000 0
b10000 .
b11100 /
#29000
b11 "
b11 2
bx *
bx 1
1!
x%
x)
x$
b10110001 >
b10110001 +
b10110001 0
b10001 .
b11101 /
#30000
b11 "
b11 2
bx *
bx 1
1!
x%
x)
x$
b10110010 >
b10110010 +
b10110010 0
b10010 .
b11110 /
#31000
b11 "
b11 2
bx *
bx 1
1!
x%
x)
x$
b10110011 >
b10110011 +
b10110011 0
b10011 .
b11111 /
#32000
b11 "
b11 2
bx *
bx 1
1!
x%
x)
x$
b10110100 >
b10110100 +
b10110100 0
b10100 .
b100000 /
#33000
b11 "
b11 2
bx *
bx 1
1!
x%
x)
x$
b10110101 >
b10110101 +
b10110101 0
b10101 .
b100001 /
#34000
b11 "
b11 2
bx *
bx 1
1!
x%
x)
x$
b10110110 >
b10110110 +
b10110110 0
b10110 .
b100010 /
#35000
b11 "
b11 2
bx *
bx 1
1!
x%
x)
x$
b10110111 >
b10110111 +
b10110111 0
b10111 .
b100011 /
#36000
b11 "
b11 2
bx *
bx 1
1!
x%
x)
x$
b10111000 >
b10111000 +
b10111000 0
b11000 .
b100100 /
#37000
b11 "
b11 2
bx *
bx 1
1!
x%
x)
x$
b10111001 >
b10111001 +
b10111001 0
b11001 .
b100101 /
#38000
b11 "
b11 2
bx *
bx 1
1!
x%
x)
x$
b10111010 >
b10111010 +
b10111010 0
b11010 .
b100110 /
#39000
b11 "
b11 2
bx *
bx 1
1!
x%
x)
x$
b10111011 >
b10111011 +
b10111011 0
b11011 .
b100111 /
#40000
b11 "
b11 2
bx *
bx 1
1!
x%
x)
x$
b10111100 >
b10111100 +
b10111100 0
b11100 .
b101000 /
#41000
b11 "
b11 2
bx *
bx 1
1!
x%
x)
x$
b10111101 >
b10111101 +
b10111101 0
b11101 .
b101001 /
#42000
b11 "
b11 2
bx *
bx 1
1!
x%
x)
x$
b10111110 >
b10111110 +
b10111110 0
b11110 .
b101010 /
#43000
b11 "
b11 2
bx *
bx 1
1!
x%
x)
x$
b10111111 >
b10111111 +
b10111111 0
b11111 .
b101011 /
#44000
1(
b10 "
b10 2
b111 *
b111 1
0!
x%
0)
1$
b10000110100001001011010 =
b10 ;
b111 3
0<
15
04
19
b10110100000 >
b10110100000 +
b10110100000 0
b0 .
b101100 /
#45000
b10 "
b10 2
b111 *
b111 1
1(
x%
1$
b10110100001 >
b10110100001 +
b10110100001 0
b1 .
b101101 /
#46000
b10 "
b10 2
b111 *
b111 1
1(
x%
1$
b10110100010 >
b10110100010 +
b10110100010 0
b10 .
b101110 /
#47000
b10 "
b10 2
b111 *
b111 1
1(
x%
1$
b10110100011 >
b10110100011 +
b10110100011 0
b11 .
b101111 /
#48000
b10 "
b10 2
b111 *
b111 1
1(
x%
1$
b10110100100 >
b10110100100 +
b10110100100 0
b100 .
b110000 /
#49000
b10 "
b10 2
b111 *
b111 1
1(
x%
1$
b10110100101 >
b10110100101 +
b10110100101 0
b101 .
b110001 /
#50000
b10 "
b10 2
b111 *
b111 1
1(
x%
1$
b10110100110 >
b10110100110 +
b10110100110 0
b110 .
b110010 /
#51000
b10 "
b10 2
b111 *
b111 1
1(
x%
1$
b10110100111 >
b10110100111 +
b10110100111 0
b111 .
b110011 /
#52000
1'
1#
1)
b1 "
b1 2
b10 *
b10 1
0(
1%
x$
b1001100010001000101010101010010 =
b1 ;
b10 3
05
16
1:
18
14
x9
b11111000010 >
b11111000010 +
b11111000010 0
b1000 .
b110100 /
#53000
1&
b1 "
b1 2
b10 *
b10 1
0'
0#
x%
1)
1$
b1010011010101000101010101010010 =
17
06
0:
x8
19
b11111000000 >
b11111000000 +
b11111000000 0
b110101 /
#54000
b0 "
b0 2
b0 *
b0 1
0&
0%
0)
0$
b10101010110111001100100011001010110011001101001011011100110010101100100001000000110111101110000011000110110111101100100011001010010000000110001 =
b0 ;
b0 3
07
08
04
09
b0 >
b0 +
b0 0
b0 ,
b110110 /
#55000
b10101010110111001100100011001010110011001101001011011100110010101100100001000000110111101110000011000110110111101100100011001010010000000110010 =
b11111111111 >
b11111111111 +
b11111111111 0
b11111111111 ,
b110111 /
#56000
b10101010110111001100100011001010110011001101001011011100110010101100100001000000110111101110000011000110110111101100100011001010010000000110011 =
b1010101010 >
b1010101010 +
b1010101010 0
b1010101010 ,
b111000 /
#57000
b10101010110111001100100011001010110011001101001011011100110010101100100001000000110111101110000011000110110111101100100011001010010000000110100 =
b10101010101 >
b10101010101 +
b10101010101 0
b10101010101 ,
b111001 /
#58000
b10101010110111001100100011001010110011001101001011011100110010101100100001000000110111101110000011000110110111101100100011001010010000000110101 =
b110011001 >
b110011001 +
b110011001 0
b110011001 ,
b111010 /
#59000
b10101010110111001100100011001010110011001101001011011100110010101100100001000000110111101110000011000110110111101100100011001010010000000110110 =
b11001100110 >
b11001100110 +
b11001100110 0
b11001100110 ,
b111011 /
#60000
b10101010110111001100100011001010110011001101001011011100110010101100100001000000110111101110000011000110110111101100100011001010010000000110111 =
b11100011 >
b11100011 +
b11100011 0
b11100011 ,
b111100 /
#61000
b10101010110111001100100011001010110011001101001011011100110010101100100001000000110111101110000011000110110111101100100011001010010000000111000 =
b11100011100 >
b11100011100 +
b11100011100 0
b11100011100 ,
b111101 /
#62000
b10101010110111001100100011001010110011001101001011011100110010101100100001000000110111101110000011000110110111101100100011001010010000000111001 =
b1111110000 >
b1111110000 +
b1111110000 0
b1111110000 ,
b111110 /
#63000
b1010101011011100110010001100101011001100110100101101110011001010110010000100000011011110111000001100011011011110110010001100101001000000011000100110000 =
b10000001111 >
b10000001111 +
b10000001111 0
b10000001111 ,
b111111 /
#64000
b1000000 /
