Lab07/NextPClogic.v
// NextPC Logic Module for ARMv8 Processor
// Determines the next Program Counter value based on branch conditions

module NextPClogic(
    output reg [63:0] NextPC,
    input  [63:0] CurrentPC,
    input  [63:0] SignExtImm64,
    input         Branch,
    input         ALUZero,
    input         Uncondbranch
);

    always @(*) begin
        // Unconditional branch takes highest priority
        if (Uncondbranch) begin
            // For unconditional branch (B instruction)
            // NextPC = CurrentPC + SignExtImm64
            NextPC = CurrentPC + SignExtImm64;
        end
        // Conditional branch when both Branch and ALUZero are true
        else if (Branch && ALUZero) begin
            // For conditional branch taken (CBZ instruction when register is zero)
            // NextPC = CurrentPC + SignExtImm64
            NextPC = CurrentPC + SignExtImm64;
        end
        // Otherwise, proceed to next sequential instruction
        else begin
            // No branch: NextPC = CurrentPC + 4
            NextPC = CurrentPC + 4;
        end
    end
endmodule

Lab07/DataMemory.v
`timescale 1ns / 1ps

`define SIZE 1024

module DataMemory(ReadData , Address , WriteData , MemoryRead , MemoryWrite , Clock);
   input [63:0]      WriteData;
   input [63:0]      Address;
   input             Clock, MemoryRead, MemoryWrite;
   output reg [63:0] ReadData;

   reg [7:0] 	     memBank [`SIZE-1:0];


   // This task is used to write arbitrary data to the Data Memory by
   // the intialization block.
   task initset;
      input [63:0] addr;
      input [63:0] data;
      begin
	 memBank[addr] =  data[63:56] ; // Big-endian for the win...
	 memBank[addr+1] =  data[55:48];
	 memBank[addr+2] =  data[47:40];
	 memBank[addr+3] =  data[39:32];
	 memBank[addr+4] =  data[31:24];
	 memBank[addr+5] =  data[23:16];
	 memBank[addr+6] =  data[15:8];
	 memBank[addr+7] =  data[7:0];
      end
   endtask


   initial
     begin
        // preseting some data in the data memory used by test #1

        // Address 0x0 gets 0x1
        initset( 64'h0,  64'h1);  //Counter variable
        initset( 64'h8,  64'ha);  //Part of mask
        initset( 64'h10, 64'h5);  //Other part of mask
        initset( 64'h18, 64'h0ffbea7deadbeeff); //big constant
        initset( 64'h20, 64'h0); //clearing space

        // Add any data you need for your tests here.

     end

   // This always block reads the data memory and places a double word
   // on the ReadData bus.
   always @(*)
  begin
     if(MemoryRead)
       begin
          ReadData[63:56] = memBank[Address];
          ReadData[55:48] = memBank[Address+1];
          ReadData[47:40] = memBank[Address+2];
          ReadData[39:32] = memBank[Address+3];
          ReadData[31:24] = memBank[Address+4];
          ReadData[23:16] = memBank[Address+5];
          ReadData[15:8]  = memBank[Address+6];
          ReadData[7:0]   = memBank[Address+7];
       end
     else
       begin
          ReadData = 64'bx;
       end
  end

   // This always block takes data from the WriteData bus and writes
   // it into the DataMemory.
   always @(posedge Clock)
     begin
        if(MemoryWrite)
          begin
             memBank[Address] <= #3 WriteData[63:56] ;
             memBank[Address+1] <= #3 WriteData[55:48];
             memBank[Address+2] <= #3 WriteData[47:40];
             memBank[Address+3] <= #3 WriteData[39:32];
             memBank[Address+4] <= #3 WriteData[31:24];
             memBank[Address+5] <= #3 WriteData[23:16];
             memBank[Address+6] <= #3 WriteData[15:8];
             memBank[Address+7] <= #3 WriteData[7:0];
             // Could be useful for debugging:
             // $display("Writing Address:%h Data:%h",Address, WriteData);
          end
     end
endmodule

Lab07/ALU.v
// 64-bit Arithmetic Logic Unit (ALU) for ARMv8 Processor
// Supports AND, OR, ADD, SUB, and PassB operations

`define AND   4'b0000
`define OR    4'b0001
`define ADD   4'b0010
`define SUB   4'b0110
`define PassB 4'b0111

module ALU(
    output reg [63:0] BusW,
    input      [63:0] BusA,
    input      [63:0] BusB,
    input      [3:0]  ALUCtrl,
    output reg        Zero
);

    always @(*) begin
        case (ALUCtrl)
            `AND: begin
                // Bitwise AND operation
                BusW = BusA & BusB;
            end
            
            `OR: begin
                // Bitwise OR operation
                BusW = BusA | BusB;
            end
            
            `ADD: begin
                // Addition operation
                BusW = BusA + BusB;
            end
            
            `SUB: begin
                // Subtraction operation
                BusW = BusA - BusB;
            end
            
            `PassB: begin
                // Pass input B (used by CBZ)
                BusW = BusB;
            end
            
            default: begin
                // Default case to avoid latches. should never execute
                BusW = 64'b0;
            end
        endcase

        Zero = (BusW == 64'b0) ? 1'b1 : 1'b0;

    end

endmodule

Lab07/SignExtender.v
// Sign Extender Module for ARMv8 Processor
// Supports I-Type, D-Type, CB-Type, and B-Type instructions

`define Itype   2'b00
`define Dtype   2'b01
`define CBtype  2'b10
`define Btype   2'b11

module SignExtender(
    output reg [63:0] SignExOut,
    input      [25:0] Instruction,
    input      [1:0]  SignOp
);

    always @(*) begin
        case (SignOp)
            `Itype: begin
                // I-Type: 12-bit immediate in bits [21:10]
                SignExOut = {{52{Instruction[21]}}, Instruction[21:10]};
            end
            
            `Dtype: begin
                // D-Type: 9-bit immediate in bits [20:12]
                SignExOut = {{55{Instruction[20]}}, Instruction[20:12]};
            end
            
            `CBtype: begin
                // CB-Type: 19-bit immediate in bits [23:5]
                SignExOut = {{43{Instruction[23]}}, Instruction[23:5], 2'b00};
            end
            
            `Btype: begin
                // B-Type: 26-bit immediate in bits [25:0]
                SignExOut = {{36{Instruction[25]}}, Instruction[25:0], 2'b00};
            end
            
            default: begin
                SignExOut = 64'b0;
            end
        endcase
    end

endmodule

Lab05/RegisterFile.v
module RegisterFile(
    output wire [63:0] BusA, 
    output wire [63:0] BusB,
    input  wire [63:0] BusW,
    input  wire [4:0]  RA, 
    input  wire [4:0]  RB, 
    input  wire [4:0]  RW,
    input  wire        RegWr,
    input  wire        Clk
);
    // 32 registers of 64 bits. regs[31] will be treated as XZR (reads => 0, writes ignored).
    reg [63:0] regs [31:0];

    // Combinational read ports (blocking assignments as requested).
    reg [63:0] readA;
    reg [63:0] readB;

    always @(*) begin
        // If read address is 31 => XZR (zero). Otherwise return stored register.
        if (RA == 5'd31)
            readA = 64'd0;
        else
            readA = regs[RA];

        if (RB == 5'd31)
            readB = 64'd0;
        else
            readB = regs[RB];
    end

    // Synchronous write (non-blocking). Writes to XZR (reg 31) are dropped.
    always @(posedge Clk) begin
        if (RegWr && (RW != 5'd31)) begin
            regs[RW] <= BusW;
        end
    end

    // Outputs have a #3 simulation delay to prevent shoot-through in waveforms.
    // These delays are for simulation only; the rest of the RTL is synthesizable.
    assign BusA = readA;
    assign BusB = readB;
endmodule

Lab07/SingleCycleControl.v
`timescale 1ns / 1ps

`define OPCODE_ANDREG 11'b10001010000
`define OPCODE_ORRREG 11'b10101010000
`define OPCODE_ADDREG 11'b10001011000
`define OPCODE_SUBREG 11'b11001011000

`define OPCODE_ADDIMM 11'b1001000100?
`define OPCODE_SUBIMM 11'b1101000100?

`define OPCODE_MOVZ   11'b110100101??

`define OPCODE_B      11'b000101?????
`define OPCODE_CBZ    11'b10110100???

`define OPCODE_LDUR   11'b11111000010
`define OPCODE_STUR   11'b11111000000

module SC_Control(
               output reg       Reg2Loc,
               output reg       ALUSrc,
               output reg       MemtoReg,
               output reg       RegWrite,
               output reg       MemRead,
               output reg       MemWrite,
               output reg       Branch,
               output reg       Uncondbranch,
               output reg [3:0] ALUOp,
               output reg [1:0] SignOp,
               input [10:0]     opcode
               );

    always @(opcode) begin
        // Default values (all zeros for undefined opcodes)
        Reg2Loc = 1'b0;
        ALUSrc = 1'b0;
        MemtoReg = 1'b0;
        RegWrite = 1'b0;
        MemRead = 1'b0;
        MemWrite = 1'b0;
        Branch = 1'b0;
        Uncondbranch = 1'b0;
        ALUOp = 4'b0000;
        SignOp = 2'b00;
        
        casez(opcode)
            // R-type instructions (register-register operations)
            `OPCODE_ADDREG: begin
                Reg2Loc = 1'b0;
                ALUSrc = 1'b0;
                MemtoReg = 1'b0;
                RegWrite = 1'b1;
                MemRead = 1'b0;
                MemWrite = 1'b0;
                Branch = 1'b0;
                Uncondbranch = 1'b0;
                ALUOp = 4'b0010;
                SignOp = 2'bXX;
            end
            
            `OPCODE_SUBREG: begin
                Reg2Loc = 1'b0;
                ALUSrc = 1'b0;
                MemtoReg = 1'b0;
                RegWrite = 1'b1;
                MemRead = 1'b0;
                MemWrite = 1'b0;
                Branch = 1'b0;
                Uncondbranch = 1'b0;
                ALUOp = 4'b0110;
                SignOp = 2'bXX;
            end
            
            `OPCODE_ANDREG: begin
                Reg2Loc = 1'b0;
                ALUSrc = 1'b0;
                MemtoReg = 1'b0;
                RegWrite = 1'b1;
                MemRead = 1'b0;
                MemWrite = 1'b0;
                Branch = 1'b0;
                Uncondbranch = 1'b0;
                ALUOp = 4'b0000;
                SignOp = 2'bXX;
            end
            
            `OPCODE_ORRREG: begin
                Reg2Loc = 1'b0;
                ALUSrc = 1'b0;
                MemtoReg = 1'b0;
                RegWrite = 1'b1;
                MemRead = 1'b0;
                MemWrite = 1'b0;
                Branch = 1'b0;
                Uncondbranch = 1'b0;
                ALUOp = 4'b0001;
                SignOp = 2'bXX;
            end
            
            `OPCODE_ADDIMM: begin
                Reg2Loc = 1'bX;
                ALUSrc = 1'b1;
                MemtoReg = 1'b0;
                RegWrite = 1'b1;
                MemRead = 1'b0;
                MemWrite = 1'b0;
                Branch = 1'b0;
                Uncondbranch = 1'b0;
                ALUOp = 4'b0010;
                SignOp = 2'b00;
            end
            
            `OPCODE_SUBIMM: begin
                Reg2Loc = 1'bX;
                ALUSrc = 1'b1;
                MemtoReg = 1'b0;
                RegWrite = 1'b1;
                MemRead = 1'b0;
                MemWrite = 1'b0;
                Branch = 1'b0;
                Uncondbranch = 1'b0;
                ALUOp = 4'b0110;
                SignOp = 2'b00;
            end
            
            `OPCODE_MOVZ: begin
                Reg2Loc = 1'bX;
                ALUSrc = 1'b1;
                MemtoReg = 1'b0;
                RegWrite = 1'b1;
                MemRead = 1'b0;
                MemWrite = 1'b0;
                Branch = 1'b0;
                Uncondbranch = 1'b0;
                ALUOp = 4'b0111;
                SignOp = 2'b00;  //or 10?
            end
            
            `OPCODE_LDUR: begin
                Reg2Loc = 1'bX;
                ALUSrc = 1'b1;
                MemtoReg = 1'b1;
                RegWrite = 1'b1;
                MemRead = 1'b1;
                MemWrite = 1'b0;
                Branch = 1'b0;
                Uncondbranch = 1'b0;
                ALUOp = 4'b0010;
                SignOp = 2'b01;
            end
            
            `OPCODE_STUR: begin
                Reg2Loc = 1'b1;
                ALUSrc = 1'b1;
                MemtoReg = 1'bX;
                RegWrite = 1'b0;
                MemRead = 1'b0;
                MemWrite = 1'b1;
                Branch = 1'b0;
                Uncondbranch = 1'b0;
                ALUOp = 4'b0010;
                SignOp = 2'b01;
            end
            
            `OPCODE_B: begin
                Reg2Loc = 1'bX;
                ALUSrc = 1'bX;
                MemtoReg = 1'bX;
                RegWrite = 1'b0;
                MemRead = 1'b0;
                MemWrite = 1'b0;
                Branch = 1'b0;
                Uncondbranch = 1'b1;
                ALUOp = 4'bXXXX;
                SignOp = 2'b11;
            end
            
            `OPCODE_CBZ: begin
                Reg2Loc = 1'b1;
                ALUSrc = 1'b0;
                MemtoReg = 1'bX;
                RegWrite = 1'b0;
                MemRead = 1'b0;
                MemWrite = 1'b0;
                Branch = 1'b1;
                Uncondbranch = 1'b0;
                ALUOp = 4'b0111;
                SignOp = 2'b10;
            end
            
            default: begin
                Reg2Loc = 1'b0;
                ALUSrc = 1'b0;
                MemtoReg = 1'b0;
                RegWrite = 1'b0;
                MemRead = 1'b0;
                MemWrite = 1'b0;
                Branch = 1'b0;
                Uncondbranch = 1'b0;
                ALUOp = 4'b0000;
                SignOp = 2'b00;
            end
        endcase
    end

endmodule

Lab07/InstructionMemory.v
`timescale 1ns / 1ps
/*
 * Module: InstructionMemory
 *
 * Implements read-only instruction memory
 * 
 */
module InstructionMemory(Data, Address);
   parameter T_rd = 20;
   parameter MemSize = 40;
   
   output [31:0] Data;
   input [63:0]  Address;
   reg [31:0] 	 Data;
   
   /*
    * ECEN 350 Processor Test Functions
    * Texas A&M University
    */
   
   always @ (Address) begin

      case(Address)

	/* Test Program 1:
	 * Program loads constants from the data memory. Uses these constants to test
	 * the following instructions: LDUR, ORR, AND, CBZ, ADD, SUB, STUR and B.
	 * 
	 * Assembly code for test:
	 * 
	 * 0: LDUR X9, [XZR, 0x0]    //Load 1 into x9
	 * 4: LDUR X10, [XZR, 0x8]   //Load a into x10
	 * 8: LDUR X11, [XZR, 0x10]  //Load 5 into x11
	 * C: LDUR X12, [XZR, 0x18]  //Load big constant into x12
	 * 10: LDUR X13, [XZR, 0x20]  //load a 0 into X13
	 * 
	 * 14: ORR X10, X10, X11  //Create mask of 0xf
	 * 18: AND X12, X12, X10  //Mask off low order bits of big constant
	 * 
	 * loop:
	 * 1C: CBZ X12, end  //while X12 is not 0
	 * 20: ADD X13, X13, X9  //Increment counter in X13
	 * 24: SUB X12, X12, X9  //Decrement remainder of big constant in X12
	 * 28: B loop  //Repeat till X12 is 0
	 * 2C: STUR X13, [XZR, 0x20]  //store back the counter value into the memory location 0x20
	 */
	

	63'h000: Data = 32'hF84003E9;
	63'h004: Data = 32'hF84083EA;
	63'h008: Data = 32'hF84103EB;
	63'h00c: Data = 32'hF84183EC;
	63'h010: Data = 32'hF84203ED;
	63'h014: Data = 32'hAA0B014A;
	63'h018: Data = 32'h8A0A018C;
	63'h01c: Data = 32'hB400008C;
	63'h020: Data = 32'h8B0901AD;
	63'h024: Data = 32'hCB09018C;
	63'h028: Data = 32'h17FFFFFD;
	63'h02c: Data = 32'hF80203ED;
	63'h030: Data = 32'hF84203ED;  //One last load to place stored value on memdbus for test checking.

	/* Add code for your tests here 
	// Test Program 2: MOVZ test
	// Build 0x123456789abcdef0 in X9 using MOVZ and ORR

	MOVZ X9, 0xdef0, LSL 0   // X9 = 0x000000000000def0
	MOVZ X10, 0x9abc, LSL 16 // X10 = 0x0000000009abc0000
	ORR X9, X9, X10          // X9 = 0x0000000009abcdef0

	MOVZ X10, 0x5678, LSL 32 // X10 = 0x0000567800000000
	ORR X9, X9, X10          // X9 = 0x000056789abcdef0

	MOVZ X10, 0x1234, LSL 48 // X10 = 0x1234000000000000
	ORR X9, X9, X10          // X9 = 0x123456789abcdef0

	STUR X9, [XZR, 0x28]     // Store to address 0x28
	LDUR X10, [XZR, 0x28]    // Load back to X10
	*/
	63'h034: Data = 32'hD29BDE09;  // MOVZ X9, 0xdef0, LSL 0
	63'h038: Data = 32'hD2B3578A;  // MOVZ X10, 0x9abc, LSL 16
	63'h03c: Data = 32'hAA0A0129;  // ORR X9, X9, X10
	63'h040: Data = 32'hD2CACF0A;  // MOVZ X10, 0x5678, LSL 32
	63'h044: Data = 32'hAA0A0129;  // ORR X9, X9, X10
	63'h048: Data = 32'hD2E2468A;  // MOVZ X10, 0x1234, LSL 48
	63'h04c: Data = 32'hAA0A0129;  // ORR X9, X9, X10
	63'h050: Data = 32'hF80283E9;  // STUR X9, [XZR, 0x28]
	63'h054: Data = 32'hF84283EA;  // LDUR X10, [XZR, 0x28]
	
	default: Data = 32'hXXXXXXXX;
      endcase
   end
endmodule

Lab07/SingleCycleProc.v
`timescale 1ns / 1ps

module SingleCycleProc(
		   input	     reset, //Active High
		   input [63:0]	     startpc,
		   output reg [63:0] currentpc,
		   output [63:0]     MemtoRegOut, // this should be
						   // attached to the
						   // output of the
						   // MemtoReg Mux
		   input	     CLK
		   );

   // Next PC connections
   wire [63:0] 			     nextpc;       // The next PC, to be updated on clock cycle

   // Instruction Memory connections
   wire [31:0] 			     instruction;  // The current instruction

   // Parts of instruction
   wire [4:0] 			     rd;            // The destination register
   wire [4:0] 			     rm;            // Operand 1
   wire [4:0] 			     rn;            // Operand 2
   wire [10:0] 			     opcode;

   // Control wires
   wire 			     Reg2Loc;
   wire 			     ALUSrc;
   wire 			     MemtoReg;
   wire 			     RegWrite;
   wire 			     MemRead;
   wire 			     MemWrite;
   wire 			     Branch;
   wire 			     Uncondbranch;
   wire [3:0] 			     ALUOp;
   wire [1:0] 			     SignOp;

   // Register file connections
   wire [63:0] 			     regoutA;     // Output A
   wire [63:0] 			     regoutB;     // Output B

   // ALU connections
   wire [63:0] 			     aluout;
   wire 			     zero;

   // Sign Extender connections
   wire [63:0] 			     extimm;

   // Data Memory connections
   wire [63:0] 			     dmemout;     // Data memory output

   // Additional mux wires
   wire [63:0] 			     aluinputB;   // Second ALU input (from mux)

   // PC update logic
   always @(posedge CLK)
     begin
        if (reset)
          currentpc <= startpc;
        else
          currentpc <= nextpc;
     end

   // Parts of instruction
   assign rd = instruction[4:0];
   assign rm = instruction[9:5];
   assign rn = Reg2Loc ? instruction[4:0] : instruction[20:16];
   assign opcode = instruction[31:21];

   InstructionMemory imem(
			  .Data(instruction),
			  .Address(currentpc)
			  );

   SC_Control control(
		   .Reg2Loc(Reg2Loc),
		   .ALUSrc(ALUSrc),
		   .MemtoReg(MemtoReg),
		   .RegWrite(RegWrite),
		   .MemRead(MemRead),
		   .MemWrite(MemWrite),
		   .Branch(Branch),
		   .Uncondbranch(Uncondbranch),
		   .ALUOp(ALUOp),
		   .SignOp(SignOp),
		   .opcode(opcode)
		   );

   /*
    * Connect the remaining datapath elements below.
    * Do not forget any additional multiplexers that may be required.
    */

   // Register File
   RegisterFile regfile(
			.BusA(regoutA),
			.BusB(regoutB),
			.BusW(MemtoRegOut),
			.RA(rm),
			.RB(rn),
			.RW(rd),
			.RegWr(RegWrite),
			.Clk(CLK)
			);

   // Sign Extender
   SignExtender signext(
			.SignExOut(extimm),
			.Instruction(instruction),
			.SignOp(SignOp)
			);

   // ALU Input B Mux (selects between register or immediate)
   assign aluinputB = ALUSrc ? extimm : regoutB;

   // ALU
   ALU alu(
	   .BusW(aluout),
	   .BusA(regoutA),
	   .BusB(aluinputB),
	   .ALUCtrl(ALUOp),
	   .Zero(zero)
	   );

   // Data Memory
   DataMemory dmem(
		   .ReadData(dmemout),
		   .Address(aluout),
		   .WriteData(regoutB),
		   .MemoryRead(MemRead),
		   .MemoryWrite(MemWrite),
		   .Clock(CLK)
		   );

   // MemtoReg Mux (selects between ALU result or memory data)
   assign MemtoRegOut = MemtoReg ? dmemout : aluout;

   // Next PC Logic
   NextPClogic pclogic(
		       .NextPC(nextpc),
		       .CurrentPC(currentpc),
		       .SignExtImm64(extimm),
		       .Branch(Branch),
		       .ALUZero(zero),
		       .Uncondbranch(Uncondbranch)
		       );

endmodule

Lab07/SingleCycleProcTest.v
`timescale 1ns / 1ps

`define STRLEN 32
`define HalfClockPeriod 60
`define ClockPeriod `HalfClockPeriod * 2

module SingleCycleProcTest_v;

   initial
     begin
        $dumpfile("singlecycle.vcd");
        $dumpvars;
     end

   // These tasks are used to check if a given test has passed and
   // confirm that all tests passed.
   task passTest;
      input [63:0] actualOut, expectedOut;
      input [`STRLEN*8:0] testType;
      inout [7:0] 	  passed;

      if(actualOut == expectedOut) begin $display ("%s passed", testType); passed = passed + 1; end
      else $display ("%s failed: 0x%x should be 0x%x", testType, actualOut, expectedOut);
   endtask

   task allPassed;
      input [7:0] passed;
      input [7:0] numTests;

      if(passed == numTests) $display ("All tests passed");
      else $display("Some tests failed: %d of %d passed", passed, numTests);
   endtask

   // Inputs
   reg 		  CLK;
   reg		  Reset;
   reg [63:0] 	  startPC;
   reg [7:0] 	  passed;
   reg [15:0] 	  watchdog;

   // Outputs
   wire [63:0] 	  MemtoRegOut;
   wire [63:0] 	  currentPC;

   // Instantiate the Unit Under Test (UUT)
   SingleCycleProc uut (
		    .CLK(CLK),
		    .reset(Reset),
		    .startpc(startPC),
		    .currentpc(currentPC),
		    .MemtoRegOut(MemtoRegOut)
		    );

   initial begin
      // Initialize Inputs
      Reset = 0;
      startPC = 0;
      passed = 0;

      // Initialize Watchdog timer
      watchdog = 0;

      // Wait for global reset
      #(1 * `ClockPeriod);

      // Program 1
      #1
        Reset = 1; startPC = 0;
      @(posedge CLK);
      @(negedge CLK);
      @(posedge CLK);
      Reset = 0;

      // ***********************************************************
      // This while loop will continue cycling the processor until the
      // PC reaches the final instruction in the first test.  If the
      // program forms an infinite loop, never reaching the end, the
      // watchdog timer will kick in and kill simulation after 64K
      // cycles.
      // ***********************************************************

      while (currentPC < 64'h30)
        begin
	   @(posedge CLK);
	   @(negedge CLK);
           $display("CurrentPC:%h",currentPC);
        end
      passTest(MemtoRegOut, 64'hF, "Results of Program 1", passed);

      // ***********************************************************
      // Add your new tests here
      // ***********************************************************
      //Program 2
      

      // Done
      allPassed(passed, 2);   // Be sure to change the one to match
      // the number of tests you add.
      $finish;
   end

   // Initialize the clock to be 0
   initial begin
      CLK = 0;
   end

   // The following is correct if clock starts at LOW level at StartTime //
   always begin
      #`HalfClockPeriod CLK = ~CLK;
      #`HalfClockPeriod CLK = ~CLK;
      watchdog = watchdog +1;
   end

   // Kill the simulation if the watchdog hits 64K cycles
   always @*
     if (watchdog == 16'hFF)
       begin
          $display("Watchdog Timer Expired.");
          $finish;
       end


endmodule

Lab07/singlecycle.vcd
$date
	Thu Oct 23 16:53:50 2025
$end
$version
	Icarus Verilog
$end
$timescale
	1ps
$end
$scope module SingleCycleProcTest_v $end
$var wire 64 ! currentPC [63:0] $end
$var wire 64 " MemtoRegOut [63:0] $end
$var reg 1 # CLK $end
$var reg 1 $ Reset $end
$var reg 8 % passed [7:0] $end
$var reg 64 & startPC [63:0] $end
$var reg 16 ' watchdog [15:0] $end
$scope module uut $end
$var wire 1 # CLK $end
$var wire 1 $ reset $end
$var wire 64 ( startpc [63:0] $end
$var wire 1 ) zero $end
$var wire 5 * rn [4:0] $end
$var wire 5 + rm [4:0] $end
$var wire 64 , regoutB [63:0] $end
$var wire 64 - regoutA [63:0] $end
$var wire 5 . rd [4:0] $end
$var wire 11 / opcode [10:0] $end
$var wire 64 0 nextpc [63:0] $end
$var wire 32 1 instruction [31:0] $end
$var wire 64 2 extimm [63:0] $end
$var wire 64 3 dmemout [63:0] $end
$var wire 64 4 aluout [63:0] $end
$var wire 64 5 aluinputB [63:0] $end
$var wire 1 6 Uncondbranch $end
$var wire 2 7 SignOp [1:0] $end
$var wire 1 8 RegWrite $end
$var wire 1 9 Reg2Loc $end
$var wire 64 : MemtoRegOut [63:0] $end
$var wire 1 ; MemtoReg $end
$var wire 1 < MemWrite $end
$var wire 1 = MemRead $end
$var wire 1 > Branch $end
$var wire 1 ? ALUSrc $end
$var wire 4 @ ALUOp [3:0] $end
$var reg 64 A currentpc [63:0] $end
$scope module alu $end
$var wire 64 B BusB [63:0] $end
$var wire 64 C BusA [63:0] $end
$var wire 4 D ALUCtrl [3:0] $end
$var reg 64 E BusW [63:0] $end
$var reg 1 ) Zero $end
$upscope $end
$scope module control $end
$var wire 11 F opcode [10:0] $end
$var reg 4 G ALUOp [3:0] $end
$var reg 1 ? ALUSrc $end
$var reg 1 > Branch $end
$var reg 1 = MemRead $end
$var reg 1 < MemWrite $end
$var reg 1 ; MemtoReg $end
$var reg 1 9 Reg2Loc $end
$var reg 1 8 RegWrite $end
$var reg 2 H SignOp [1:0] $end
$var reg 1 6 Uncondbranch $end
$upscope $end
$scope module dmem $end
$var wire 64 I Address [63:0] $end
$var wire 1 # Clock $end
$var wire 1 = MemoryRead $end
$var wire 1 < MemoryWrite $end
$var wire 64 J WriteData [63:0] $end
$var reg 64 K ReadData [63:0] $end
$scope task initset $end
$var reg 64 L addr [63:0] $end
$var reg 64 M data [63:0] $end
$upscope $end
$upscope $end
$scope module imem $end
$var wire 64 N Address [63:0] $end
$var reg 32 O Data [31:0] $end
$upscope $end
$scope module pclogic $end
$var wire 1 ) ALUZero $end
$var wire 1 > Branch $end
$var wire 64 P CurrentPC [63:0] $end
$var wire 1 6 Uncondbranch $end
$var wire 64 Q SignExtImm64 [63:0] $end
$var reg 64 R NextPC [63:0] $end
$upscope $end
$scope module regfile $end
$var wire 64 S BusA [63:0] $end
$var wire 64 T BusW [63:0] $end
$var wire 1 # Clk $end
$var wire 5 U RA [4:0] $end
$var wire 5 V RB [4:0] $end
$var wire 5 W RW [4:0] $end
$var wire 1 8 RegWr $end
$var wire 64 X BusB [63:0] $end
$var reg 64 Y readA [63:0] $end
$var reg 64 Z readB [63:0] $end
$upscope $end
$scope module signext $end
$var wire 26 [ Instruction [25:0] $end
$var wire 2 \ SignOp [1:0] $end
$var reg 64 ] SignExOut [63:0] $end
$upscope $end
$upscope $end
$scope task allPassed $end
$var reg 8 ^ numTests [7:0] $end
$var reg 8 _ passed [7:0] $end
$upscope $end
$scope task passTest $end
$var reg 64 ` actualOut [63:0] $end
$var reg 64 a expectedOut [63:0] $end
$var reg 8 b passed [7:0] $end
$var reg 257 c testType [256:0] $end
$upscope $end
$upscope $end
$enddefinitions $end
#0
$dumpvars
bx c
bx b
bx a
bx `
bx _
bx ^
bx ]
bx \
bx [
bx Z
bx Y
bx X
bx W
bx V
bx U
bx T
bx S
bx R
bx Q
bx P
bx O
bx N
b0 M
b100000 L
bx K
bx J
bx I
bx H
bx G
bx F
bx E
bx D
bx C
bx B
bx A
bx @
x?
x>
x=
x<
x;
bx :
x9
x8
bx 7
x6
bx 5
bx 4
bx 3
bx 2
bx 1
bx 0
bx /
bx .
bx -
bx ,
bx +
bx *
x)
b0 (
b0 '
b0 &
b0 %
0$
0#
bx "
bx !
$end
#60000
1#
#120000
b1 '
0#
#121000
1$
#180000
b1 "
b1 :
b1 T
b1 3
b1 K
1)
b0 4
b0 E
b0 I
b0 5
b0 B
b0 2
b0 Q
b0 ]
b1 7
b1 H
b1 \
b10 @
b10 D
b10 G
06
0>
0<
1=
18
1;
1?
x9
b0x00x *
b0x00x V
b0 -
b0 C
b0 S
b0 Y
b10000000000001111101001 [
b11111000010 /
b11111000010 F
b11111 +
b11111 U
b1001 .
b1001 W
b11111000010000000000001111101001 1
b11111000010000000000001111101001 O
b100 0
b100 R
b0 !
b0 A
b0 N
b0 P
1#
#240000
b10 '
0#
#300000
b1010 "
b1010 :
b1010 T
b1010 3
b1010 K
0)
b1000 4
b1000 E
b1000 I
b1000 5
b1000 B
b1000 2
b1000 Q
b1000 ]
b0x0x0 *
b0x0x0 V
b10000001000001111101010 [
b1010 .
b1010 W
b11111000010000001000001111101010 1
b11111000010000001000001111101010 O
b1000 0
b1000 R
b100 !
b100 A
b100 N
b100 P
0$
1#
#360000
b11 '
0#
#420000
b101 "
b101 :
b101 T
b101 3
b101 K
b10000 4
b10000 E
b10000 I
b10000 5
b10000 B
b10000 2
b10000 Q
b10000 ]
b0x0x1 *
b0x0x1 V
b10000010000001111101011 [
b1011 .
b1011 W
b11111000010000010000001111101011 1
b11111000010000010000001111101011 O
b1100 0
b1100 R
b1000 !
b1000 A
b1000 N
b1000 P
1#
#480000
b100 '
0#
#540000
b111111111011111010100111110111101010110110111110111011111111 "
b111111111011111010100111110111101010110110111110111011111111 :
b111111111011111010100111110111101010110110111110111011111111 T
b111111111011111010100111110111101010110110111110111011111111 3
b111111111011111010100111110111101010110110111110111011111111 K
b11000 4
b11000 E
b11000 I
b11000 5
b11000 B
b11000 2
b11000 Q
b11000 ]
b0xx0x *
b0xx0x V
b10000011000001111101100 [
b1100 .
b1100 W
b11111000010000011000001111101100 1
b11111000010000011000001111101100 O
b10000 0
b10000 R
b1100 !
b1100 A
b1100 N
b1100 P
1#
#600000
b101 '
0#
#660000
b0 "
b0 :
b0 T
b0 3
b0 K
b100000 4
b100000 E
b100000 I
b100000 5
b100000 B
b100000 2
b100000 Q
b100000 ]
b0xxxx *
b0xxxx V
b10000100000001111101101 [
b1101 .
b1101 W
b11111000010000100000001111101101 1
b11111000010000100000001111101101 O
b10100 0
b10100 R
b10000 !
b10000 A
b10000 N
b10000 P
1#
#720000
b110 '
0#
#780000
b101 ,
b101 J
b101 X
b101 Z
bx 3
bx K
b1111 "
b1111 :
b1111 T
b101 5
b101 B
b1111 4
b1111 E
b1111 I
b0 2
b0 Q
b0 ]
bx 7
bx H
bx \
b1 @
b1 D
b1 G
0=
18
0;
0?
09
b1011 *
b1011 V
b1010 -
b1010 C
b1010 S
b1010 Y
b10000010110000000101001010 [
b10101010000 /
b10101010000 F
b1010 +
b1010 U
b1010 .
b1010 W
b10101010000010110000000101001010 1
b10101010000010110000000101001010 O
b11000 0
b11000 R
b10100 !
b10100 A
b10100 N
b10100 P
1#
#840000
b111 '
0#
#900000
b1111 5
b1111 B
b1111 "
b1111 :
b1111 T
b1111 ,
b1111 J
b1111 X
b1111 Z
b1111 4
b1111 E
b1111 I
bx 7
bx H
bx \
b0 @
b0 D
b0 G
18
b1010 *
b1010 V
b10000010100000000110001100 [
b10001010000 /
b10001010000 F
b1100 +
b1100 U
b1100 .
b1100 W
b10001010000010100000000110001100 1
b10001010000010100000000110001100 O
b11100 0
b11100 R
b111111111011111010100111110111101010110110111110111011111111 -
b111111111011111010100111110111101010110110111110111011111111 C
b111111111011111010100111110111101010110110111110111011111111 S
b111111111011111010100111110111101010110110111110111011111111 Y
b11000 !
b11000 A
b11000 N
b11000 P
1#
#960000
b1000 '
0#
#1020000
0)
b1111 4
b1111 E
b1111 I
b1111 5
b1111 B
bx "
bx :
bx T
b1111 ,
b1111 J
b1111 X
b1111 Z
b10000 2
b10000 Q
b10000 ]
b111 @
b111 D
b111 G
1>
x;
19
b10 7
b10 H
b10 \
08
b1100 *
b1100 V
b10001100 [
b10110100000 /
b10110100000 F
b100 +
b100 U
bx -
bx C
bx S
bx Y
b10110100000000000000000010001100 1
b10110100000000000000000010001100 O
b100000 0
b100000 R
b11100 !
b11100 A
b11100 N
b11100 P
1#
#1080000
b1001 '
0#
