Lab05/RegisterFile.v
module RegisterFile(
    output wire [63:0] BusA, 
    output wire [63:0] BusB,
    input  wire [63:0] BusW,
    input  wire [4:0]  RA, 
    input  wire [4:0]  RB, 
    input  wire [4:0]  RW,
    input  wire        RegWr,
    input  wire        Clk
);
    // 32 registers of 64 bits. regs[31] will be treated as XZR (reads => 0, writes ignored).
    reg [63:0] regs [31:0];

    // Combinational read ports (blocking assignments as requested).
    reg [63:0] readA;
    reg [63:0] readB;

    always @(*) begin
        // If read address is 31 => XZR (zero). Otherwise return stored register.
        if (RA == 5'd31)
            readA = 64'd0;
        else
            readA = regs[RA];

        if (RB == 5'd31)
            readB = 64'd0;
        else
            readB = regs[RB];
    end

    // Synchronous write (non-blocking). Writes to XZR (reg 31) are dropped.
    always @(posedge Clk) begin
        if (RegWr && (RW != 5'd31)) begin
            regs[RW] <= BusW;
        end
    end

    // Outputs have a #3 simulation delay to prevent shoot-through in waveforms.
    // These delays are for simulation only; the rest of the RTL is synthesizable.
    assign BusA = readA;
    assign BusB = readB;
endmodule

Lab05/RegisterFile_tb.v
`timescale 1ns/1ps

module tb_RegisterFile;

    // DUT interface signals
    reg  [63:0] BusW;
    reg  [4:0]  RA, RB, RW;
    reg         RegWr;
    reg         Clk;
    wire [63:0] BusA, BusB;


    // Instantiate the DUT
    RegisterFile dut (
        .BusA(BusA),
        .BusB(BusB),
        .BusW(BusW),
        .RA(RA),
        .RB(RB),
        .RW(RW),
        .RegWr(RegWr),
        .Clk(Clk)
    );


    // Golden model: stores expected register contents
    reg [63:0] golden [31:0];


    // Clock generator
    initial begin
        Clk = 0;
        forever #5 Clk = ~Clk;  // 10 ns period
    end

    initial begin
        $dumpfile("RegisterFile_tb.vcd");  // waveform file
        $dumpvars(0, tb_RegisterFile);     // dump all signals in this testbench
    end


    integer r;
    reg [63:0] rand_val;


    initial begin
        // Initialize golden registers
        for (r = 0; r < 32; r = r + 1)
            golden[r] = 64'd0;


        // Test with write enable ON
        $display("---- Testing with RegWr = 1 ----");
        RegWr = 1;
        for (r = 0; r < 32; r = r + 1) begin
            rand_val = $random;  // random 32-bit signed value
            rand_val = {rand_val, $random}; // make it 64-bit


            RW = r;
            BusW = rand_val;
            @(posedge Clk);  // perform write


            // Update golden model unless RW == 31
            if (r != 31) golden[r] = rand_val;


            // Read back via BusA
            RA = r;
            #10;  // allow #3 delay on BusA
            if (BusA !== golden[r]) begin
                $display("ERROR: Write enabled, Reg[%0d] expected %h, got %h", 
                         r, golden[r], BusA);
                $stop;
            end
        end


        // Test with write enable OFF
        $display("---- Testing with RegWr = 0 ----");
        RegWr = 0;
        for (r = 0; r < 32; r = r + 1) begin
            rand_val = {$random, $random}; // another random 64-bit value


            RW = r;
            BusW = rand_val;
            @(posedge Clk);  // attempt write, should not change regs

            // Read back via BusB
            RB = r;
            #10;  // allow #3 delay on BusB
            if (BusB !== golden[r]) begin
                $display("ERROR: Write disabled, Reg[%0d] expected %h, got %h", 
                         r, golden[r], BusB);
                $stop;
            end
        end

        $display("All randomized tests PASSED!");
        $finish;
    end

endmodule

Lab05/RegisterFile_tb.vcd
$date
	Tue Sep 30 18:58:00 2025
$end
$version
	Icarus Verilog
$end
$timescale
	1ps
$end
$scope module tb_RegisterFile $end
$var wire 64 ! BusB [63:0] $end
$var wire 64 " BusA [63:0] $end
$var reg 64 # BusW [63:0] $end
$var reg 1 $ Clk $end
$var reg 5 % RA [4:0] $end
$var reg 5 & RB [4:0] $end
$var reg 5 ' RW [4:0] $end
$var reg 1 ( RegWr $end
$var reg 64 ) rand_val [63:0] $end
$var integer 32 * r [31:0] $end
$scope module dut $end
$var wire 64 + BusA [63:0] $end
$var wire 64 , BusB [63:0] $end
$var wire 64 - BusW [63:0] $end
$var wire 1 $ Clk $end
$var wire 5 . RA [4:0] $end
$var wire 5 / RB [4:0] $end
$var wire 5 0 RW [4:0] $end
$var wire 1 ( RegWr $end
$var reg 64 1 readA [63:0] $end
$var reg 64 2 readB [63:0] $end
$upscope $end
$upscope $end
$enddefinitions $end
#0
$dumpvars
bx 2
bx 1
b0 0
bx /
bx .
b1001000010101001101010010010011000000100010010101111010000001 -
bx ,
bx +
b0 *
b1001000010101001101010010010011000000100010010101111010000001 )
1(
b0 '
bx &
bx %
0$
b1001000010101001101010010010011000000100010010101111010000001 #
bx "
bx !
$end
#5000
b1001000010101001101010010010011000000100010010101111010000001 "
b1001000010101001101010010010011000000100010010101111010000001 +
b1001000010101001101010010010011000000100010010101111010000001 1
b0 %
b0 .
1$
#10000
0$
#15000
b1000010010000100110101100000100110110001111100000101011001100011 "
b1000010010000100110101100000100110110001111100000101011001100011 +
b1000010010000100110101100000100110110001111100000101011001100011 1
b1 %
b1 .
1$
b1000010010000100110101100000100110110001111100000101011001100011 #
b1000010010000100110101100000100110110001111100000101011001100011 -
b1 '
b1 0
b1000010010000100110101100000100110110001111100000101011001100011 )
b1 *
#20000
0$
#25000
b11010111001011110110000110101000110110111111001100110001101 "
b11010111001011110110000110101000110110111111001100110001101 +
b11010111001011110110000110101000110110111111001100110001101 1
b10 %
b10 .
1$
b11010111001011110110000110101000110110111111001100110001101 #
b11010111001011110110000110101000110110111111001100110001101 -
b10 '
b10 0
b11010111001011110110000110101000110110111111001100110001101 )
b10 *
#30000
0$
#35000
b1011001011000010100001000110010110001001001101110101001000010010 "
b1011001011000010100001000110010110001001001101110101001000010010 +
b1011001011000010100001000110010110001001001101110101001000010010 1
b11 %
b11 .
1$
b1011001011000010100001000110010110001001001101110101001000010010 #
b1011001011000010100001000110010110001001001101110101001000010010 -
b11 '
b11 0
b1011001011000010100001000110010110001001001101110101001000010010 )
b11 *
#40000
0$
#45000
b11110011111000110000000100000110110101111100110100001101 "
b11110011111000110000000100000110110101111100110100001101 +
b11110011111000110000000100000110110101111100110100001101 1
b100 %
b100 .
1$
b11110011111000110000000100000110110101111100110100001101 #
b11110011111000110000000100000110110101111100110100001101 -
b100 '
b100 0
b11110011111000110000000100000110110101111100110100001101 )
b100 *
#50000
0$
#55000
b11101100100011111100010111011000011110100011011100110100111101 "
b11101100100011111100010111011000011110100011011100110100111101 +
b11101100100011111100010111011000011110100011011100110100111101 1
b101 %
b101 .
1$
b11101100100011111100010111011000011110100011011100110100111101 #
b11101100100011111100010111011000011110100011011100110100111101 -
b101 '
b101 0
b11101100100011111100010111011000011110100011011100110100111101 )
b101 *
#60000
0$
#65000
b111011011010100010101111110110101000110001011011111011110001100 "
b111011011010100010101111110110101000110001011011111011110001100 +
b111011011010100010101111110110101000110001011011111011110001100 1
b110 %
b110 .
1$
b111011011010100010101111110110101000110001011011111011110001100 #
b111011011010100010101111110110101000110001011011111011110001100 -
b110 '
b110 0
b111011011010100010101111110110101000110001011011111011110001100 )
b110 *
#70000
0$
#75000
b111110011111101111010011111100111100011001101110010010011000110 "
b111110011111101111010011111100111100011001101110010010011000110 +
b111110011111101111010011111100111100011001101110010010011000110 1
b111 %
b111 .
1$
b111110011111101111010011111100111100011001101110010010011000110 #
b111110011111101111010011111100111100011001101110010010011000110 -
b111 '
b111 0
b111110011111101111010011111100111100011001101110010010011000110 )
b111 *
#80000
0$
#85000
b1110001011110111100001001100010111010101000100111101001010101010 "
b1110001011110111100001001100010111010101000100111101001010101010 +
b1110001011110111100001001100010111010101000100111101001010101010 1
b1000 %
b1000 .
1$
b1110001011110111100001001100010111010101000100111101001010101010 #
b1110001011110111100001001100010111010101000100111101001010101010 -
b1000 '
b1000 0
b1110001011110111100001001100010111010101000100111101001010101010 )
b1000 *
#90000
0$
#95000
b111001010101111111101111110010110111011110100100111001001110111 "
b111001010101111111101111110010110111011110100100111001001110111 +
b111001010101111111101111110010110111011110100100111001001110111 1
b1001 %
b1001 .
1$
b111001010101111111101111110010110111011110100100111001001110111 #
b111001010101111111101111110010110111011110100100111001001110111 -
b1001 '
b1001 0
b111001010101111111101111110010110111011110100100111001001110111 )
b1001 *
#100000
0$
#105000
b1000100100110010110101100001001001000111111011001101101110001111 "
b1000100100110010110101100001001001000111111011001101101110001111 +
b1000100100110010110101100001001001000111111011001101101110001111 1
b1010 %
b1010 .
1$
b1000100100110010110101100001001001000111111011001101101110001111 #
b1000100100110010110101100001001001000111111011001101101110001111 -
b1010 '
b1010 0
b1000100100110010110101100001001001000111111011001101101110001111 )
b1010 *
#110000
0$
#115000
b111100100110000011010011111001011100111011101101001011011001110 "
b111100100110000011010011111001011100111011101101001011011001110 +
b111100100110000011010011111001011100111011101101001011011001110 1
b1011 %
b1011 .
1$
b111100100110000011010011111001011100111011101101001011011001110 #
b111100100110000011010011111001011100111011101101001011011001110 -
b1011 '
b1011 0
b111100100110000011010011111001011100111011101101001011011001110 )
b1011 *
#120000
0$
#125000
b1111010000000000011110101110100011100010110010100100111011000101 "
b1111010000000000011110101110100011100010110010100100111011000101 +
b1111010000000000011110101110100011100010110010100100111011000101 1
b1100 %
b1100 .
1$
b1111010000000000011110101110100011100010110010100100111011000101 #
b1111010000000000011110101110100011100010110010100100111011000101 -
b1100 '
b1100 0
b1111010000000000011110101110100011100010110010100100111011000101 )
b1100 *
#130000
0$
#135000
b10111001011000010010010101110011011110100011100010100010111101 "
b10111001011000010010010101110011011110100011100010100010111101 +
b10111001011000010010010101110011011110100011100010100010111101 1
b1101 %
b1101 .
1$
b10111001011000010010010101110011011110100011100010100010111101 #
b10111001011000010010010101110011011110100011100010100010111101 -
b1101 '
b1101 0
b10111001011000010010010101110011011110100011100010100010111101 )
b1101 *
#140000
0$
#145000
b1001011010101011010110000010110110110010101001110010011001100101 "
b1001011010101011010110000010110110110010101001110010011001100101 +
b1001011010101011010110000010110110110010101001110010011001100101 1
b1110 %
b1110 .
1$
b1001011010101011010110000010110110110010101001110010011001100101 #
b1001011010101011010110000010110110110010101001110010011001100101 -
b1110 '
b1110 0
b1001011010101011010110000010110110110010101001110010011001100101 )
b1110 *
#150000
0$
#155000
b1011000111101111011000100110001100000101011100111000011100001010 "
b1011000111101111011000100110001100000101011100111000011100001010 +
b1011000111101111011000100110001100000101011100111000011100001010 1
b1111 %
b1111 .
1$
b1011000111101111011000100110001100000101011100111000011100001010 #
b1011000111101111011000100110001100000101011100111000011100001010 -
b1111 '
b1111 0
b1011000111101111011000100110001100000101011100111000011100001010 )
b1111 *
#160000
0$
#165000
b1100000000111011001000101000000000010000011001000010000100100000 "
b1100000000111011001000101000000000010000011001000010000100100000 +
b1100000000111011001000101000000000010000011001000010000100100000 1
b10000 %
b10000 .
1$
b1100000000111011001000101000000000010000011001000010000100100000 #
b1100000000111011001000101000000000010000011001000010000100100000 -
b10000 '
b10000 0
b1100000000111011001000101000000000010000011001000010000100100000 )
b10000 *
#170000
0$
#175000
b101010101111000010001011010101011001110110011001100110010011101 "
b101010101111000010001011010101011001110110011001100110010011101 +
b101010101111000010001011010101011001110110011001100110010011101 1
b10001 %
b10001 .
1$
b101010101111000010001011010101011001110110011001100110010011101 #
b101010101111000010001011010101011001110110011001100110010011101 -
b10001 '
b10001 0
b101010101111000010001011010101011001110110011001100110010011101 )
b10001 *
#180000
0$
#185000
b1100101100100000001111101001011010001001100000111011100000010011 "
b1100101100100000001111101001011010001001100000111011100000010011 +
b1100101100100000001111101001011010001001100000111011100000010011 1
b10010 %
b10010 .
1$
b1100101100100000001111101001011010001001100000111011100000010011 #
b1100101100100000001111101001011010001001100000111011100000010011 -
b10010 '
b10010 0
b1100101100100000001111101001011010001001100000111011100000010011 )
b10010 *
#190000
0$
#195000
b1000011010111100001110000000110110101001101001111101011001010011 "
b1000011010111100001110000000110110101001101001111101011001010011 +
b1000011010111100001110000000110110101001101001111101011001010011 1
b10011 %
b10011 .
1$
b1000011010111100001110000000110110101001101001111101011001010011 #
b1000011010111100001110000000110110101001101001111101011001010011 -
b10011 '
b10011 0
b1000011010111100001110000000110110101001101001111101011001010011 )
b10011 *
#200000
0$
#205000
b11010110011111110111010110101111101010101001100010101011010101 "
b11010110011111110111010110101111101010101001100010101011010101 +
b11010110011111110111010110101111101010101001100010101011010101 1
b10100 %
b10100 .
1$
b11010110011111110111010110101111101010101001100010101011010101 #
b11010110011111110111010110101111101010101001100010101011010101 -
b10100 '
b10100 0
b11010110011111110111010110101111101010101001100010101011010101 )
b10100 *
#210000
0$
#215000
b1000000100010111010010100000001011010111010101100011111010101110 "
b1000000100010111010010100000001011010111010101100011111010101110 +
b1000000100010111010010100000001011010111010101100011111010101110 1
b10101 %
b10101 .
1$
b1000000100010111010010100000001011010111010101100011111010101110 #
b1000000100010111010010100000001011010111010101100011111010101110 -
b10101 '
b10101 0
b1000000100010111010010100000001011010111010101100011111010101110 )
b10101 *
#220000
0$
#225000
b111011111111111010010001110111100111110001010111001011001111 "
b111011111111111010010001110111100111110001010111001011001111 +
b111011111111111010010001110111100111110001010111001011001111 1
b10110 %
b10110 .
1$
b111011111111111010010001110111100111110001010111001011001111 #
b111011111111111010010001110111100111110001010111001011001111 -
b10110 '
b10110 0
b111011111111111010010001110111100111110001010111001011001111 )
b10110 *
#230000
0$
#235000
b1000110000100010010010010001100000101000010010110010100001010 "
b1000110000100010010010010001100000101000010010110010100001010 +
b1000110000100010010010010001100000101000010010110010100001010 1
b10111 %
b10111 .
1$
b1000110000100010010010010001100000101000010010110010100001010 #
b1000110000100010010010010001100000101000010010110010100001010 -
b10111 '
b10111 0
b1000110000100010010010010001100000101000010010110010100001010 )
b10111 *
#240000
0$
#245000
b1110010101110011000010101100101010011110001100010100110000111100 "
b1110010101110011000010101100101010011110001100010100110000111100 +
b1110010101110011000010101100101010011110001100010100110000111100 1
b11000 %
b11000 .
1$
b1110010101110011000010101100101010011110001100010100110000111100 #
b1110010101110011000010101100101010011110001100010100110000111100 -
b11000 '
b11000 0
b1110010101110011000010101100101010011110001100010100110000111100 )
b11000 *
#250000
0$
#255000
b111100101101000101111011111001001000101001011100110000110001010 "
b111100101101000101111011111001001000101001011100110000110001010 +
b111100101101000101111011111001001000101001011100110000110001010 1
b11001 %
b11001 .
1$
b111100101101000101111011111001001000101001011100110000110001010 #
b111100101101000101111011111001001000101001011100110000110001010 -
b11001 '
b11001 0
b111100101101000101111011111001001000101001011100110000110001010 )
b11001 *
#260000
0$
#265000
b10000011000100101100110100000111101100010010110011010011011000 "
b10000011000100101100110100000111101100010010110011010011011000 +
b10000011000100101100110100000111101100010010110011010011011000 1
b11010 %
b11010 .
1$
b10000011000100101100110100000111101100010010110011010011011000 #
b10000011000100101100110100000111101100010010110011010011011000 -
b11010 '
b11010 0
b10000011000100101100110100000111101100010010110011010011011000 )
b11010 *
#270000
0$
#275000
b11110000100000111100110111100011000100100010100001001010001001 "
b11110000100000111100110111100011000100100010100001001010001001 +
b11110000100000111100110111100011000100100010100001001010001001 1
b11011 %
b11011 .
1$
b11110000100000111100110111100011000100100010100001001010001001 #
b11110000100000111100110111100011000100100010100001001010001001 -
b11011 '
b11011 0
b11110000100000111100110111100011000100100010100001001010001001 )
b11011 *
#280000
0$
#285000
b111010111000101000011011110101101011011000000100110010110110110 "
b111010111000101000011011110101101011011000000100110010110110110 +
b111010111000101000011011110101101011011000000100110010110110110 1
b11100 %
b11100 .
1$
b111010111000101000011011110101101011011000000100110010110110110 #
b111010111000101000011011110101101011011000000100110010110110110 -
b11100 '
b11100 0
b111010111000101000011011110101101011011000000100110010110110110 )
b11100 *
#290000
0$
#295000
b110001101001011111110011100011001010111000101010001001110101110 "
b110001101001011111110011100011001010111000101010001001110101110 +
b110001101001011111110011100011001010111000101010001001110101110 1
b11101 %
b11101 .
1$
b110001101001011111110011100011001010111000101010001001110101110 #
b110001101001011111110011100011001010111000101010001001110101110 -
b11101 '
b11101 0
b110001101001011111110011100011001010111000101010001001110101110 )
b11101 *
#300000
0$
#305000
b1101111001110101000000101011110000010101000011111101110100101010 "
b1101111001110101000000101011110000010101000011111101110100101010 +
b1101111001110101000000101011110000010101000011111101110100101010 1
b11110 %
b11110 .
1$
b1101111001110101000000101011110000010101000011111101110100101010 #
b1101111001110101000000101011110000010101000011111101110100101010 -
b11110 '
b11110 0
b1101111001110101000000101011110000010101000011111101110100101010 )
b11110 *
#310000
0$
#315000
b0 "
b0 +
b0 1
b11111 %
b11111 .
1$
b1000010111010111100110100000101110111000100101111011111001110001 #
b1000010111010111100110100000101110111000100101111011111001110001 -
b11111 '
b11111 0
b1000010111010111100110100000101110111000100101111011111001110001 )
b11111 *
#320000
0$
#325000
b1001000010101001101010010010011000000100010010101111010000001 !
b1001000010101001101010010010011000000100010010101111010000001 ,
b1001000010101001101010010010011000000100010010101111010000001 2
b0 &
b0 /
1$
b100001011110010010000011000010100100111111100100101010101001111 #
b100001011110010010000011000010100100111111100100101010101001111 -
b0 '
b0 0
b100001011110010010000011000010100100111111100100101010101001111 )
0(
b0 *
#330000
0$
#335000
b1000010010000100110101100000100110110001111100000101011001100011 !
b1000010010000100110101100000100110110001111100000101011001100011 ,
b1000010010000100110101100000100110110001111100000101011001100011 2
b1 &
b1 /
1$
b1001110111001100011000000011101100011101000001100011001100111010 #
b1001110111001100011000000011101100011101000001100011001100111010 -
b1 '
b1 0
b1001110111001100011000000011101100011101000001100011001100111010 )
b1 *
#340000
0$
#345000
b11010111001011110110000110101000110110111111001100110001101 !
b11010111001011110110000110101000110110111111001100110001101 ,
b11010111001011110110000110101000110110111111001100110001101 2
b10 &
b10 /
1$
b1011111100100011001100100111111000001010101010100100101100010101 #
b1011111100100011001100100111111000001010101010100100101100010101 -
b10 '
b10 0
b1011111100100011001100100111111000001010101010100100101100010101 )
b10 *
#350000
0$
#355000
b1011001011000010100001000110010110001001001101110101001000010010 !
b1011001011000010100001000110010110001001001101110101001000010010 ,
b1011001011000010100001000110010110001001001101110101001000010010 2
b11 &
b11 /
1$
b111100011011001100110111111000101101100100111000100101111011001 #
b111100011011001100110111111000101101100100111000100101111011001 -
b11 '
b11 0
b111100011011001100110111111000101101100100111000100101111011001 )
b11 *
#360000
0$
#365000
b11110011111000110000000100000110110101111100110100001101 !
b11110011111000110000000100000110110101111100110100001101 ,
b11110011111000110000000100000110110101111100110100001101 2
b100 &
b100 /
1$
b11000100100011000001110110001000100110001101011111101101001100 #
b11000100100011000001110110001000100110001101011111101101001100 -
b100 '
b100 0
b11000100100011000001110110001000100110001101011111101101001100 )
b100 *
#370000
0$
#375000
b11101100100011111100010111011000011110100011011100110100111101 !
b11101100100011111100010111011000011110100011011100110100111101 ,
b11101100100011111100010111011000011110100011011100110100111101 2
b101 &
b101 /
1$
b100111110100001010101011001111101000111101110011010000110001111 #
b100111110100001010101011001111101000111101110011010000110001111 -
b101 '
b101 0
b100111110100001010101011001111101000111101110011010000110001111 )
b101 *
#380000
0$
#385000
b111011011010100010101111110110101000110001011011111011110001100 !
b111011011010100010101111110110101000110001011011111011110001100 ,
b111011011010100010101111110110101000110001011011111011110001100 2
b110 &
b110 /
1$
b111110001101101101010011111100011011011110011010110000010110111 #
b111110001101101101010011111100011011011110011010110000010110111 -
b110 '
b110 0
b111110001101101101010011111100011011011110011010110000010110111 )
b110 *
#390000
0$
#395000
b111110011111101111010011111100111100011001101110010010011000110 !
b111110011111101111010011111100111100011001101110010010011000110 ,
b111110011111101111010011111100111100011001101110010010011000110 2
b111 &
b111 /
1$
b1100111111000100010101101001111110101110011111011001010001011100 #
b1100111111000100010101101001111110101110011111011001010001011100 -
b111 '
b111 0
b1100111111000100010101101001111110101110011111011001010001011100 )
b111 *
#400000
0$
#405000
b1110001011110111100001001100010111010101000100111101001010101010 !
b1110001011110111100001001100010111010101000100111101001010101010 ,
b1110001011110111100001001100010111010101000100111101001010101010 2
b1000 &
b1000 /
1$
b1010110111001011110000000101101101000100110111100011011110001001 #
b1010110111001011110000000101101101000100110111100011011110001001 -
b1000 '
b1000 0
b1010110111001011110000000101101101000100110111100011011110001001 )
b1000 *
#410000
0$
#415000
b111001010101111111101111110010110111011110100100111001001110111 !
b111001010101111111101111110010110111011110100100111001001110111 ,
b111001010101111111101111110010110111011110100100111001001110111 2
b1001 &
b1001 /
1$
b1010010010101110001100100100100111101000001000110011111011010000 #
b1010010010101110001100100100100111101000001000110011111011010000 -
b1001 '
b1001 0
b1010010010101110001100100100100111101000001000110011111011010000 )
b1001 *
#420000
0$
#425000
b1000100100110010110101100001001001000111111011001101101110001111 !
b1000100100110010110101100001001001000111111011001101101110001111 ,
b1000100100110010110101100001001001000111111011001101101110001111 2
b1010 &
b1010 /
1$
b1110101111111110110000001101011110101000110001111111110001010001 #
b1110101111111110110000001101011110101000110001111111110001010001 -
b1010 '
b1010 0
b1110101111111110110000001101011110101000110001111111110001010001 )
b1010 *
#430000
0$
#435000
b111100100110000011010011111001011100111011101101001011011001110 !
b111100100110000011010011111001011100111011101101001011011001110 ,
b111100100110000011010011111001011100111011101101001011011001110 2
b1011 &
b1011 /
1$
b100101100100001001011111001011000000110000111010111111100001100 #
b100101100100001001011111001011000000110000111010111111100001100 -
b1011 '
b1011 0
b100101100100001001011111001011000000110000111010111111100001100 )
b1011 *
#440000
0$
#445000
b1111010000000000011110101110100011100010110010100100111011000101 !
b1111010000000000011110101110100011100010110010100100111011000101 ,
b1111010000000000011110101110100011100010110010100100111011000101 2
b1100 &
b1100 /
1$
b1110000100101100110011101100001001100100010101111110110111001000 #
b1110000100101100110011101100001001100100010101111110110111001000 -
b1100 '
b1100 0
b1110000100101100110011101100001001100100010101111110110111001000 )
b1100 *
#450000
0$
#455000
b10111001011000010010010101110011011110100011100010100010111101 !
b10111001011000010010010101110011011110100011100010100010111101 ,
b10111001011000010010010101110011011110100011100010100010111101 2
b1101 &
b1101 /
1$
b1011101110000010010110100111011100011110111100101110110100111101 #
b1011101110000010010110100111011100011110111100101110110100111101 -
b1101 '
b1101 0
b1011101110000010010110100111011100011110111100101110110100111101 )
b1101 *
#460000
0$
#465000
b1001011010101011010110000010110110110010101001110010011001100101 !
b1001011010101011010110000010110110110010101001110010011001100101 ,
b1001011010101011010110000010110110110010101001110010011001100101 2
b1110 &
b1110 /
1$
b100100001100110110110001001010111111000001010000000001111110 #
b100100001100110110110001001010111111000001010000000001111110 -
b1110 '
b1110 0
b100100001100110110110001001010111111000001010000000001111110 )
b1110 *
#470000
0$
#475000
b1011000111101111011000100110001100000101011100111000011100001010 !
b1011000111101111011000100110001100000101011100111000011100001010 ,
b1011000111101111011000100110001100000101011100111000011100001010 2
b1111 &
b1111 /
1$
b11011011100101100000010110110100011100110110011110011100111001 #
b11011011100101100000010110110100011100110110011110011100111001 -
b1111 '
b1111 0
b11011011100101100000010110110100011100110110011110011100111001 )
b1111 *
#480000
0$
#485000
b1100000000111011001000101000000000010000011001000010000100100000 !
b1100000000111011001000101000000000010000011001000010000100100000 ,
b1100000000111011001000101000000000010000011001000010000100100000 2
b10000 &
b10000 /
1$
b111111010010100011110001111111101001111010111111011011010011 #
b111111010010100011110001111111101001111010111111011011010011 -
b10000 '
b10000 0
b111111010010100011110001111111101001111010111111011011010011 )
b10000 *
#490000
0$
#495000
b101010101111000010001011010101011001110110011001100110010011101 !
b101010101111000010001011010101011001110110011001100110010011101 ,
b101010101111000010001011010101011001110110011001100110010011101 2
b10001 &
b10001 /
1$
b100001011011001001011111000010110111100000101001000100001111000 #
b100001011011001001011111000010110111100000101001000100001111000 -
b10001 '
b10001 0
b100001011011001001011111000010110111100000101001000100001111000 )
b10001 *
#500000
0$
#505000
b1100101100100000001111101001011010001001100000111011100000010011 !
b1100101100100000001111101001011010001001100000111011100000010011 ,
b1100101100100000001111101001011010001001100000111011100000010011 2
b10010 &
b10010 /
1$
b10110111011010010110010101101100100100100010110100101101001001 #
b10110111011010010110010101101100100100100010110100101101001001 -
b10010 '
b10010 0
b10110111011010010110010101101100100100100010110100101101001001 )
b10010 *
#510000
0$
#515000
b1000011010111100001110000000110110101001101001111101011001010011 !
b1000011010111100001110000000110110101001101001111101011001010011 ,
b1000011010111100001110000000110110101001101001111101011001010011 2
b10011 &
b10011 /
1$
b1001111111110010101011100011111100010101000011001010111100101010 #
b1001111111110010101011100011111100010101000011001010111100101010 -
b10011 '
b10011 0
b1001111111110010101011100011111100010101000011001010111100101010 )
b10011 *
#520000
0$
#525000
b11010110011111110111010110101111101010101001100010101011010101 !
b11010110011111110111010110101111101010101001100010101011010101 ,
b11010110011111110111010110101111101010101001100010101011010101 2
b10100 &
b10100 /
1$
b10110000010101011000110101100011000011001111110011100010000110 #
b10110000010101011000110101100011000011001111110011100010000110 -
b10100 '
b10100 0
b10110000010101011000110101100011000011001111110011100010000110 )
b10100 *
#530000
0$
#535000
b1000000100010111010010100000001011010111010101100011111010101110 !
b1000000100010111010010100000001011010111010101100011111010101110 ,
b1000000100010111010010100000001011010111010101100011111010101110 2
b10101 &
b10101 /
1$
b1100011100011010000011001000111011001110001011111111001010011100 #
b1100011100011010000011001000111011001110001011111111001010011100 -
b10101 '
b10101 0
b1100011100011010000011001000111011001110001011111111001010011100 )
b10101 *
#540000
0$
#545000
b111011111111111010010001110111100111110001010111001011001111 !
b111011111111111010010001110111100111110001010111001011001111 ,
b111011111111111010010001110111100111110001010111001011001111 2
b10110 &
b10110 /
1$
b111110100110101100110011111101010010011011111011011110000100110 #
b111110100110101100110011111101010010011011111011011110000100110 -
b10110 '
b10110 0
b111110100110101100110011111101010010011011111011011110000100110 )
b10110 *
#550000
0$
#555000
b1000110000100010010010010001100000101000010010110010100001010 !
b1000110000100010010010010001100000101000010010110010100001010 ,
b1000110000100010010010010001100000101000010010110010100001010 2
b10111 &
b10111 /
1$
b11100110010110000101110111001111010001100010111011010010100011 #
b11100110010110000101110111001111010001100010111011010010100011 -
b10111 '
b10111 0
b11100110010110000101110111001111010001100010111011010010100011 )
b10111 *
#560000
0$
#565000
b1110010101110011000010101100101010011110001100010100110000111100 !
b1110010101110011000010101100101010011110001100010100110000111100 ,
b1110010101110011000010101100101010011110001100010100110000111100 2
b11000 &
b11000 /
1$
b1001011110011001101010000010111111011001110100101001001010110011 #
b1001011110011001101010000010111111011001110100101001001010110011 -
b11000 '
b11000 0
b1001011110011001101010000010111111011001110100101001001010110011 )
b11000 *
#570000
0$
#575000
b111100101101000101111011111001001000101001011100110000110001010 !
b111100101101000101111011111001001000101001011100110000110001010 ,
b111100101101000101111011111001001000101001011100110000110001010 2
b11001 &
b11001 /
1$
b1010111111011000010101100101111100100010001010010000110101000100 #
b1010111111011000010101100101111100100010001010010000110101000100 -
b11001 '
b11001 0
b1010111111011000010101100101111100100010001010010000110101000100 )
b11001 *
#580000
0$
#585000
b10000011000100101100110100000111101100010010110011010011011000 !
b10000011000100101100110100000111101100010010110011010011011000 ,
b10000011000100101100110100000111101100010010110011010011011000 2
b11010 &
b11010 /
1$
b111101111111000111111011111011111100101100110110011011011001011 #
b111101111111000111111011111011111100101100110110011011011001011 -
b11010 '
b11010 0
b111101111111000111111011111011111100101100110110011011011001011 )
b11010 *
#590000
0$
#595000
b11110000100000111100110111100011000100100010100001001010001001 !
b11110000100000111100110111100011000100100010100001001010001001 ,
b11110000100000111100110111100011000100100010100001001010001001 2
b11011 &
b11011 /
1$
b1111001100001001000110101110011000101101001010001101101101011010 #
b1111001100001001000110101110011000101101001010001101101101011010 -
b11011 '
b11011 0
b1111001100001001000110101110011000101101001010001101101101011010 )
b11011 *
#600000
0$
#605000
b111010111000101000011011110101101011011000000100110010110110110 !
b111010111000101000011011110101101011011000000100110010110110110 ,
b111010111000101000011011110101101011011000000100110010110110110 2
b11100 &
b11100 /
1$
b1010011001111110000010010100111110110100000101110001011101101 #
b1010011001111110000010010100111110110100000101110001011101101 -
b11100 '
b11100 0
b1010011001111110000010010100111110110100000101110001011101101 )
b11100 *
#610000
0$
#615000
b110001101001011111110011100011001010111000101010001001110101110 !
b110001101001011111110011100011001010111000101010001001110101110 ,
b110001101001011111110011100011001010111000101010001001110101110 2
b11101 &
b11101 /
1$
b1110110101010011011011001101101010110010100111111011011001100101 #
b1110110101010011011011001101101010110010100111111011011001100101 -
b11101 '
b11101 0
b1110110101010011011011001101101010110010100111111011011001100101 )
b11101 *
#620000
0$
#625000
b1101111001110101000000101011110000010101000011111101110100101010 !
b1101111001110101000000101011110000010101000011111101110100101010 ,
b1101111001110101000000101011110000010101000011111101110100101010 2
b11110 &
b11110 /
1$
b1101101010001010111000101011010111101111101111101001010011011111 #
b1101101010001010111000101011010111101111101111101001010011011111 -
b11110 '
b11110 0
b1101101010001010111000101011010111101111101111101001010011011111 )
b11110 *
#630000
0$
#635000
b0 !
b0 ,
b0 2
b11111 &
b11111 /
1$
b11110011110001000110010111100100100010001100011111111101000100 #
b11110011110001000110010111100100100010001100011111111101000100 -
b11111 '
b11111 0
b11110011110001000110010111100100100010001100011111111101000100 )
b11111 *
#640000
0$
#645000
1$
b100000 *
