Lab07/ALU.v
// 64-bit Arithmetic Logic Unit (ALU) for ARMv8 Processor
// Supports AND, OR, ADD, SUB, and PassB operations

`define AND   4'b0000
`define OR    4'b0001
`define ADD   4'b0010
`define SUB   4'b0110
`define PassB 4'b0111

module ALU(
    output reg [63:0] BusW,
    input      [63:0] BusA,
    input      [63:0] BusB,
    input      [3:0]  ALUCtrl,
    output reg        Zero
);

    always @(*) begin
        case (ALUCtrl)
            `AND: begin
                // Bitwise AND operation
                BusW = BusA & BusB;
            end
            
            `OR: begin
                // Bitwise OR operation
                BusW = BusA | BusB;
            end
            
            `ADD: begin
                // Addition operation
                BusW = BusA + BusB;
            end
            
            `SUB: begin
                // Subtraction operation
                BusW = BusA - BusB;
            end
            
            `PassB: begin
                // Pass input B (used by CBZ)
                BusW = BusB;
            end
            
            default: begin
                // Default case to avoid latches. should never execute
                BusW = 64'b0;
            end
        endcase

        Zero = (BusW == 64'b0) ? 1'b1 : 1'b0;

    end

endmodule

Lab06/ALU_tb.v
// Self-Checking Testbench for ALU Module
// Tests all ALU operations with randomized inputs and corner cases

`timescale 1ns/1ps

`define AND   4'b0000
`define OR    4'b0001
`define ADD   4'b0010
`define SUB   4'b0110
`define PassB 4'b0111

module ALU_tb;

    // Testbench signals
    reg [63:0] BusA;
    reg [63:0] BusB;
    reg [3:0]  ALUCtrl;
    wire [63:0] BusW;
    wire Zero;
    
    // Expected outputs for verification
    reg [63:0] expected_BusW;
    reg expected_Zero;
    
    // Test counters
    integer i;
    integer errors;
    integer total_tests;
    
    // Instantiate the ALU module
    ALU uut (
        .BusW(BusW),
        .BusA(BusA),
        .BusB(BusB),
        .ALUCtrl(ALUCtrl),
        .Zero(Zero)
    );
    
    // Task to check results
    task check_result;
        input [63:0] exp_BusW;
        input exp_Zero;
        input [3:0] ctrl;
        input [63:0] a;
        input [63:0] b;
        begin
            #1; // Small delay for signals to settle
            if (BusW !== exp_BusW || Zero !== exp_Zero) begin
                $display("ERROR at time %0t: ALUCtrl=%b, BusA=%h, BusB=%h", 
                         $time, ctrl, a, b);
                $display("  Expected: BusW=%h, Zero=%b", exp_BusW, exp_Zero);
                $display("  Got:      BusW=%h, Zero=%b", BusW, Zero);
                errors = errors + 1;
            end
            total_tests = total_tests + 1;
        end
    endtask
    
    // Task to test a specific operation
    task test_operation;
        input [3:0] op;
        input [127:0] op_name;
        begin
            $display("Testing %0s operation (ALUCtrl = %b)...", op_name, op);
            ALUCtrl = op;
            
            // Test corner cases: all zeros and all ones combinations
            // Case 1: A=0, B=0
            BusA = 64'h0000000000000000;
            BusB = 64'h0000000000000000;
            case (op)
                `AND:   expected_BusW = BusA & BusB;
                `OR:    expected_BusW = BusA | BusB;
                `ADD:   expected_BusW = BusA + BusB;
                `SUB:   expected_BusW = BusA - BusB;
                `PassB: expected_BusW = BusB;
                default: expected_BusW = 64'b0;
            endcase
            expected_Zero = (expected_BusW == 64'b0);
            #10;
            check_result(expected_BusW, expected_Zero, op, BusA, BusB);
            
            // Case 2: A=0, B=all 1's
            BusA = 64'h0000000000000000;
            BusB = 64'hFFFFFFFFFFFFFFFF;
            case (op)
                `AND:   expected_BusW = BusA & BusB;
                `OR:    expected_BusW = BusA | BusB;
                `ADD:   expected_BusW = BusA + BusB;
                `SUB:   expected_BusW = BusA - BusB;
                `PassB: expected_BusW = BusB;
                default: expected_BusW = 64'b0;
            endcase
            expected_Zero = (expected_BusW == 64'b0);
            #10;
            check_result(expected_BusW, expected_Zero, op, BusA, BusB);
            
            // Case 3: A=all 1's, B=0
            BusA = 64'hFFFFFFFFFFFFFFFF;
            BusB = 64'h0000000000000000;
            case (op)
                `AND:   expected_BusW = BusA & BusB;
                `OR:    expected_BusW = BusA | BusB;
                `ADD:   expected_BusW = BusA + BusB;
                `SUB:   expected_BusW = BusA - BusB;
                `PassB: expected_BusW = BusB;
                default: expected_BusW = 64'b0;
            endcase
            expected_Zero = (expected_BusW == 64'b0);
            #10;
            check_result(expected_BusW, expected_Zero, op, BusA, BusB);
            
            // Case 4: A=all 1's, B=all 1's
            BusA = 64'hFFFFFFFFFFFFFFFF;
            BusB = 64'hFFFFFFFFFFFFFFFF;
            case (op)
                `AND:   expected_BusW = BusA & BusB;
                `OR:    expected_BusW = BusA | BusB;
                `ADD:   expected_BusW = BusA + BusB;
                `SUB:   expected_BusW = BusA - BusB;
                `PassB: expected_BusW = BusB;
                default: expected_BusW = 64'b0;
            endcase
            expected_Zero = (expected_BusW == 64'b0);
            #10;
            check_result(expected_BusW, expected_Zero, op, BusA, BusB);
            
            // Test at least one case that produces Zero=1
            case (op)
                `AND: begin
                    BusA = 64'hAAAAAAAAAAAAAAAA;
                    BusB = 64'h5555555555555555;
                end
                `OR: begin
                    BusA = 64'h0000000000000000;
                    BusB = 64'h0000000000000000;
                end
                `ADD: begin
                    BusA = 64'h0000000000000000;
                    BusB = 64'h0000000000000000;
                end
                `SUB: begin
                    BusA = 64'h1234567890ABCDEF;
                    BusB = 64'h1234567890ABCDEF;
                end
                `PassB: begin
                    BusB = 64'h0000000000000000;
                end
            endcase
            case (op)
                `AND:   expected_BusW = BusA & BusB;
                `OR:    expected_BusW = BusA | BusB;
                `ADD:   expected_BusW = BusA + BusB;
                `SUB:   expected_BusW = BusA - BusB;
                `PassB: expected_BusW = BusB;
                default: expected_BusW = 64'b0;
            endcase
            expected_Zero = (expected_BusW == 64'b0);
            #10;
            check_result(expected_BusW, expected_Zero, op, BusA, BusB);
            
            // Test at least one case that produces Zero=0
            case (op)
                `AND: begin
                    BusA = 64'hFFFFFFFFFFFFFFFF;
                    BusB = 64'hFFFFFFFFFFFFFFFF;
                end
                `OR: begin
                    BusA = 64'h0000000000000001;
                    BusB = 64'h0000000000000000;
                end
                `ADD: begin
                    BusA = 64'h0000000000000001;
                    BusB = 64'h0000000000000001;
                end
                `SUB: begin
                    BusA = 64'h0000000000000002;
                    BusB = 64'h0000000000000001;
                end
                `PassB: begin
                    BusB = 64'h0000000000000001;
                end
            endcase
            case (op)
                `AND:   expected_BusW = BusA & BusB;
                `OR:    expected_BusW = BusA | BusB;
                `ADD:   expected_BusW = BusA + BusB;
                `SUB:   expected_BusW = BusA - BusB;
                `PassB: expected_BusW = BusB;
                default: expected_BusW = 64'b0;
            endcase
            expected_Zero = (expected_BusW == 64'b0);
            #10;
            check_result(expected_BusW, expected_Zero, op, BusA, BusB);
            
            // Random tests (100 iterations)
            for (i = 0; i < 100; i = i + 1) begin
                BusA = {$random, $random};
                BusB = {$random, $random};
                
                case (op)
                    `AND:   expected_BusW = BusA & BusB;
                    `OR:    expected_BusW = BusA | BusB;
                    `ADD:   expected_BusW = BusA + BusB;
                    `SUB:   expected_BusW = BusA - BusB;
                    `PassB: expected_BusW = BusB;
                    default: expected_BusW = 64'b0;
                endcase
                expected_Zero = (expected_BusW == 64'b0);
                #10;
                check_result(expected_BusW, expected_Zero, op, BusA, BusB);
            end
        end
    endtask
    
    initial begin
        // Initialize VCD dump
        $dumpfile("alu.vcd");
        $dumpvars(0, ALU_tb);
        
        // Initialize counters
        errors = 0;
        total_tests = 0;
        
        $display("=== ALU Testbench Starting ===");
        $display("Testing with 100+ random values per operation");
        $display("");
        
        // Test each ALU operation
        test_operation(`AND, "AND");
        test_operation(`OR, "OR");
        test_operation(`ADD, "ADD");
        test_operation(`SUB, "SUB");
        test_operation(`PassB, "PassB");
        
        // Special test: ADD overflow
        $display("Testing ADD overflow...");
        ALUCtrl = `ADD;
        BusA = 64'hFFFFFFFFFFFFFFFF;
        BusB = 64'h0000000000000001;
        expected_BusW = BusA + BusB; // Will overflow to 0
        expected_Zero = (expected_BusW == 64'b0);
        #10;
        check_result(expected_BusW, expected_Zero, ALUCtrl, BusA, BusB);
        $display("  Overflow test: %h + %h = %h", BusA, BusB, BusW);
        
        // Another overflow test
        BusA = 64'hFFFFFFFFFFFFFFFF;
        BusB = 64'hFFFFFFFFFFFFFFFF;
        expected_BusW = BusA + BusB; // Will overflow
        expected_Zero = (expected_BusW == 64'b0);
        #10;
        check_result(expected_BusW, expected_Zero, ALUCtrl, BusA, BusB);
        $display("  Overflow test: %h + %h = %h", BusA, BusB, BusW);
        
        // Final report
        $display("");
        $display("=== Test Results ===");
        $display("Total tests: %0d", total_tests);
        $display("Errors: %0d", errors);
        
        if (errors == 0) begin
            $display("*** ALL TESTS PASSED ***");
        end else begin
            $display("*** TESTS FAILED ***");
        end
        
        $display("");
        $finish;
    end

endmodule

Lab06/alu.vcd
$date
	Tue Oct  7 18:18:37 2025
$end
$version
	Icarus Verilog
$end
$timescale
	1ps
$end
$scope module ALU_tb $end
$var wire 1 ! Zero $end
$var wire 64 " BusW [63:0] $end
$var reg 4 # ALUCtrl [3:0] $end
$var reg 64 $ BusA [63:0] $end
$var reg 64 % BusB [63:0] $end
$var reg 64 & expected_BusW [63:0] $end
$var reg 1 ' expected_Zero $end
$var integer 32 ( errors [31:0] $end
$var integer 32 ) i [31:0] $end
$var integer 32 * total_tests [31:0] $end
$scope module uut $end
$var wire 4 + ALUCtrl [3:0] $end
$var wire 64 , BusA [63:0] $end
$var wire 64 - BusB [63:0] $end
$var wire 1 ! Zero $end
$var reg 64 . BusW [63:0] $end
$upscope $end
$scope task check_result $end
$var reg 64 / a [63:0] $end
$var reg 64 0 b [63:0] $end
$var reg 4 1 ctrl [3:0] $end
$var reg 64 2 exp_BusW [63:0] $end
$var reg 1 3 exp_Zero $end
$upscope $end
$scope task test_operation $end
$var reg 4 4 op [3:0] $end
$var reg 128 5 op_name [127:0] $end
$upscope $end
$upscope $end
$enddefinitions $end
#0
$dumpvars
b10000010100111001000100 5
b0 4
x3
bx 2
bx 1
bx 0
bx /
b0 .
b0 -
b0 ,
b0 +
b0 *
bx )
b0 (
1'
b0 &
b0 %
b0 $
b0 #
b0 "
1!
$end
#10000
b0 0
b0 /
b0 1
13
b0 2
#11000
b1111111111111111111111111111111111111111111111111111111111111111 %
b1111111111111111111111111111111111111111111111111111111111111111 -
b1 *
#21000
b1111111111111111111111111111111111111111111111111111111111111111 0
#22000
b0 %
b0 -
b1111111111111111111111111111111111111111111111111111111111111111 $
b1111111111111111111111111111111111111111111111111111111111111111 ,
b10 *
#32000
b0 0
b1111111111111111111111111111111111111111111111111111111111111111 /
#33000
0!
b1111111111111111111111111111111111111111111111111111111111111111 "
b1111111111111111111111111111111111111111111111111111111111111111 .
0'
b1111111111111111111111111111111111111111111111111111111111111111 &
b1111111111111111111111111111111111111111111111111111111111111111 %
b1111111111111111111111111111111111111111111111111111111111111111 -
b11 *
#43000
b1111111111111111111111111111111111111111111111111111111111111111 0
03
b1111111111111111111111111111111111111111111111111111111111111111 2
#44000
1!
b0 "
b0 .
1'
b0 &
b101010101010101010101010101010101010101010101010101010101010101 %
b101010101010101010101010101010101010101010101010101010101010101 -
b1010101010101010101010101010101010101010101010101010101010101010 $
b1010101010101010101010101010101010101010101010101010101010101010 ,
b100 *
#54000
b101010101010101010101010101010101010101010101010101010101010101 0
b1010101010101010101010101010101010101010101010101010101010101010 /
13
b0 2
#55000
0!
b1111111111111111111111111111111111111111111111111111111111111111 "
b1111111111111111111111111111111111111111111111111111111111111111 .
0'
b1111111111111111111111111111111111111111111111111111111111111111 &
b1111111111111111111111111111111111111111111111111111111111111111 %
b1111111111111111111111111111111111111111111111111111111111111111 -
b1111111111111111111111111111111111111111111111111111111111111111 $
b1111111111111111111111111111111111111111111111111111111111111111 ,
b101 *
#65000
b1111111111111111111111111111111111111111111111111111111111111111 0
b1111111111111111111111111111111111111111111111111111111111111111 /
03
b1111111111111111111111111111111111111111111111111111111111111111 2
#66000
b100000101000000000010000000100000000101011000000001 "
b100000101000000000010000000100000000101011000000001 .
b100000101000000000010000000100000000101011000000001 &
b1000010010000100110101100000100110110001111100000101011001100011 %
b1000010010000100110101100000100110110001111100000101011001100011 -
b1001000010101001101010010010011000000100010010101111010000001 $
b1001000010101001101010010010011000000100010010101111010000001 ,
b0 )
b110 *
#76000
b1000010010000100110101100000100110110001111100000101011001100011 0
b1001000010101001101010010010011000000100010010101111010000001 /
b100000101000000000010000000100000000101011000000001 2
#77000
b1010000000000000000000010100000000000101110001000000000000 "
b1010000000000000000000010100000000000101110001000000000000 .
b1010000000000000000000010100000000000101110001000000000000 &
b1011001011000010100001000110010110001001001101110101001000010010 %
b1011001011000010100001000110010110001001001101110101001000010010 -
b11010111001011110110000110101000110110111111001100110001101 $
b11010111001011110110000110101000110110111111001100110001101 ,
b1 )
b111 *
#87000
b1011001011000010100001000110010110001001001101110101001000010010 0
b11010111001011110110000110101000110110111111001100110001101 /
b1010000000000000000000010100000000000101110001000000000000 2
#88000
b100011111000010000000000000110100001011100110100001101 "
b100011111000010000000000000110100001011100110100001101 .
b100011111000010000000000000110100001011100110100001101 &
b11101100100011111100010111011000011110100011011100110100111101 %
b11101100100011111100010111011000011110100011011100110100111101 -
b11110011111000110000000100000110110101111100110100001101 $
b11110011111000110000000100000110110101111100110100001101 ,
b10 )
b1000 *
#98000
b11101100100011111100010111011000011110100011011100110100111101 0
b11110011111000110000000100000110110101111100110100001101 /
b100011111000010000000000000110100001011100110100001101 2
#99000
b111010011010100010000011110100101000010001001010010010010000100 "
b111010011010100010000011110100101000010001001010010010010000100 .
b111010011010100010000011110100101000010001001010010010010000100 &
b111110011111101111010011111100111100011001101110010010011000110 %
b111110011111101111010011111100111100011001101110010010011000110 -
b111011011010100010101111110110101000110001011011111011110001100 $
b111011011010100010101111110110101000110001011011111011110001100 ,
b11 )
b1001 *
#109000
b111110011111101111010011111100111100011001101110010010011000110 0
b111011011010100010101111110110101000110001011011111011110001100 /
b111010011010100010000011110100101000010001001010010010010000100 2
#110000
b110001010100111100001001100010110010001000100100101001000100010 "
b110001010100111100001001100010110010001000100100101001000100010 .
b110001010100111100001001100010110010001000100100101001000100010 &
b111001010101111111101111110010110111011110100100111001001110111 %
b111001010101111111101111110010110111011110100100111001001110111 -
b1110001011110111100001001100010111010101000100111101001010101010 $
b1110001011110111100001001100010111010101000100111101001010101010 ,
b100 )
b1010 *
#120000
b111001010101111111101111110010110111011110100100111001001110111 0
b1110001011110111100001001100010111010101000100111101001010101010 /
b110001010100111100001001100010110010001000100100101001000100010 2
#121000
b100100110000010000000001001001000111011001001001001010001110 "
b100100110000010000000001001001000111011001001001001010001110 .
b100100110000010000000001001001000111011001001001001010001110 &
b111100100110000011010011111001011100111011101101001011011001110 %
b111100100110000011010011111001011100111011101101001011011001110 -
b1000100100110010110101100001001001000111111011001101101110001111 $
b1000100100110010110101100001001001000111111011001101101110001111 ,
b101 )
b1011 *
#131000
b111100100110000011010011111001011100111011101101001011011001110 0
b1000100100110010110101100001001001000111111011001101101110001111 /
b100100110000010000000001001001000111011001001001001010001110 2
#132000
b10010000000000010010000100100011000010100010100000100010000101 "
b10010000000000010010000100100011000010100010100000100010000101 .
b10010000000000010010000100100011000010100010100000100010000101 &
b10111001011000010010010101110011011110100011100010100010111101 %
b10111001011000010010010101110011011110100011100010100010111101 -
b1111010000000000011110101110100011100010110010100100111011000101 $
b1111010000000000011110101110100011100010110010100100111011000101 ,
b110 )
b1100 *
#142000
b10111001011000010010010101110011011110100011100010100010111101 0
b1111010000000000011110101110100011100010110010100100111011000101 /
b10010000000000010010000100100011000010100010100000100010000101 2
#143000
b1001000010101011010000000010000100000000001000110000011000000000 "
b1001000010101011010000000010000100000000001000110000011000000000 .
b1001000010101011010000000010000100000000001000110000011000000000 &
b1011000111101111011000100110001100000101011100111000011100001010 %
b1011000111101111011000100110001100000101011100111000011100001010 -
b1001011010101011010110000010110110110010101001110010011001100101 $
b1001011010101011010110000010110110110010101001110010011001100101 ,
b111 )
b1101 *
#153000
b1011000111101111011000100110001100000101011100111000011100001010 0
b1001011010101011010110000010110110110010101001110010011001100101 /
b1001000010101011010000000010000100000000001000110000011000000000 2
#154000
b100000000111000000000001000000000000000010001000000000000000000 "
b100000000111000000000001000000000000000010001000000000000000000 .
b100000000111000000000001000000000000000010001000000000000000000 &
b101010101111000010001011010101011001110110011001100110010011101 %
b101010101111000010001011010101011001110110011001100110010011101 -
b1100000000111011001000101000000000010000011001000010000100100000 $
b1100000000111011001000101000000000010000011001000010000100100000 ,
b1000 )
b1110 *
#164000
b101010101111000010001011010101011001110110011001100110010011101 0
b1100000000111011001000101000000000010000011001000010000100100000 /
b100000000111000000000001000000000000000010001000000000000000000 2
#165000
b1000001000100000001110000000010010001001100000111001000000010011 "
b1000001000100000001110000000010010001001100000111001000000010011 .
b1000001000100000001110000000010010001001100000111001000000010011 &
b1000011010111100001110000000110110101001101001111101011001010011 %
b1000011010111100001110000000110110101001101001111101011001010011 -
b1100101100100000001111101001011010001001100000111011100000010011 $
b1100101100100000001111101001011010001001100000111011100000010011 ,
b1001 )
b1111 *
#175000
b1000011010111100001110000000110110101001101001111101011001010011 0
b1100101100100000001111101001011010001001100000111011100000010011 /
b1000001000100000001110000000010010001001100000111001000000010011 2
#176000
b100010111010010000000001011000010000001100010101010000100 "
b100010111010010000000001011000010000001100010101010000100 .
b100010111010010000000001011000010000001100010101010000100 &
b1000000100010111010010100000001011010111010101100011111010101110 %
b1000000100010111010010100000001011010111010101100011111010101110 -
b11010110011111110111010110101111101010101001100010101011010101 $
b11010110011111110111010110101111101010101001100010101011010101 ,
b1010 )
b10000 *
#186000
b1000000100010111010010100000001011010111010101100011111010101110 0
b11010110011111110111010110101111101010101001100010101011010101 /
b100010111010010000000001011000010000001100010101010000100 2
#187000
b10000100010010010000000100000101000000010110000000001010 "
b10000100010010010000000100000101000000010110000000001010 .
b10000100010010010000000100000101000000010110000000001010 &
b1000110000100010010010010001100000101000010010110010100001010 %
b1000110000100010010010010001100000101000010010110010100001010 -
b111011111111111010010001110111100111110001010111001011001111 $
b111011111111111010010001110111100111110001010111001011001111 ,
b1011 )
b10001 *
#197000
b1000110000100010010010010001100000101000010010110010100001010 0
b111011111111111010010001110111100111110001010111001011001111 /
b10000100010010010000000100000101000000010110000000001010 2
#198000
b110000101100000000010001100001000000100001000000100000000001000 "
b110000101100000000010001100001000000100001000000100000000001000 .
b110000101100000000010001100001000000100001000000100000000001000 &
b111100101101000101111011111001001000101001011100110000110001010 %
b111100101101000101111011111001001000101001011100110000110001010 -
b1110010101110011000010101100101010011110001100010100110000111100 $
b1110010101110011000010101100101010011110001100010100110000111100 ,
b1100 )
b10010 *
#208000
b111100101101000101111011111001001000101001011100110000110001010 0
b1110010101110011000010101100101010011110001100010100110000111100 /
b110000101100000000010001100001000000100001000000100000000001000 2
#209000
b10000000000000101100110100000011000100000010100001000010001000 "
b10000000000000101100110100000011000100000010100001000010001000 .
b10000000000000101100110100000011000100000010100001000010001000 &
b11110000100000111100110111100011000100100010100001001010001001 %
b11110000100000111100110111100011000100100010100001001010001001 -
b10000011000100101100110100000111101100010010110011010011011000 $
b10000011000100101100110100000111101100010010110011010011011000 ,
b1101 )
b10011 *
#219000
b11110000100000111100110111100011000100100010100001001010001001 0
b10000011000100101100110100000111101100010010110011010011011000 /
b10000000000000101100110100000011000100000010100001000010001000 2
#220000
b110000101000001000010011100001001010011000000000000000110100110 "
b110000101000001000010011100001001010011000000000000000110100110 .
b110000101000001000010011100001001010011000000000000000110100110 &
b110001101001011111110011100011001010111000101010001001110101110 %
b110001101001011111110011100011001010111000101010001001110101110 -
b111010111000101000011011110101101011011000000100110010110110110 $
b111010111000101000011011110101101011011000000100110010110110110 ,
b1110 )
b10100 *
#230000
b110001101001011111110011100011001010111000101010001001110101110 0
b111010111000101000011011110101101011011000000100110010110110110 /
b110000101000001000010011100001001010011000000000000000110100110 2
#231000
b1000010001010101000000100000100000010000000001111001110000100000 "
b1000010001010101000000100000100000010000000001111001110000100000 .
b1000010001010101000000100000100000010000000001111001110000100000 &
b1000010111010111100110100000101110111000100101111011111001110001 %
b1000010111010111100110100000101110111000100101111011111001110001 -
b1101111001110101000000101011110000010101000011111101110100101010 $
b1101111001110101000000101011110000010101000011111101110100101010 ,
b1111 )
b10101 *
#241000
b1000010111010111100110100000101110111000100101111011111001110001 0
b1101111001110101000000101011110000010101000011111101110100101010 /
b1000010001010101000000100000100000010000000001111001110000100000 2
#242000
b11000000010000000000000100000101000000100001000100001010 "
b11000000010000000000000100000101000000100001000100001010 .
b11000000010000000000000100000101000000100001000100001010 &
b1001110111001100011000000011101100011101000001100011001100111010 %
b1001110111001100011000000011101100011101000001100011001100111010 -
b100001011110010010000011000010100100111111100100101010101001111 $
b100001011110010010000011000010100100111111100100101010101001111 ,
b10000 )
b10110 *
#252000
b1001110111001100011000000011101100011101000001100011001100111010 0
b100001011110010010000011000010100100111111100100101010101001111 /
b11000000010000000000000100000101000000100001000100001010 2
#253000
b11100000000001000100100111000000001000100010000100101100010001 "
b11100000000001000100100111000000001000100010000100101100010001 .
b11100000000001000100100111000000001000100010000100101100010001 &
b111100011011001100110111111000101101100100111000100101111011001 %
b111100011011001100110111111000101101100100111000100101111011001 -
b1011111100100011001100100111111000001010101010100100101100010101 $
b1011111100100011001100100111111000001010101010100100101100010101 ,
b10001 )
b10111 *
#263000
b111100011011001100110111111000101101100100111000100101111011001 0
b1011111100100011001100100111111000001010101010100100101100010101 /
b11100000000001000100100111000000001000100010000100101100010001 2
#264000
b100100001000001010000001000000110001100011010000100001100 "
b100100001000001010000001000000110001100011010000100001100 .
b100100001000001010000001000000110001100011010000100001100 &
b100111110100001010101011001111101000111101110011010000110001111 %
b100111110100001010101011001111101000111101110011010000110001111 -
b11000100100011000001110110001000100110001101011111101101001100 $
b11000100100011000001110110001000100110001101011111101101001100 ,
b10010 )
b11000 *
#274000
b100111110100001010101011001111101000111101110011010000110001111 0
b11000100100011000001110110001000100110001101011111101101001100 /
b100100001000001010000001000000110001100011010000100001100 2
#275000
b100110001000100000000001001100010001010010011010000000000010100 "
b100110001000100000000001001100010001010010011010000000000010100 .
b100110001000100000000001001100010001010010011010000000000010100 &
b1100111111000100010101101001111110101110011111011001010001011100 %
b1100111111000100010101101001111110101110011111011001010001011100 -
b111110001101101101010011111100011011011110011010110000010110111 $
b111110001101101101010011111100011011011110011010110000010110111 ,
b10011 )
b11001 *
#285000
b1100111111000100010101101001111110101110011111011001010001011100 0
b111110001101101101010011111100011011011110011010110000010110111 /
b100110001000100000000001001100010001010010011010000000000010100 2
#286000
b1010010010001010000000000100100101000000000000100011011010000000 "
b1010010010001010000000000100100101000000000000100011011010000000 .
b1010010010001010000000000100100101000000000000100011011010000000 &
b1010010010101110001100100100100111101000001000110011111011010000 %
b1010010010101110001100100100100111101000001000110011111011010000 -
b1010110111001011110000000101101101000100110111100011011110001001 $
b1010110111001011110000000101101101000100110111100011011110001001 ,
b10100 )
b11010 *
#296000
b1010010010101110001100100100100111101000001000110011111011010000 0
b1010110111001011110000000101101101000100110111100011011110001001 /
b1010010010001010000000000100100101000000000000100011011010000000 2
#297000
b100101100100000000000001001011000000000000001010111110000000000 "
b100101100100000000000001001011000000000000001010111110000000000 .
b100101100100000000000001001011000000000000001010111110000000000 &
b100101100100001001011111001011000000110000111010111111100001100 %
b100101100100001001011111001011000000110000111010111111100001100 -
b1110101111111110110000001101011110101000110001111111110001010001 $
b1110101111111110110000001101011110101000110001111111110001010001 ,
b10101 )
b11011 *
#307000
b100101100100001001011111001011000000110000111010111111100001100 0
b1110101111111110110000001101011110101000110001111111110001010001 /
b100101100100000000000001001011000000000000001010111110000000000 2
#308000
b1010000100000000010010100100001000000100010100101110110100001000 "
b1010000100000000010010100100001000000100010100101110110100001000 .
b1010000100000000010010100100001000000100010100101110110100001000 &
b1011101110000010010110100111011100011110111100101110110100111101 %
b1011101110000010010110100111011100011110111100101110110100111101 -
b1110000100101100110011101100001001100100010101111110110111001000 $
b1110000100101100110011101100001001100100010101111110110111001000 ,
b10110 )
b11100 *
#318000
b1011101110000010010110100111011100011110111100101110110100111101 0
b1110000100101100110011101100001001100100010101111110110111001000 /
b1010000100000000010010100100001000000100010100101110110100001000 2
#319000
b100100000010000000000011100000000010000000000111000 "
b100100000010000000000011100000000010000000000111000 .
b100100000010000000000011100000000010000000000111000 &
b11011011100101100000010110110100011100110110011110011100111001 %
b11011011100101100000010110110100011100110110011110011100111001 -
b100100001100110110110001001010111111000001010000000001111110 $
b100100001100110110110001001010111111000001010000000001111110 ,
b10111 )
b11101 *
#329000
b11011011100101100000010110110100011100110110011110011100111001 0
b100100001100110110110001001010111111000001010000000001111110 /
b100100000010000000000011100000000010000000000111000 2
#330000
b1011010000000011110000010110101000000000001000000001010000 "
b1011010000000011110000010110101000000000001000000001010000 .
b1011010000000011110000010110101000000000001000000001010000 &
b100001011011001001011111000010110111100000101001000100001111000 %
b100001011011001001011111000010110111100000101001000100001111000 -
b111111010010100011110001111111101001111010111111011011010011 $
b111111010010100011110001111111101001111010111111011011010011 ,
b11000 )
b11110 *
#340000
b100001011011001001011111000010110111100000101001000100001111000 0
b111111010010100011110001111111101001111010111111011011010011 /
b1011010000000011110000010110101000000000001000000001010000 2
#341000
b110111010010000010000001101100000100000010000000101100001000 "
b110111010010000010000001101100000100000010000000101100001000 .
b110111010010000010000001101100000100000010000000101100001000 &
b1001111111110010101011100011111100010101000011001010111100101010 %
b1001111111110010101011100011111100010101000011001010111100101010 -
b10110111011010010110010101101100100100100010110100101101001001 $
b10110111011010010110010101101100100100100010110100101101001001 ,
b11001 )
b11111 *
#351000
b1001111111110010101011100011111100010101000011001010111100101010 0
b10110111011010010110010101101100100100100010110100101101001001 /
b110111010010000010000001101100000100000010000000101100001000 2
#352000
b10000010000000000000000100011000010001011110011000010000100 "
b10000010000000000000000100011000010001011110011000010000100 .
b10000010000000000000000100011000010001011110011000010000100 &
b1100011100011010000011001000111011001110001011111111001010011100 %
b1100011100011010000011001000111011001110001011111111001010011100 -
b10110000010101011000110101100011000011001111110011100010000110 $
b10110000010101011000110101100011000011001111110011100010000110 ,
b11010 )
b100000 *
#362000
b1100011100011010000011001000111011001110001011111111001010011100 0
b10110000010101011000110101100011000011001111110011100010000110 /
b10000010000000000000000100011000010001011110011000010000100 2
#363000
b11100100010100000100010111001010010001000010011011010000100010 "
b11100100010100000100010111001010010001000010011011010000100010 .
b11100100010100000100010111001010010001000010011011010000100010 &
b11100110010110000101110111001111010001100010111011010010100011 %
b11100110010110000101110111001111010001100010111011010010100011 -
b111110100110101100110011111101010010011011111011011110000100110 $
b111110100110101100110011111101010010011011111011011110000100110 ,
b11011 )
b100001 *
#373000
b11100110010110000101110111001111010001100010111011010010100011 0
b111110100110101100110011111101010010011011111011011110000100110 /
b11100100010100000100010111001010010001000010011011010000100010 2
#374000
b1000011110011000000000000000111100000000000000000000000000000000 "
b1000011110011000000000000000111100000000000000000000000000000000 .
b1000011110011000000000000000111100000000000000000000000000000000 &
b1010111111011000010101100101111100100010001010010000110101000100 %
b1010111111011000010101100101111100100010001010010000110101000100 -
b1001011110011001101010000010111111011001110100101001001010110011 $
b1001011110011001101010000010111111011001110100101001001010110011 ,
b11100 )
b100010 *
#384000
b1010111111011000010101100101111100100010001010010000110101000100 0
b1001011110011001101010000010111111011001110100101001001010110011 /
b1000011110011000000000000000111100000000000000000000000000000000 2
#385000
b111001100001000000110001110011000100101000010000001001001001010 "
b111001100001000000110001110011000100101000010000001001001001010 .
b111001100001000000110001110011000100101000010000001001001001010 &
b1111001100001001000110101110011000101101001010001101101101011010 %
b1111001100001001000110101110011000101101001010001101101101011010 -
b111101111111000111111011111011111100101100110110011011011001011 $
b111101111111000111111011111011111100101100110110011011011001011 ,
b11101 )
b100011 *
#395000
b1111001100001001000110101110011000101101001010001101101101011010 0
b111101111111000111111011111011111100101100110110011011011001011 /
b111001100001000000110001110011000100101000010000001001001001010 2
#396000
b10001000011010000000000100010110010100000101010001001100101 "
b10001000011010000000000100010110010100000101010001001100101 .
b10001000011010000000000100010110010100000101010001001100101 &
b1110110101010011011011001101101010110010100111111011011001100101 %
b1110110101010011011011001101101010110010100111111011011001100101 -
b1010011001111110000010010100111110110100000101110001011101101 $
b1010011001111110000010010100111110110100000101110001011101101 ,
b11110 )
b100100 *
#406000
b1110110101010011011011001101101010110010100111111011011001100101 0
b1010011001111110000010010100111110110100000101110001011101101 /
b10001000011010000000000100010110010100000101010001001100101 2
#407000
b1100010000000000000000011000100100010001100001001010001000100 "
b1100010000000000000000011000100100010001100001001010001000100 .
b1100010000000000000000011000100100010001100001001010001000100 &
b11110011110001000110010111100100100010001100011111111101000100 %
b11110011110001000110010111100100100010001100011111111101000100 -
b1101101010001010111000101011010111101111101111101001010011011111 $
b1101101010001010111000101011010111101111101111101001010011011111 ,
b11111 )
b100101 *
#417000
b11110011110001000110010111100100100010001100011111111101000100 0
b1101101010001010111000101011010111101111101111101001010011011111 /
b1100010000000000000000011000100100010001100001001010001000100 2
#418000
b100000001110100000011001000000000000101000010010000101100001010 "
b100000001110100000011001000000000000101000010010000101100001010 .
b100000001110100000011001000000000000101000010010000101100001010 &
b101010111110110101011011010101100000111011011111100111100001110 %
b101010111110110101011011010101100000111011011111100111100001110 -
b1110100001110100000011001101000000010101000010010000101100101010 $
b1110100001110100000011001101000000010101000010010000101100101010 ,
b100000 )
b100110 *
#428000
b101010111110110101011011010101100000111011011111100111100001110 0
b1110100001110100000011001101000000010101000010010000101100101010 /
b100000001110100000011001000000000000101000010010000101100001010 2
#429000
b110111001011101001000001101110011000001010100000000000010000010 "
b110111001011101001000001101110011000001010100000000000010000010 .
b110111001011101001000001101110011000001010100000000000010000010 &
b1111111011011111011100101111110111100001111100010000001011000011 %
b1111111011011111011100101111110111100001111100010000001011000011 -
b110111001011101101011011101110011001101010111101011110010011010 $
b110111001011101101011011101110011001101010111101011110010011010 ,
b100001 )
b100111 *
