Lab07/NextPClogic.v
// NextPC Logic Module for ARMv8 Processor
// Determines the next Program Counter value based on branch conditions

module NextPClogic(
    output reg [63:0] NextPC,
    input  [63:0] CurrentPC,
    input  [63:0] SignExtImm64,
    input         Branch,
    input         ALUZero,
    input         Uncondbranch
);

    always @(*) begin
        // Unconditional branch takes highest priority
        if (Uncondbranch) begin
            // For unconditional branch (B instruction)
            // NextPC = CurrentPC + SignExtImm64
            NextPC = CurrentPC + SignExtImm64;
        end
        // Conditional branch when both Branch and ALUZero are true
        else if (Branch && ALUZero) begin
            // For conditional branch taken (CBZ instruction when register is zero)
            // NextPC = CurrentPC + SignExtImm64
            NextPC = CurrentPC + SignExtImm64;
        end
        // Otherwise, proceed to next sequential instruction
        else begin
            // No branch: NextPC = CurrentPC + 4
            NextPC = CurrentPC + 4;
        end
    end
endmodule

Lab06/NextPClogic_tb.v
// Self-Checking Testbench for NextPC Logic Module
// Tests all combinations of control inputs with randomized data

`timescale 1ns/1ps

module NextPClogic_tb;

    // Testbench signals
    reg [63:0] CurrentPC;
    reg [63:0] SignExtImm64;
    reg Branch;
    reg ALUZero;
    reg Uncondbranch;
    wire [63:0] NextPC;
    
    // Expected output for verification
    reg [63:0] expected_NextPC;
    
    // Test counters
    integer i;
    integer errors;
    integer total_tests;
    
    // Instantiate the NextPC logic module
    NextPClogic uut (
        .NextPC(NextPC),
        .CurrentPC(CurrentPC),
        .SignExtImm64(SignExtImm64),
        .Branch(Branch),
        .ALUZero(ALUZero),
        .Uncondbranch(Uncondbranch)
    );
    
    // Task to check results
    task check_result;
        input [63:0] exp_NextPC;
        input [63:0] curr_pc;
        input [63:0] imm;
        input br;
        input zero;
        input uncond;
        begin
            #1; // Small delay for signals to settle
            if (NextPC !== exp_NextPC) begin
                $display("ERROR at time %0t:", $time);
                $display("  Inputs: CurrentPC=%h, SignExtImm64=%h", curr_pc, imm);
                $display("          Branch=%b, ALUZero=%b, Uncondbranch=%b", br, zero, uncond);
                $display("  Expected NextPC: %h", exp_NextPC);
                $display("  Got NextPC:      %h", NextPC);
                errors = errors + 1;
            end
            total_tests = total_tests + 1;
        end
    endtask
    
    // Function to compute expected NextPC
    function [63:0] compute_expected;
        input [63:0] curr_pc;
        input [63:0] imm;
        input br;
        input zero;
        input uncond;
        begin
            if (uncond) begin
                compute_expected = curr_pc + imm;
            end
            else if (br && zero) begin
                compute_expected = curr_pc + imm;
            end
            else begin
                compute_expected = curr_pc + 4;
            end
        end
    endfunction
    
    // Task to test a specific control combination
    task test_control_combination;
        input br;
        input zero;
        input uncond;
        begin
            $display("Testing Branch=%b, ALUZero=%b, Uncondbranch=%b", br, zero, uncond);
            
            Branch = br;
            ALUZero = zero;
            Uncondbranch = uncond;
            
            // Perform 10 random tests for this control combination
            for (i = 0; i < 10; i = i + 1) begin
                // Generate random CurrentPC (aligned to 4-byte boundary for realism)
                CurrentPC = {$random, $random} & 64'hFFFFFFFFFFFFFFFC;
                
                // Generate random SignExtImm64
                SignExtImm64 = {$random, $random};
                
                // Compute expected result
                expected_NextPC = compute_expected(CurrentPC, SignExtImm64, Branch, ALUZero, Uncondbranch);
                
                #10;
                check_result(expected_NextPC, CurrentPC, SignExtImm64, Branch, ALUZero, Uncondbranch);
            end
        end
    endtask
    
    initial begin
        // Initialize VCD dump
        $dumpfile("nextpc.vcd");
        $dumpvars(0, NextPClogic_tb);
        
        // Initialize counters
        errors = 0;
        total_tests = 0;
        
        $display("=== NextPC Logic Testbench Starting ===");
        $display("Testing all 8 combinations of control inputs");
        $display("Each combination tested with 10 random data inputs");
        $display("");
        
        // Test all 8 combinations of the three control inputs
        // Branch=0, ALUZero=0, Uncondbranch=0 -> NextPC = CurrentPC + 4
        test_control_combination(0, 0, 0);
        
        // Branch=0, ALUZero=0, Uncondbranch=1 -> NextPC = CurrentPC + SignExtImm64
        test_control_combination(0, 0, 1);
        
        // Branch=0, ALUZero=1, Uncondbranch=0 -> NextPC = CurrentPC + 4
        test_control_combination(0, 1, 0);
        
        // Branch=0, ALUZero=1, Uncondbranch=1 -> NextPC = CurrentPC + SignExtImm64
        test_control_combination(0, 1, 1);
        
        // Branch=1, ALUZero=0, Uncondbranch=0 -> NextPC = CurrentPC + 4
        test_control_combination(1, 0, 0);
        
        // Branch=1, ALUZero=0, Uncondbranch=1 -> NextPC = CurrentPC + SignExtImm64
        test_control_combination(1, 0, 1);
        
        // Branch=1, ALUZero=1, Uncondbranch=0 -> NextPC = CurrentPC + SignExtImm64
        test_control_combination(1, 1, 0);
        
        // Branch=1, ALUZero=1, Uncondbranch=1 -> NextPC = CurrentPC + SignExtImm64
        test_control_combination(1, 1, 1);
        
        // Additional specific test cases
        $display("");
        $display("Testing specific corner cases...");
        
        // Test 1: Simple sequential execution
        CurrentPC = 64'h0000000000001000;
        SignExtImm64 = 64'h0000000000000100;
        Branch = 0;
        ALUZero = 0;
        Uncondbranch = 0;
        expected_NextPC = CurrentPC + 4;
        #10;
        check_result(expected_NextPC, CurrentPC, SignExtImm64, Branch, ALUZero, Uncondbranch);
        
        // Test 2: Unconditional branch forward
        CurrentPC = 64'h0000000000001000;
        SignExtImm64 = 64'h0000000000000100;
        Branch = 0;
        ALUZero = 0;
        Uncondbranch = 1;
        expected_NextPC = CurrentPC + SignExtImm64;
        #10;
        check_result(expected_NextPC, CurrentPC, SignExtImm64, Branch, ALUZero, Uncondbranch);
        
        // Test 3: Unconditional branch backward (negative offset)
        CurrentPC = 64'h0000000000001000;
        SignExtImm64 = 64'hFFFFFFFFFFFFFF00; // Negative offset
        Branch = 0;
        ALUZero = 0;
        Uncondbranch = 1;
        expected_NextPC = CurrentPC + SignExtImm64;
        #10;
        check_result(expected_NextPC, CurrentPC, SignExtImm64, Branch, ALUZero, Uncondbranch);
        
        // Test 4: Conditional branch taken (CBZ with zero register)
        CurrentPC = 64'h0000000000002000;
        SignExtImm64 = 64'h0000000000000080;
        Branch = 1;
        ALUZero = 1;
        Uncondbranch = 0;
        expected_NextPC = CurrentPC + SignExtImm64;
        #10;
        check_result(expected_NextPC, CurrentPC, SignExtImm64, Branch, ALUZero, Uncondbranch);
        
        // Test 5: Conditional branch not taken (CBZ with non-zero register)
        CurrentPC = 64'h0000000000002000;
        SignExtImm64 = 64'h0000000000000080;
        Branch = 1;
        ALUZero = 0;
        Uncondbranch = 0;
        expected_NextPC = CurrentPC + 4;
        #10;
        check_result(expected_NextPC, CurrentPC, SignExtImm64, Branch, ALUZero, Uncondbranch);
        
        // Test 6: Unconditional branch takes priority over conditional
        CurrentPC = 64'h0000000000003000;
        SignExtImm64 = 64'h0000000000000200;
        Branch = 1;
        ALUZero = 1;
        Uncondbranch = 1;
        expected_NextPC = CurrentPC + SignExtImm64;
        #10;
        check_result(expected_NextPC, CurrentPC, SignExtImm64, Branch, ALUZero, Uncondbranch);
        
        // Test 7: PC at zero
        CurrentPC = 64'h0000000000000000;
        SignExtImm64 = 64'h0000000000000010;
        Branch = 0;
        ALUZero = 0;
        Uncondbranch = 0;
        expected_NextPC = CurrentPC + 4;
        #10;
        check_result(expected_NextPC, CurrentPC, SignExtImm64, Branch, ALUZero, Uncondbranch);
        
        // Test 8: Large PC value
        CurrentPC = 64'hFFFFFFFFFFFFF000;
        SignExtImm64 = 64'h0000000000001000;
        Branch = 0;
        ALUZero = 0;
        Uncondbranch = 1;
        expected_NextPC = CurrentPC + SignExtImm64;
        #10;
        check_result(expected_NextPC, CurrentPC, SignExtImm64, Branch, ALUZero, Uncondbranch);
        
        // Final report
        $display("");
        $display("=== Test Results ===");
        $display("Total tests: %0d", total_tests);
        $display("Errors: %0d", errors);
        
        if (errors == 0) begin
            $display("*** ALL TESTS PASSED ***");
        end else begin
            $display("*** TESTS FAILED ***");
        end
        
        $display("");
        $finish;
    end

endmodule

Lab06/nextpc.vcd
$date
	Tue Oct  7 18:19:37 2025
$end
$version
	Icarus Verilog
$end
$timescale
	1ps
$end
$scope module NextPClogic_tb $end
$var wire 64 ! NextPC [63:0] $end
$var reg 1 " ALUZero $end
$var reg 1 # Branch $end
$var reg 64 $ CurrentPC [63:0] $end
$var reg 64 % SignExtImm64 [63:0] $end
$var reg 1 & Uncondbranch $end
$var reg 64 ' expected_NextPC [63:0] $end
$var integer 32 ( errors [31:0] $end
$var integer 32 ) i [31:0] $end
$var integer 32 * total_tests [31:0] $end
$scope function compute_expected $end
$var reg 1 + br $end
$var reg 64 , curr_pc [63:0] $end
$var reg 64 - imm [63:0] $end
$var reg 1 . uncond $end
$var reg 1 / zero $end
$upscope $end
$scope module uut $end
$var wire 1 " ALUZero $end
$var wire 1 # Branch $end
$var wire 64 0 CurrentPC [63:0] $end
$var wire 64 1 SignExtImm64 [63:0] $end
$var wire 1 & Uncondbranch $end
$var reg 64 2 NextPC [63:0] $end
$upscope $end
$scope task check_result $end
$var reg 1 3 br $end
$var reg 64 4 curr_pc [63:0] $end
$var reg 64 5 exp_NextPC [63:0] $end
$var reg 64 6 imm [63:0] $end
$var reg 1 7 uncond $end
$var reg 1 8 zero $end
$upscope $end
$scope task test_control_combination $end
$var reg 1 9 br $end
$var reg 1 : uncond $end
$var reg 1 ; zero $end
$upscope $end
$upscope $end
$enddefinitions $end
#0
$dumpvars
0;
0:
09
x8
x7
bx 6
bx 5
bx 4
x3
b1001000010101001101010010010011000000100010010101111010000100 2
b1000010010000100110101100000100110110001111100000101011001100011 1
b1001000010101001101010010010011000000100010010101111010000000 0
0/
0.
b1000010010000100110101100000100110110001111100000101011001100011 -
b1001000010101001101010010010011000000100010010101111010000000 ,
0+
b0 *
b0 )
b0 (
b1001000010101001101010010010011000000100010010101111010000100 '
0&
b1000010010000100110101100000100110110001111100000101011001100011 %
b1001000010101001101010010010011000000100010010101111010000000 $
0#
0"
b1001000010101001101010010010011000000100010010101111010000100 !
$end
#10000
07
08
03
b1000010010000100110101100000100110110001111100000101011001100011 6
b1001000010101001101010010010011000000100010010101111010000000 4
b1001000010101001101010010010011000000100010010101111010000100 5
#11000
b11010111001011110110000110101000110110111111001100110010000 !
b11010111001011110110000110101000110110111111001100110010000 2
b11010111001011110110000110101000110110111111001100110010000 '
b11010111001011110110000110101000110110111111001100110001100 ,
b1011001011000010100001000110010110001001001101110101001000010010 -
b1011001011000010100001000110010110001001001101110101001000010010 %
b1011001011000010100001000110010110001001001101110101001000010010 1
b11010111001011110110000110101000110110111111001100110001100 $
b11010111001011110110000110101000110110111111001100110001100 0
b1 )
b1 *
#21000
b1011001011000010100001000110010110001001001101110101001000010010 6
b11010111001011110110000110101000110110111111001100110001100 4
b11010111001011110110000110101000110110111111001100110010000 5
#22000
b11110011111000110000000100000110110101111100110100010000 !
b11110011111000110000000100000110110101111100110100010000 2
b11110011111000110000000100000110110101111100110100010000 '
b11110011111000110000000100000110110101111100110100001100 ,
b11101100100011111100010111011000011110100011011100110100111101 -
b11101100100011111100010111011000011110100011011100110100111101 %
b11101100100011111100010111011000011110100011011100110100111101 1
b11110011111000110000000100000110110101111100110100001100 $
b11110011111000110000000100000110110101111100110100001100 0
b10 )
b10 *
#32000
b11101100100011111100010111011000011110100011011100110100111101 6
b11110011111000110000000100000110110101111100110100001100 4
b11110011111000110000000100000110110101111100110100010000 5
#33000
b111011011010100010101111110110101000110001011011111011110010000 !
b111011011010100010101111110110101000110001011011111011110010000 2
b111011011010100010101111110110101000110001011011111011110010000 '
b111011011010100010101111110110101000110001011011111011110001100 ,
b111110011111101111010011111100111100011001101110010010011000110 -
b111110011111101111010011111100111100011001101110010010011000110 %
b111110011111101111010011111100111100011001101110010010011000110 1
b111011011010100010101111110110101000110001011011111011110001100 $
b111011011010100010101111110110101000110001011011111011110001100 0
b11 )
b11 *
#43000
b111110011111101111010011111100111100011001101110010010011000110 6
b111011011010100010101111110110101000110001011011111011110001100 4
b111011011010100010101111110110101000110001011011111011110010000 5
#44000
b1110001011110111100001001100010111010101000100111101001010101100 !
b1110001011110111100001001100010111010101000100111101001010101100 2
b1110001011110111100001001100010111010101000100111101001010101100 '
b1110001011110111100001001100010111010101000100111101001010101000 ,
b111001010101111111101111110010110111011110100100111001001110111 -
b111001010101111111101111110010110111011110100100111001001110111 %
b111001010101111111101111110010110111011110100100111001001110111 1
b1110001011110111100001001100010111010101000100111101001010101000 $
b1110001011110111100001001100010111010101000100111101001010101000 0
b100 )
b100 *
#54000
b111001010101111111101111110010110111011110100100111001001110111 6
b1110001011110111100001001100010111010101000100111101001010101000 4
b1110001011110111100001001100010111010101000100111101001010101100 5
#55000
b1000100100110010110101100001001001000111111011001101101110010000 !
b1000100100110010110101100001001001000111111011001101101110010000 2
b1000100100110010110101100001001001000111111011001101101110010000 '
b1000100100110010110101100001001001000111111011001101101110001100 ,
b111100100110000011010011111001011100111011101101001011011001110 -
b111100100110000011010011111001011100111011101101001011011001110 %
b111100100110000011010011111001011100111011101101001011011001110 1
b1000100100110010110101100001001001000111111011001101101110001100 $
b1000100100110010110101100001001001000111111011001101101110001100 0
b101 )
b101 *
#65000
b111100100110000011010011111001011100111011101101001011011001110 6
b1000100100110010110101100001001001000111111011001101101110001100 4
b1000100100110010110101100001001001000111111011001101101110010000 5
#66000
b1111010000000000011110101110100011100010110010100100111011001000 !
b1111010000000000011110101110100011100010110010100100111011001000 2
b1111010000000000011110101110100011100010110010100100111011001000 '
b1111010000000000011110101110100011100010110010100100111011000100 ,
b10111001011000010010010101110011011110100011100010100010111101 -
b10111001011000010010010101110011011110100011100010100010111101 %
b10111001011000010010010101110011011110100011100010100010111101 1
b1111010000000000011110101110100011100010110010100100111011000100 $
b1111010000000000011110101110100011100010110010100100111011000100 0
b110 )
b110 *
#76000
b10111001011000010010010101110011011110100011100010100010111101 6
b1111010000000000011110101110100011100010110010100100111011000100 4
b1111010000000000011110101110100011100010110010100100111011001000 5
#77000
b1001011010101011010110000010110110110010101001110010011001101000 !
b1001011010101011010110000010110110110010101001110010011001101000 2
b1001011010101011010110000010110110110010101001110010011001101000 '
b1001011010101011010110000010110110110010101001110010011001100100 ,
b1011000111101111011000100110001100000101011100111000011100001010 -
b1011000111101111011000100110001100000101011100111000011100001010 %
b1011000111101111011000100110001100000101011100111000011100001010 1
b1001011010101011010110000010110110110010101001110010011001100100 $
b1001011010101011010110000010110110110010101001110010011001100100 0
b111 )
b111 *
#87000
b1011000111101111011000100110001100000101011100111000011100001010 6
b1001011010101011010110000010110110110010101001110010011001100100 4
b1001011010101011010110000010110110110010101001110010011001101000 5
#88000
b1100000000111011001000101000000000010000011001000010000100100100 !
b1100000000111011001000101000000000010000011001000010000100100100 2
b1100000000111011001000101000000000010000011001000010000100100100 '
b1100000000111011001000101000000000010000011001000010000100100000 ,
b101010101111000010001011010101011001110110011001100110010011101 -
b101010101111000010001011010101011001110110011001100110010011101 %
b101010101111000010001011010101011001110110011001100110010011101 1
b1100000000111011001000101000000000010000011001000010000100100000 $
b1100000000111011001000101000000000010000011001000010000100100000 0
b1000 )
b1000 *
#98000
b101010101111000010001011010101011001110110011001100110010011101 6
b1100000000111011001000101000000000010000011001000010000100100000 4
b1100000000111011001000101000000000010000011001000010000100100100 5
#99000
b1100101100100000001111101001011010001001100000111011100000010100 !
b1100101100100000001111101001011010001001100000111011100000010100 2
b1100101100100000001111101001011010001001100000111011100000010100 '
b1100101100100000001111101001011010001001100000111011100000010000 ,
b1000011010111100001110000000110110101001101001111101011001010011 -
b1000011010111100001110000000110110101001101001111101011001010011 %
b1000011010111100001110000000110110101001101001111101011001010011 1
b1100101100100000001111101001011010001001100000111011100000010000 $
b1100101100100000001111101001011010001001100000111011100000010000 0
b1001 )
b1001 *
#109000
b1000011010111100001110000000110110101001101001111101011001010011 6
b1100101100100000001111101001011010001001100000111011100000010000 4
b1100101100100000001111101001011010001001100000111011100000010100 5
#110000
b1011011010110111001001110110111011000001111111000110100110000010 !
b1011011010110111001001110110111011000001111111000110100110000010 2
b1011011010110111001001110110111011000001111111000110100110000010 '
b11010110011111110111010110101111101010101001100010101011010100 ,
b1000000100010111010010100000001011010111010101100011111010101110 -
1.
b1000000100010111010010100000001011010111010101100011111010101110 %
b1000000100010111010010100000001011010111010101100011111010101110 1
b11010110011111110111010110101111101010101001100010101011010100 $
b11010110011111110111010110101111101010101001100010101011010100 0
1&
1:
b0 )
b1010 *
#120000
17
b1000000100010111010010100000001011010111010101100011111010101110 6
b11010110011111110111010110101111101010101001100010101011010100 4
b1011011010110111001001110110111011000001111111000110100110000010 5
#121000
b10000010000100001100100100000011101100110011101101011111010110 !
b10000010000100001100100100000011101100110011101101011111010110 2
b10000010000100001100100100000011101100110011101101011111010110 '
b111011111111111010010001110111100111110001010111001011001100 ,
b1000110000100010010010010001100000101000010010110010100001010 -
b1000110000100010010010010001100000101000010010110010100001010 %
b1000110000100010010010010001100000101000010010110010100001010 1
b111011111111111010010001110111100111110001010111001011001100 $
b111011111111111010010001110111100111110001010111001011001100 0
b1 )
b1011 *
#131000
b1000110000100010010010010001100000101000010010110010100001010 6
b111011111111111010010001110111100111110001010111001011001100 4
b10000010000100001100100100000011101100110011101101011111010110 5
#132000
b101111011011011110010001011110011100011010111111010110111000110 !
b101111011011011110010001011110011100011010111111010110111000110 2
b101111011011011110010001011110011100011010111111010110111000110 '
b1110010101110011000010101100101010011110001100010100110000111100 ,
b111100101101000101111011111001001000101001011100110000110001010 -
b111100101101000101111011111001001000101001011100110000110001010 %
b111100101101000101111011111001001000101001011100110000110001010 1
b1110010101110011000010101100101010011110001100010100110000111100 $
b1110010101110011000010101100101010011110001100010100110000111100 0
b10 )
b1100 *
#142000
b111100101101000101111011111001001000101001011100110000110001010 6
b1110010101110011000010101100101010011110001100010100110000111100 4
b101111011011011110010001011110011100011010111111010110111000110 5
#143000
b101110011100101101001101011101010110000110101010100011101100001 !
b101110011100101101001101011101010110000110101010100011101100001 2
b101110011100101101001101011101010110000110101010100011101100001 '
b10000011000100101100110100000111101100010010110011010011011000 ,
b11110000100000111100110111100011000100100010100001001010001001 -
b11110000100000111100110111100011000100100010100001001010001001 %
b11110000100000111100110111100011000100100010100001001010001001 1
b10000011000100101100110100000111101100010010110011010011011000 $
b10000011000100101100110100000111101100010010110011010011011000 0
b11 )
b1101 *
#153000
b11110000100000111100110111100011000100100010100001001010001001 6
b10000011000100101100110100000111101100010010110011010011011000 4
b101110011100101101001101011101010110000110101010100011101100001 5
#154000
b1101100100010001000001111011000110110010000101110111100101100010 !
b1101100100010001000001111011000110110010000101110111100101100010 2
b1101100100010001000001111011000110110010000101110111100101100010 '
b111010111000101000011011110101101011011000000100110010110110100 ,
b110001101001011111110011100011001010111000101010001001110101110 -
b110001101001011111110011100011001010111000101010001001110101110 %
b110001101001011111110011100011001010111000101010001001110101110 1
b111010111000101000011011110101101011011000000100110010110110100 $
b111010111000101000011011110101101011011000000100110010110110100 0
b100 )
b1110 *
#164000
b110001101001011111110011100011001010111000101010001001110101110 6
b111010111000101000011011110101101011011000000100110010110110100 4
b1101100100010001000001111011000110110010000101110111100101100010 5
#165000
b110010001001100100111001100011111001101101001111001101110011001 !
b110010001001100100111001100011111001101101001111001101110011001 2
b110010001001100100111001100011111001101101001111001101110011001 '
b1101111001110101000000101011110000010101000011111101110100101000 ,
b1000010111010111100110100000101110111000100101111011111001110001 -
b1000010111010111100110100000101110111000100101111011111001110001 %
b1000010111010111100110100000101110111000100101111011111001110001 1
b1101111001110101000000101011110000010101000011111101110100101000 $
b1101111001110101000000101011110000010101000011111101110100101000 0
b101 )
b1111 *
#175000
b1000010111010111100110100000101110111000100101111011111001110001 6
b1101111001110101000000101011110000010101000011111101110100101000 4
b110010001001100100111001100011111001101101001111001101110011001 5
#176000
b1110000010111110101000011100000001000100111110001000100010000110 !
b1110000010111110101000011100000001000100111110001000100010000110 2
b1110000010111110101000011100000001000100111110001000100010000110 '
b100001011110010010000011000010100100111111100100101010101001100 ,
b1001110111001100011000000011101100011101000001100011001100111010 -
b1001110111001100011000000011101100011101000001100011001100111010 %
b1001110111001100011000000011101100011101000001100011001100111010 1
b100001011110010010000011000010100100111111100100101010101001100 $
b100001011110010010000011000010100100111111100100101010101001100 0
b110 )
b10000 *
#186000
b1001110111001100011000000011101100011101000001100011001100111010 6
b100001011110010010000011000010100100111111100100101010101001100 4
b1110000010111110101000011100000001000100111110001000100010000110 5
#187000
b11011111111100110011100110111101110111010001101001011011101101 !
b11011111111100110011100110111101110111010001101001011011101101 2
b11011111111100110011100110111101110111010001101001011011101101 '
b1011111100100011001100100111111000001010101010100100101100010100 ,
b111100011011001100110111111000101101100100111000100101111011001 -
b111100011011001100110111111000101101100100111000100101111011001 %
b111100011011001100110111111000101101100100111000100101111011001 1
b1011111100100011001100100111111000001010101010100100101100010100 $
b1011111100100011001100100111111000001010101010100100101100010100 0
b111 )
b10001 *
#197000
b111100011011001100110111111000101101100100111000100101111011001 6
b1011111100100011001100100111111000001010101010100100101100010100 4
b11011111111100110011100110111101110111010001101001011011101101 5
#198000
b1000000011000100010111010000000101101101111011111001110011011011 !
b1000000011000100010111010000000101101101111011111001110011011011 2
b1000000011000100010111010000000101101101111011111001110011011011 '
b11000100100011000001110110001000100110001101011111101101001100 ,
b100111110100001010101011001111101000111101110011010000110001111 -
b100111110100001010101011001111101000111101110011010000110001111 %
b100111110100001010101011001111101000111101110011010000110001111 1
b11000100100011000001110110001000100110001101011111101101001100 $
b11000100100011000001110110001000100110001101011111101101001100 0
b1000 )
b10010 *
#208000
b100111110100001010101011001111101000111101110011010000110001111 6
b11000100100011000001110110001000100110001101011111101101001100 4
b1000000011000100010111010000000101101101111011111001110011011011 5
#209000
b100110000110010000000001001100010001010010010101111010100010000 !
b100110000110010000000001001100010001010010010101111010100010000 2
b100110000110010000000001001100010001010010010101111010100010000 '
b111110001101101101010011111100011011011110011010110000010110100 ,
b1100111111000100010101101001111110101110011111011001010001011100 -
b1100111111000100010101101001111110101110011111011001010001011100 %
b1100111111000100010101101001111110101110011111011001010001011100 1
b111110001101101101010011111100011011011110011010110000010110100 $
b111110001101101101010011111100011011011110011010110000010110100 0
b1001 )
b10011 *
#219000
b1100111111000100010101101001111110101110011111011001010001011100 6
b111110001101101101010011111100011011011110011010110000010110100 4
b100110000110010000000001001100010001010010010101111010100010000 5
#220000
b1010110111001011110000000101101101000100110111100011011110001100 !
b1010110111001011110000000101101101000100110111100011011110001100 2
b1010110111001011110000000101101101000100110111100011011110001100 '
b1010110111001011110000000101101101000100110111100011011110001000 ,
b1010010010101110001100100100100111101000001000110011111011010000 -
1/
0.
b1010010010101110001100100100100111101000001000110011111011010000 %
b1010010010101110001100100100100111101000001000110011111011010000 1
b1010110111001011110000000101101101000100110111100011011110001000 $
b1010110111001011110000000101101101000100110111100011011110001000 0
0&
1"
0:
1;
b0 )
b10100 *
#230000
07
18
b1010010010101110001100100100100111101000001000110011111011010000 6
b1010110111001011110000000101101101000100110111100011011110001000 4
b1010110111001011110000000101101101000100110111100011011110001100 5
#231000
b1110101111111110110000001101011110101000110001111111110001010100 !
b1110101111111110110000001101011110101000110001111111110001010100 2
b1110101111111110110000001101011110101000110001111111110001010100 '
b1110101111111110110000001101011110101000110001111111110001010000 ,
b100101100100001001011111001011000000110000111010111111100001100 -
b100101100100001001011111001011000000110000111010111111100001100 %
b100101100100001001011111001011000000110000111010111111100001100 1
b1110101111111110110000001101011110101000110001111111110001010000 $
b1110101111111110110000001101011110101000110001111111110001010000 0
b1 )
b10101 *
#241000
b100101100100001001011111001011000000110000111010111111100001100 6
b1110101111111110110000001101011110101000110001111111110001010000 4
b1110101111111110110000001101011110101000110001111111110001010100 5
#242000
b1110000100101100110011101100001001100100010101111110110111001100 !
b1110000100101100110011101100001001100100010101111110110111001100 2
b1110000100101100110011101100001001100100010101111110110111001100 '
b1110000100101100110011101100001001100100010101111110110111001000 ,
b1011101110000010010110100111011100011110111100101110110100111101 -
b1011101110000010010110100111011100011110111100101110110100111101 %
b1011101110000010010110100111011100011110111100101110110100111101 1
b1110000100101100110011101100001001100100010101111110110111001000 $
b1110000100101100110011101100001001100100010101111110110111001000 0
b10 )
b10110 *
#252000
b1011101110000010010110100111011100011110111100101110110100111101 6
b1110000100101100110011101100001001100100010101111110110111001000 4
b1110000100101100110011101100001001100100010101111110110111001100 5
#253000
b100100001100110110110001001010111111000001010000000010000000 !
b100100001100110110110001001010111111000001010000000010000000 2
b100100001100110110110001001010111111000001010000000010000000 '
b100100001100110110110001001010111111000001010000000001111100 ,
b11011011100101100000010110110100011100110110011110011100111001 -
b11011011100101100000010110110100011100110110011110011100111001 %
b11011011100101100000010110110100011100110110011110011100111001 1
b100100001100110110110001001010111111000001010000000001111100 $
b100100001100110110110001001010111111000001010000000001111100 0
b11 )
b10111 *
#263000
b11011011100101100000010110110100011100110110011110011100111001 6
b100100001100110110110001001010111111000001010000000001111100 4
b100100001100110110110001001010111111000001010000000010000000 5
#264000
b111111010010100011110001111111101001111010111111011011010100 !
b111111010010100011110001111111101001111010111111011011010100 2
b111111010010100011110001111111101001111010111111011011010100 '
b111111010010100011110001111111101001111010111111011011010000 ,
b100001011011001001011111000010110111100000101001000100001111000 -
b100001011011001001011111000010110111100000101001000100001111000 %
b100001011011001001011111000010110111100000101001000100001111000 1
b111111010010100011110001111111101001111010111111011011010000 $
b111111010010100011110001111111101001111010111111011011010000 0
b100 )
b11000 *
#274000
b100001011011001001011111000010110111100000101001000100001111000 6
b111111010010100011110001111111101001111010111111011011010000 4
b111111010010100011110001111111101001111010111111011011010100 5
#275000
b10110111011010010110010101101100100100100010110100101101001100 !
b10110111011010010110010101101100100100100010110100101101001100 2
b10110111011010010110010101101100100100100010110100101101001100 '
b10110111011010010110010101101100100100100010110100101101001000 ,
b1001111111110010101011100011111100010101000011001010111100101010 -
b1001111111110010101011100011111100010101000011001010111100101010 %
b1001111111110010101011100011111100010101000011001010111100101010 1
b10110111011010010110010101101100100100100010110100101101001000 $
b10110111011010010110010101101100100100100010110100101101001000 0
b101 )
b11001 *
#285000
b1001111111110010101011100011111100010101000011001010111100101010 6
b10110111011010010110010101101100100100100010110100101101001000 4
b10110111011010010110010101101100100100100010110100101101001100 5
#286000
b10110000010101011000110101100011000011001111110011100010001000 !
b10110000010101011000110101100011000011001111110011100010001000 2
b10110000010101011000110101100011000011001111110011100010001000 '
b10110000010101011000110101100011000011001111110011100010000100 ,
b1100011100011010000011001000111011001110001011111111001010011100 -
b1100011100011010000011001000111011001110001011111111001010011100 %
b1100011100011010000011001000111011001110001011111111001010011100 1
b10110000010101011000110101100011000011001111110011100010000100 $
b10110000010101011000110101100011000011001111110011100010000100 0
b110 )
b11010 *
#296000
b1100011100011010000011001000111011001110001011111111001010011100 6
b10110000010101011000110101100011000011001111110011100010000100 4
b10110000010101011000110101100011000011001111110011100010001000 5
#297000
b111110100110101100110011111101010010011011111011011110000101000 !
b111110100110101100110011111101010010011011111011011110000101000 2
b111110100110101100110011111101010010011011111011011110000101000 '
b111110100110101100110011111101010010011011111011011110000100100 ,
b11100110010110000101110111001111010001100010111011010010100011 -
b11100110010110000101110111001111010001100010111011010010100011 %
b11100110010110000101110111001111010001100010111011010010100011 1
b111110100110101100110011111101010010011011111011011110000100100 $
b111110100110101100110011111101010010011011111011011110000100100 0
b111 )
b11011 *
#307000
b11100110010110000101110111001111010001100010111011010010100011 6
b111110100110101100110011111101010010011011111011011110000100100 4
b111110100110101100110011111101010010011011111011011110000101000 5
#308000
b1001011110011001101010000010111111011001110100101001001010110100 !
b1001011110011001101010000010111111011001110100101001001010110100 2
b1001011110011001101010000010111111011001110100101001001010110100 '
b1001011110011001101010000010111111011001110100101001001010110000 ,
b1010111111011000010101100101111100100010001010010000110101000100 -
b1010111111011000010101100101111100100010001010010000110101000100 %
b1010111111011000010101100101111100100010001010010000110101000100 1
b1001011110011001101010000010111111011001110100101001001010110000 $
b1001011110011001101010000010111111011001110100101001001010110000 0
b1000 )
b11100 *
#318000
b1010111111011000010101100101111100100010001010010000110101000100 6
b1001011110011001101010000010111111011001110100101001001010110000 4
b1001011110011001101010000010111111011001110100101001001010110100 5
#319000
b111101111111000111111011111011111100101100110110011011011001100 !
b111101111111000111111011111011111100101100110110011011011001100 2
b111101111111000111111011111011111100101100110110011011011001100 '
b111101111111000111111011111011111100101100110110011011011001000 ,
b1111001100001001000110101110011000101101001010001101101101011010 -
b1111001100001001000110101110011000101101001010001101101101011010 %
b1111001100001001000110101110011000101101001010001101101101011010 1
b111101111111000111111011111011111100101100110110011011011001000 $
b111101111111000111111011111011111100101100110110011011011001000 0
b1001 )
b11101 *
#329000
b1111001100001001000110101110011000101101001010001101101101011010 6
b111101111111000111111011111011111100101100110110011011011001000 4
b111101111111000111111011111011111100101100110110011011011001100 5
#330000
b1000100011001011100000010010101001001000101001100101010001 !
b1000100011001011100000010010101001001000101001100101010001 2
b1000100011001011100000010010101001001000101001100101010001 '
b1010011001111110000010010100111110110100000101110001011101100 ,
b1110110101010011011011001101101010110010100111111011011001100101 -
1.
b1110110101010011011011001101101010110010100111111011011001100101 %
b1110110101010011011011001101101010110010100111111011011001100101 1
b1010011001111110000010010100111110110100000101110001011101100 $
b1010011001111110000010010100111110110100000101110001011101100 0
1&
1:
b0 )
b11110 *
#340000
17
b1110110101010011011011001101101010110010100111111011011001100101 6
b1010011001111110000010010100111110110100000101110001011101100 4
b1000100011001011100000010010101001001000101001100101010001 5
