Lab07/SignExtender.v
// Sign Extender Module for ARMv8 Processor
// Supports I-Type, D-Type, CB-Type, and B-Type instructions

`define Itype   2'b00
`define Dtype   2'b01
`define CBtype  2'b10
`define Btype   2'b11

module SignExtender(
    output reg [63:0] SignExOut,
    input      [25:0] Instruction,
    input      [1:0]  SignOp
);

    always @(*) begin
        case (SignOp)
            `Itype: begin
                // I-Type: 12-bit immediate in bits [21:10]
                SignExOut = {{52{Instruction[21]}}, Instruction[21:10]};
            end
            
            `Dtype: begin
                // D-Type: 9-bit immediate in bits [20:12]
                SignExOut = {{55{Instruction[20]}}, Instruction[20:12]};
            end
            
            `CBtype: begin
                // CB-Type: 19-bit immediate in bits [23:5]
                SignExOut = {{43{Instruction[23]}}, Instruction[23:5], 2'b00};
            end
            
            `Btype: begin
                // B-Type: 26-bit immediate in bits [25:0]
                SignExOut = {{36{Instruction[25]}}, Instruction[25:0], 2'b00};
            end
            
            default: begin
                SignExOut = 64'b0;
            end
        endcase
    end

endmodule

Lab06/SignExtender_tb.v
`timescale 1ns/1ps

`define Itype   2'b00
`define Dtype   2'b01
`define CBtype  2'b10
`define Btype   2'b11

module SignExtender_tb;
    //regs controlled by tb and wire are outputs from the test
    // Testbench signals
    reg [25:0] Instruction;
    reg [1:0]  SignOp;
    wire [63:0] SignExOut;
    
    // Expected output for verification
    reg [63:0] expected;
    
    // Test counters
    integer i;
    integer errors;
    integer total_tests;
    
    // Instantiate the Sign Extender module (Unit Under Test)
    SignExtender uut (
        .SignExOut(SignExOut),
        .Instruction(Instruction),
        .SignOp(SignOp)
    );
    
    // Task to check results. like a function. prints error if the result doesnt match expected
    task check_result;
        input [63:0] expected_val;
        input [1:0] op_type;
        input [25:0] instr;
        begin
            if (SignExOut !== expected_val) begin
                $display("ERROR at time %0t: SignOp=%b, Instruction=%h", 
                         $time, op_type, instr);
                $display("  Expected: %h, Got: %h", expected_val, SignExOut);
                errors = errors + 1;
            end
            total_tests = total_tests + 1;
        end
    endtask
    
    // Function to compute expected I-Type output
    function [63:0] compute_itype;
        input [25:0] instr;
        begin
            // 12-bit immediate, sign extend from bit 11
            compute_itype = {{52{instr[11]}}, instr[11:0]};
        end
    endfunction
    
    // Function to compute expected D-Type output
    function [63:0] compute_dtype;
        input [25:0] instr;
        begin
            // 9-bit immediate, sign extend from bit 8
            compute_dtype = {{55{instr[8]}}, instr[8:0]};
        end
    endfunction
    
    // Function to compute expected CB-Type output
    function [63:0] compute_cbtype;
        input [25:0] instr;
        begin
            // 19-bit immediate, sign extend and shift left by 2
            compute_cbtype = {{43{instr[18]}}, instr[18:0], 2'b00};
        end
    endfunction
    
    // Function to compute expected B-Type output
    function [63:0] compute_btype;
        input [25:0] instr;
        begin
            // 26-bit immediate, sign extend and shift left by 2
            compute_btype = {{36{instr[25]}}, instr[25:0], 2'b00};
        end
    endfunction
    
    //begin testing
    initial begin
        // Initialize VCD dump
        $dumpfile("sign_extender.vcd");
        $dumpvars(0, SignExtender_tb);
        
        // Initialize counters
        errors = 0;
        total_tests = 0;
        
        $display("=== Sign Extender Testbench Starting ===");
        $display("Testing with 100 random values per instruction type");
        $display("");
        
        // Test I-Type instructions
        $display("Testing I-Type (SignOp = 00)...");
        SignOp = `Itype;
        
        // Test some specific corner cases first
        Instruction = 26'h0000000; #10;
        expected = compute_itype(Instruction);
        check_result(expected, SignOp, Instruction);
        
        Instruction = 26'h0000FFF; #10; // Max positive 12-bit
        expected = compute_itype(Instruction);
        check_result(expected, SignOp, Instruction);
        
        Instruction = 26'h0000800; #10; // Min negative 12-bit
        expected = compute_itype(Instruction);
        check_result(expected, SignOp, Instruction);
        
        // Random tests for I-Type
        for (i = 0; i < 100; i = i + 1) begin
            Instruction = $random & 26'h3FFFFFF;
            #10;
            expected = compute_itype(Instruction);
            check_result(expected, SignOp, Instruction);
        end
        
        // Test D-Type instructions
        $display("Testing D-Type (SignOp = 01)...");
        SignOp = `Dtype;
        
        // Corner cases
        Instruction = 26'h0000000; #10;
        expected = compute_dtype(Instruction);
        check_result(expected, SignOp, Instruction);
        
        Instruction = 26'h00001FF; #10; // Max positive 9-bit
        expected = compute_dtype(Instruction);
        check_result(expected, SignOp, Instruction);
        
        Instruction = 26'h0000100; #10; // Min negative 9-bit
        expected = compute_dtype(Instruction);
        check_result(expected, SignOp, Instruction);
        
        // Random tests for D-Type
        for (i = 0; i < 100; i = i + 1) begin
            Instruction = $random & 26'h3FFFFFF;
            #10;
            expected = compute_dtype(Instruction);
            check_result(expected, SignOp, Instruction);
        end
        
        // Test CB-Type instructions
        $display("Testing CB-Type (SignOp = 10)...");
        SignOp = `CBtype;
        
        // Corner cases
        Instruction = 26'h0000000; #10;
        expected = compute_cbtype(Instruction);
        check_result(expected, SignOp, Instruction);
        
        Instruction = 26'h003FFFF; #10; // Max positive 19-bit
        expected = compute_cbtype(Instruction);
        check_result(expected, SignOp, Instruction);
        
        Instruction = 26'h0040000; #10; // Min negative 19-bit
        expected = compute_cbtype(Instruction);
        check_result(expected, SignOp, Instruction);
        
        // Random tests for CB-Type
        for (i = 0; i < 100; i = i + 1) begin
            Instruction = $random & 26'h3FFFFFF;
            #10;
            expected = compute_cbtype(Instruction);
            check_result(expected, SignOp, Instruction);
        end
        
        // Test B-Type instructions
        $display("Testing B-Type (SignOp = 11)...");
        SignOp = `Btype;
        
        // Corner cases
        Instruction = 26'h0000000; #10;
        expected = compute_btype(Instruction);
        check_result(expected, SignOp, Instruction);
        
        Instruction = 26'h1FFFFFF; #10; // Max positive 26-bit
        expected = compute_btype(Instruction);
        check_result(expected, SignOp, Instruction);
        
        Instruction = 26'h2000000; #10; // Min negative 26-bit
        expected = compute_btype(Instruction);
        check_result(expected, SignOp, Instruction);
        
        Instruction = 26'h3FFFFFF; #10; // All ones
        expected = compute_btype(Instruction);
        check_result(expected, SignOp, Instruction);
        
        // Random tests for B-Type
        for (i = 0; i < 100; i = i + 1) begin
            Instruction = $random & 26'h3FFFFFF;
            #10;
            expected = compute_btype(Instruction);
            check_result(expected, SignOp, Instruction);
        end
        
        // Final report
        $display("");
        $display("=== Test Results ===");
        $display("Total tests: %0d", total_tests);
        $display("Errors: %0d", errors);
        
        if (errors == 0) begin
            $display("*** ALL TESTS PASSED ***");
        end else begin
            $display("*** TESTS FAILED ***");
        end
        
        $display("");
        $finish;
    end

endmodule

Lab06/sign_extender.vcd
$date
	Tue Oct  7 18:17:30 2025
$end
$version
	Icarus Verilog
$end
$timescale
	1ps
$end
$scope module SignExtender_tb $end
$var wire 64 ! SignExOut [63:0] $end
$var reg 26 " Instruction [25:0] $end
$var reg 2 # SignOp [1:0] $end
$var reg 64 $ expected [63:0] $end
$var integer 32 % errors [31:0] $end
$var integer 32 & i [31:0] $end
$var integer 32 ' total_tests [31:0] $end
$scope function compute_btype $end
$var reg 26 ( instr [25:0] $end
$upscope $end
$scope function compute_cbtype $end
$var reg 26 ) instr [25:0] $end
$upscope $end
$scope function compute_dtype $end
$var reg 26 * instr [25:0] $end
$upscope $end
$scope function compute_itype $end
$var reg 26 + instr [25:0] $end
$upscope $end
$scope module uut $end
$var wire 26 , Instruction [25:0] $end
$var wire 2 - SignOp [1:0] $end
$var reg 64 . SignExOut [63:0] $end
$upscope $end
$scope task check_result $end
$var reg 64 / expected_val [63:0] $end
$var reg 26 0 instr [25:0] $end
$var reg 2 1 op_type [1:0] $end
$upscope $end
$upscope $end
$enddefinitions $end
#0
$dumpvars
bx 1
bx 0
bx /
b0 .
b0 -
b0 ,
bx +
bx *
bx )
bx (
b0 '
bx &
b0 %
bx $
b0 #
b0 "
b0 !
$end
#10000
b1111111111111111111111111111111111111111111111111111111111111111 !
b1111111111111111111111111111111111111111111111111111111111111111 .
b111111111111 "
b111111111111 ,
b1 '
b0 0
b0 1
b0 /
b0 $
b0 +
#20000
b1111111111111111111111111111111111111111111111111111100000000000 !
b1111111111111111111111111111111111111111111111111111100000000000 .
b100000000000 "
b100000000000 ,
b10 '
b111111111111 0
b1111111111111111111111111111111111111111111111111111111111111111 /
b1111111111111111111111111111111111111111111111111111111111111111 $
b111111111111 +
#30000
b10100100100 !
b10100100100 .
b10000101010011010100100100 "
b10000101010011010100100100 ,
b0 &
b11 '
b100000000000 0
b1111111111111111111111111111111111111111111111111111100000000000 /
b1111111111111111111111111111111111111111111111111111100000000000 $
b100000000000 +
#40000
b1111111111111111111111111111111111111111111111111111111010000001 !
b1111111111111111111111111111111111111111111111111111111010000001 .
b100010010101111010000001 "
b100010010101111010000001 ,
b1 &
b100 '
b10000101010011010100100100 0
b10100100100 /
b10100100100 $
b10000101010011010100100100 +
#50000
b11000001001 !
b11000001001 .
b100001001101011000001001 "
b100001001101011000001001 ,
b10 &
b101 '
b100010010101111010000001 0
b1111111111111111111111111111111111111111111111111111111010000001 /
b1111111111111111111111111111111111111111111111111111111010000001 $
b100010010101111010000001 +
#60000
b11001100011 !
b11001100011 .
b1111100000101011001100011 "
b1111100000101011001100011 ,
b11 &
b110 '
b100001001101011000001001 0
b11000001001 /
b11000001001 $
b100001001101011000001001 +
#70000
b1111111111111111111111111111111111111111111111111111101100001101 !
b1111111111111111111111111111111111111111111111111111101100001101 .
b10101110010111101100001101 "
b10101110010111101100001101 ,
b100 &
b111 '
b1111100000101011001100011 0
b11001100011 /
b11001100011 $
b1111100000101011001100011 +
#80000
b1111111111111111111111111111111111111111111111111111100110001101 !
b1111111111111111111111111111111111111111111111111111100110001101 .
b10110111111001100110001101 "
b10110111111001100110001101 ,
b101 &
b1000 '
b10101110010111101100001101 0
b1111111111111111111111111111111111111111111111111111101100001101 /
b1111111111111111111111111111111111111111111111111111101100001101 $
b10101110010111101100001101 +
#90000
b10001100101 !
b10001100101 .
b10110000101000010001100101 "
b10110000101000010001100101 ,
b110 &
b1001 '
b10110111111001100110001101 0
b1111111111111111111111111111111111111111111111111111100110001101 /
b1111111111111111111111111111111111111111111111111111100110001101 $
b10110111111001100110001101 +
#100000
b1000010010 !
b1000010010 .
b1001101110101001000010010 "
b1001101110101001000010010 ,
b111 &
b1010 '
b10110000101000010001100101 0
b10001100101 /
b10001100101 $
b10110000101000010001100101 +
#110000
b1100000001 !
b1100000001 .
b111100111110001100000001 "
b111100111110001100000001 ,
b1000 &
b1011 '
b1001101110101001000010010 0
b1000010010 /
b1000010010 $
b1001101110101001000010010 +
#120000
b1111111111111111111111111111111111111111111111111111110100001101 !
b1111111111111111111111111111111111111111111111111111110100001101 .
b10110101111100110100001101 "
b10110101111100110100001101 ,
b1001 &
b1100 '
b111100111110001100000001 0
b1100000001 /
b1100000001 $
b111100111110001100000001 +
#130000
b101110110 !
b101110110 .
b11001000111111000101110110 "
b11001000111111000101110110 ,
b1010 &
b1101 '
b10110101111100110100001101 0
b1111111111111111111111111111111111111111111111111111110100001101 /
b1111111111111111111111111111111111111111111111111111110100001101 $
b10110101111100110100001101 +
#140000
b1111111111111111111111111111111111111111111111111111110100111101 !
b1111111111111111111111111111111111111111111111111111110100111101 .
b10100011011100110100111101 "
b10100011011100110100111101 ,
b1011 &
b1110 '
b11001000111111000101110110 0
b101110110 /
b101110110 $
b11001000111111000101110110 +
#150000
b11111101101 !
b11111101101 .
b10110101000101011111101101 "
b10110101000101011111101101 ,
b1100 &
b1111 '
b10100011011100110100111101 0
b1111111111111111111111111111111111111111111111111111110100111101 /
b1111111111111111111111111111111111111111111111111111110100111101 $
b10100011011100110100111101 +
#160000
b11110001100 !
b11110001100 .
b10001011011111011110001100 "
b10001011011111011110001100 ,
b1101 &
b10000 '
b10110101000101011111101101 0
b11111101101 /
b11111101101 $
b10110101000101011111101101 +
#170000
b1111111111111111111111111111111111111111111111111111100111111001 !
b1111111111111111111111111111111111111111111111111111100111111001 .
b111111011110100111111001 "
b111111011110100111111001 ,
b1110 &
b10001 '
b10001011011111011110001100 0
b11110001100 /
b11110001100 $
b10001011011111011110001100 +
#180000
b10011000110 !
b10011000110 .
b11001101110010010011000110 "
b11001101110010010011000110 ,
b1111 &
b10010 '
b111111011110100111111001 0
b1111111111111111111111111111111111111111111111111111100111111001 /
b1111111111111111111111111111111111111111111111111111100111111001 $
b111111011110100111111001 +
#190000
b10011000101 !
b10011000101 .
b10111101111000010011000101 "
b10111101111000010011000101 ,
b10000 &
b10011 '
b11001101110010010011000110 0
b10011000110 /
b10011000110 $
b11001101110010010011000110 +
#200000
b1010101010 !
b1010101010 .
b1000100111101001010101010 "
b1000100111101001010101010 ,
b10001 &
b10100 '
b10111101111000010011000101 0
b10011000101 /
b10011000101 $
b10111101111000010011000101 +
#210000
b11111100101 !
b11111100101 .
b10101011111111011111100101 "
b10101011111111011111100101 ,
b10010 &
b10101 '
b1000100111101001010101010 0
b1010101010 /
b1010101010 $
b1000100111101001010101010 +
#220000
b1001110111 !
b1001110111 .
b11110100100111001001110111 "
b11110100100111001001110111 ,
b10011 &
b10110 '
b10101011111111011111100101 0
b11111100101 /
b11111100101 $
b10101011111111011111100101 +
#230000
b11000010010 !
b11000010010 .
b1001100101101011000010010 "
b1001100101101011000010010 ,
b10100 &
b10111 '
b11110100100111001001110111 0
b1001110111 /
b1001110111 $
b11110100100111001001110111 +
#240000
b1111111111111111111111111111111111111111111111111111101110001111 !
b1111111111111111111111111111111111111111111111111111101110001111 .
b11111011001101101110001111 "
b11111011001101101110001111 ,
b10101 &
b11000 '
b1001100101101011000010010 0
b11000010010 /
b11000010010 $
b1001100101101011000010010 +
#250000
b1111111111111111111111111111111111111111111111111111100111110010 !
b1111111111111111111111111111111111111111111111111111100111110010 .
b1001100000110100111110010 "
b1001100000110100111110010 ,
b10110 &
b11001 '
b11111011001101101110001111 0
b1111111111111111111111111111111111111111111111111111101110001111 /
b1111111111111111111111111111111111111111111111111111101110001111 $
b11111011001101101110001111 +
#260000
b11011001110 !
b11011001110 .
b11011101101001011011001110 "
b11011101101001011011001110 ,
b10111 &
b11010 '
b1001100000110100111110010 0
b1111111111111111111111111111111111111111111111111111100111110010 /
b1111111111111111111111111111111111111111111111111111100111110010 $
b1001100000110100111110010 +
#270000
b1111111111111111111111111111111111111111111111111111101011101000 !
b1111111111111111111111111111111111111111111111111111101011101000 .
b111101011101000 "
b111101011101000 ,
b11000 &
b11011 '
b11011101101001011011001110 0
b11011001110 /
b11011001110 $
b11011101101001011011001110 +
#280000
b1111111111111111111111111111111111111111111111111111111011000101 !
b1111111111111111111111111111111111111111111111111111111011000101 .
b10110010100100111011000101 "
b10110010100100111011000101 ,
b11001 &
b11100 '
b111101011101000 0
b1111111111111111111111111111111111111111111111111111101011101000 /
b1111111111111111111111111111111111111111111111111111101011101000 $
b111101011101000 +
#290000
b1111111111111111111111111111111111111111111111111111100101011100 !
b1111111111111111111111111111111111111111111111111111100101011100 .
b10010110000100100101011100 "
b10010110000100100101011100 ,
b11010 &
b11101 '
b10110010100100111011000101 0
b1111111111111111111111111111111111111111111111111111111011000101 /
b1111111111111111111111111111111111111111111111111111111011000101 $
b10110010100100111011000101 +
#300000
b1111111111111111111111111111111111111111111111111111100010111101 !
b1111111111111111111111111111111111111111111111111111100010111101 .
b10100011100010100010111101 "
b10100011100010100010111101 ,
b11011 &
b11110 '
b10010110000100100101011100 0
b1111111111111111111111111111111111111111111111111111100101011100 /
b1111111111111111111111111111111111111111111111111111100101011100 $
b10010110000100100101011100 +
#310000
b1111111111111111111111111111111111111111111111111111100000101101 !
b1111111111111111111111111111111111111111111111111111100000101101 .
b10101010110101100000101101 "
b10101010110101100000101101 ,
b11100 &
b11111 '
b10100011100010100010111101 0
b1111111111111111111111111111111111111111111111111111100010111101 /
b1111111111111111111111111111111111111111111111111111100010111101 $
b10100011100010100010111101 +
#320000
b11001100101 !
b11001100101 .
b10101001110010011001100101 "
b10101001110010011001100101 ,
b11101 &
b100000 '
b10101010110101100000101101 0
b1111111111111111111111111111111111111111111111111111100000101101 /
b1111111111111111111111111111111111111111111111111111100000101101 $
b10101010110101100000101101 +
#330000
b1001100011 !
b1001100011 .
b1111011110110001001100011 "
b1111011110110001001100011 ,
b11110 &
b100001 '
b10101001110010011001100101 0
b11001100101 /
b11001100101 $
b10101001110010011001100101 +
#340000
b11100001010 !
b11100001010 .
b1011100111000011100001010 "
b1011100111000011100001010 ,
b11111 &
b100010 '
b1111011110110001001100011 0
b1001100011 /
b1001100011 $
b1111011110110001001100011 +
#350000
b1010000000 !
b1010000000 .
b1110110010001010000000 "
b1110110010001010000000 ,
b100000 &
b100011 '
b1011100111000011100001010 0
b11100001010 /
b11100001010 $
b1011100111000011100001010 +
#360000
b100100000 !
b100100000 .
b11001000010000100100000 "
b11001000010000100100000 ,
b100001 &
b100100 '
b1110110010001010000000 0
b1010000000 /
b1010000000 $
b1110110010001010000000 +
#370000
b10110101010 !
b10110101010 .
b1011110000100010110101010 "
b1011110000100010110101010 ,
b100010 &
b100101 '
b11001000010000100100000 0
b100100000 /
b100100000 $
b11001000010000100100000 +
#380000
b1111111111111111111111111111111111111111111111111111110010011101 !
b1111111111111111111111111111111111111111111111111111110010011101 .
b10110011001100110010011101 "
b10110011001100110010011101 ,
b100011 &
b100110 '
b1011110000100010110101010 0
b10110101010 /
b10110101010 $
b1011110000100010110101010 +
#390000
b1111111111111111111111111111111111111111111111111111111010010110 !
b1111111111111111111111111111111111111111111111111111111010010110 .
b11001000000011111010010110 "
b11001000000011111010010110 ,
b100100 &
b100111 '
b10110011001100110010011101 0
b1111111111111111111111111111111111111111111111111111110010011101 /
b1111111111111111111111111111111111111111111111111111110010011101 $
b10110011001100110010011101 +
#400000
b1111111111111111111111111111111111111111111111111111100000010011 !
b1111111111111111111111111111111111111111111111111111100000010011 .
b1100000111011100000010011 "
b1100000111011100000010011 ,
b100101 &
b101000 '
b11001000000011111010010110 0
b1111111111111111111111111111111111111111111111111111111010010110 /
b1111111111111111111111111111111111111111111111111111111010010110 $
b11001000000011111010010110 +
#410000
b1111111111111111111111111111111111111111111111111111100000001101 !
b1111111111111111111111111111111111111111111111111111100000001101 .
b10101111000011100000001101 "
b10101111000011100000001101 ,
b100110 &
b101001 '
b1100000111011100000010011 0
b1111111111111111111111111111111111111111111111111111100000010011 /
b1111111111111111111111111111111111111111111111111111100000010011 $
b1100000111011100000010011 +
#420000
b11001010011 !
b11001010011 .
b1101001111101011001010011 "
b1101001111101011001010011 ,
b100111 &
b101010 '
b10101111000011100000001101 0
b1111111111111111111111111111111111111111111111111111100000001101 /
b1111111111111111111111111111111111111111111111111111100000001101 $
b10101111000011100000001101 +
#430000
b1111111111111111111111111111111111111111111111111111110101101011 !
b1111111111111111111111111111111111111111111111111111110101101011 .
b1100111111101110101101011 "
b1100111111101110101101011 ,
b101000 &
b101011 '
b1101001111101011001010011 0
b11001010011 /
b11001010011 $
b1101001111101011001010011 +
#440000
b1111111111111111111111111111111111111111111111111111101011010101 !
b1111111111111111111111111111111111111111111111111111101011010101 .
b10101001100010101011010101 "
b10101001100010101011010101 ,
b101001 &
b101100 '
b1100111111101110101101011 0
b1111111111111111111111111111111111111111111111111111110101101011 /
b1111111111111111111111111111111111111111111111111111110101101011 $
b1100111111101110101101011 +
#450000
b1111111111111111111111111111111111111111111111111111101000000010 !
b1111111111111111111111111111111111111111111111111111101000000010 .
b1000101110100101000000010 "
b1000101110100101000000010 ,
b101010 &
b101101 '
b10101001100010101011010101 0
b1111111111111111111111111111111111111111111111111111101011010101 /
b1111111111111111111111111111111111111111111111111111101011010101 $
b10101001100010101011010101 +
#460000
b1111111111111111111111111111111111111111111111111111111010101110 !
b1111111111111111111111111111111111111111111111111111111010101110 .
b11010101100011111010101110 "
b11010101100011111010101110 ,
b101011 &
b101110 '
b1000101110100101000000010 0
b1111111111111111111111111111111111111111111111111111101000000010 /
b1111111111111111111111111111111111111111111111111111101000000010 $
b1000101110100101000000010 +
#470000
b1111111111111111111111111111111111111111111111111111100100011101 !
b1111111111111111111111111111111111111111111111111111100100011101 .
b10111111111110100100011101 "
b10111111111110100100011101 ,
b101100 &
b101111 '
b11010101100011111010101110 0
b1111111111111111111111111111111111111111111111111111111010101110 /
b1111111111111111111111111111111111111111111111111111111010101110 $
b11010101100011111010101110 +
#480000
b1011001111 !
b1011001111 .
b11110001010111001011001111 "
b11110001010111001011001111 ,
b101101 &
b110000 '
b10111111111110100100011101 0
b1111111111111111111111111111111111111111111111111111100100011101 /
b1111111111111111111111111111111111111111111111111111100100011101 $
b10111111111110100100011101 +
#490000
b1111111111111111111111111111111111111111111111111111100100100011 !
b1111111111111111111111111111111111111111111111111111100100100011 .
b1100001000100100100100011 "
b1100001000100100100100011 ,
b101110 &
b110001 '
b11110001010111001011001111 0
b1011001111 /
b1011001111 $
b11110001010111001011001111 +
#500000
b10100001010 !
b10100001010 .
b1000010010110010100001010 "
b1000010010110010100001010 ,
b101111 &
b110010 '
b1100001000100100100100011 0
b1111111111111111111111111111111111111111111111111111100100100011 /
b1111111111111111111111111111111111111111111111111111100100100011 $
b1100001000100100100100011 +
#510000
b1111111111111111111111111111111111111111111111111111101011001010 !
b1111111111111111111111111111111111111111111111111111101011001010 .
b1011100110000101011001010 "
b1011100110000101011001010 ,
b110000 &
b110011 '
b1000010010110010100001010 0
b10100001010 /
b10100001010 $
b1000010010110010100001010 +
#520000
b1111111111111111111111111111111111111111111111111111110000111100 !
b1111111111111111111111111111111111111111111111111111110000111100 .
b10001100010100110000111100 "
b10001100010100110000111100 ,
b110001 &
b110100 '
b1011100110000101011001010 0
b1111111111111111111111111111111111111111111111111111101011001010 /
b1111111111111111111111111111111111111111111111111111101011001010 $
b1011100110000101011001010 +
#530000
b1111111111111111111111111111111111111111111111111111110111110010 !
b1111111111111111111111111111111111111111111111111111110111110010 .
b1011010001011110111110010 "
b1011010001011110111110010 ,
b110010 &
b110101 '
b10001100010100110000111100 0
b1111111111111111111111111111111111111111111111111111110000111100 /
b1111111111111111111111111111111111111111111111111111110000111100 $
b10001100010100110000111100 +
#540000
b110001010 !
b110001010 .
b1001011100110000110001010 "
b1001011100110000110001010 ,
b110011 &
b110110 '
b1011010001011110111110010 0
b1111111111111111111111111111111111111111111111111111110111110010 /
b1111111111111111111111111111111111111111111111111111110111110010 $
b1011010001011110111110010 +
#550000
b1101000001 !
b1101000001 .
b110001001011001101000001 "
b110001001011001101000001 ,
b110100 &
b110111 '
b1001011100110000110001010 0
b110001010 /
b110001010 $
b1001011100110000110001010 +
#560000
b10011011000 !
b10011011000 .
b10010110011010011011000 "
b10010110011010011011000 ,
b110101 &
b111000 '
b110001001011001101000001 0
b1101000001 /
b1101000001 $
b110001001011001101000001 +
#570000
b1101111000 !
b1101111000 .
b1000001111001101111000 "
b1000001111001101111000 ,
b110110 &
b111001 '
b10010110011010011011000 0
b10011011000 /
b10011011000 $
b10010110011010011011000 +
#580000
b1010001001 !
b1010001001 .
b100010100001001010001001 "
b100010100001001010001001 ,
b110111 &
b111010 '
b1000001111001101111000 0
b1101111000 /
b1101111000 $
b1000001111001101111000 +
#590000
b1111111111111111111111111111111111111111111111111111110111101011 !
b1111111111111111111111111111111111111111111111111111110111101011 .
b1110001010000110111101011 "
b1110001010000110111101011 ,
b111000 &
b111011 '
b100010100001001010001001 0
b1010001001 /
b1010001001 $
b100010100001001010001001 +
#600000
b10110110110 !
b10110110110 .
b11000000100110010110110110 "
b11000000100110010110110110 ,
b111001 &
b111100 '
b1110001010000110111101011 0
b1111111111111111111111111111111111111111111111111111110111101011 /
b1111111111111111111111111111111111111111111111111111110111101011 $
b1110001010000110111101011 +
#610000
b1111111111111111111111111111111111111111111111111111100111000110 !
b1111111111111111111111111111111111111111111111111111100111000110 .
b11010010111111100111000110 "
b11010010111111100111000110 ,
b111010 &
b111101 '
b11000000100110010110110110 0
b10110110110 /
b10110110110 $
b11000000100110010110110110 +
#620000
b1110101110 !
b1110101110 .
b11000101010001001110101110 "
b11000101010001001110101110 ,
b111011 &
b111110 '
b11010010111111100111000110 0
b1111111111111111111111111111111111111111111111111111100111000110 /
b1111111111111111111111111111111111111111111111111111100111000110 $
b11010010111111100111000110 +
#630000
b1010111100 !
b1010111100 .
b10011101010000001010111100 "
b10011101010000001010111100 ,
b111100 &
b111111 '
b11000101010001001110101110 0
b1110101110 /
b1110101110 $
b11000101010001001110101110 +
#640000
b1111111111111111111111111111111111111111111111111111110100101010 !
b1111111111111111111111111111111111111111111111111111110100101010 .
b1000011111101110100101010 "
b1000011111101110100101010 ,
b111101 &
b1000000 '
b10011101010000001010111100 0
b1010111100 /
b1010111100 $
b10011101010000001010111100 +
#650000
b1111111111111111111111111111111111111111111111111111101000001011 !
b1111111111111111111111111111111111111111111111111111101000001011 .
b1110101111001101000001011 "
b1110101111001101000001011 ,
b111110 &
b1000001 '
b1000011111101110100101010 0
b1111111111111111111111111111111111111111111111111111110100101010 /
b1111111111111111111111111111111111111111111111111111110100101010 $
b1000011111101110100101010 +
#660000
b1111111111111111111111111111111111111111111111111111111001110001 !
b1111111111111111111111111111111111111111111111111111111001110001 .
b100101111011111001110001 "
b100101111011111001110001 ,
b111111 &
b1000010 '
b1110101111001101000001011 0
b1111111111111111111111111111111111111111111111111111101000001011 /
b1111111111111111111111111111111111111111111111111111101000001011 $
b1110101111001101000001011 +
#670000
b110000101 !
b110000101 .
b10111100100100000110000101 "
b10111100100100000110000101 ,
b1000000 &
b1000011 '
b100101111011111001110001 0
b1111111111111111111111111111111111111111111111111111111001110001 /
b1111111111111111111111111111111111111111111111111111111001110001 $
b100101111011111001110001 +
#680000
b10101001111 !
b10101001111 .
b11111100100101010101001111 "
b11111100100101010101001111 ,
b1000001 &
b1000100 '
b10111100100100000110000101 0
b110000101 /
b110000101 $
b10111100100100000110000101 +
#690000
b111011 !
b111011 .
b1110011000110000000111011 "
b1110011000110000000111011 ,
b1000010 &
b1000101 '
b11111100100101010101001111 0
b10101001111 /
b10101001111 $
b11111100100101010101001111 +
#700000
b1100111010 !
b1100111010 .
b1000001100011001100111010 "
b1000001100011001100111010 ,
b1000011 &
b1000110 '
b1110011000110000000111011 0
b111011 /
b111011 $
b1110011000110000000111011 +
#710000
b1001111110 !
b1001111110 .
b11001000110011001001111110 "
b11001000110011001001111110 ,
b1000100 &
b1000111 '
b1000001100011001100111010 0
b1100111010 /
b1100111010 $
b1000001100011001100111010 +
#720000
b1111111111111111111111111111111111111111111111111111101100010101 !
b1111111111111111111111111111111111111111111111111111101100010101 .
b10101010100100101100010101 "
b10101010100100101100010101 ,
b1000101 &
b1001000 '
b11001000110011001001111110 0
b1001111110 /
b1001111110 $
b11001000110011001001111110 +
#730000
b1111111111111111111111111111111111111111111111111111101111110001 !
b1111111111111111111111111111111111111111111111111111101111110001 .
b110110011001101111110001 "
b110110011001101111110001 ,
b1000110 &
b1001001 '
b10101010100100101100010101 0
b1111111111111111111111111111111111111111111111111111101100010101 /
b1111111111111111111111111111111111111111111111111111101100010101 $
b10101010100100101100010101 +
#740000
b1111111111111111111111111111111111111111111111111111101111011001 !
b1111111111111111111111111111111111111111111111111111101111011001 .
b100111000100101111011001 "
b100111000100101111011001 ,
b1000111 &
b1001010 '
b110110011001101111110001 0
b1111111111111111111111111111111111111111111111111111101111110001 /
b1111111111111111111111111111111111111111111111111111101111110001 $
b110110011001101111110001 +
#750000
b11101100010 !
b11101100010 .
b1001000110000011101100010 "
b1001000110000011101100010 ,
b1001000 &
b1001011 '
b100111000100101111011001 0
b1111111111111111111111111111111111111111111111111111101111011001 /
b1111111111111111111111111111111111111111111111111111101111011001 $
b100111000100101111011001 +
#760000
b1111111111111111111111111111111111111111111111111111101101001100 !
b1111111111111111111111111111111111111111111111111111101101001100 .
b10001101011111101101001100 "
b10001101011111101101001100 ,
b1001001 &
b1001100 '
b1001000110000011101100010 0
b11101100010 /
b11101100010 $
b1001000110000011101100010 +
#770000
b10110011111 !
b10110011111 .
b11101000010101010110011111 "
b11101000010101010110011111 ,
b1001010 &
b1001101 '
b10001101011111101101001100 0
b1111111111111111111111111111111111111111111111111111101101001100 /
b1111111111111111111111111111111111111111111111111111101101001100 $
b10001101011111101101001100 +
#780000
b110001111 !
b110001111 .
b11101110011010000110001111 "
b11101110011010000110001111 ,
b1001011 &
b1001110 '
b11101000010101010110011111 0
b10110011111 /
b10110011111 $
b11101000010101010110011111 +
#790000
b1111111111111111111111111111111111111111111111111111100111111000 !
b1111111111111111111111111111111111111111111111111111100111111000 .
b11011011010100111111000 "
b11011011010100111111000 ,
b1001100 &
b1001111 '
b11101110011010000110001111 0
b110001111 /
b110001111 $
b11101110011010000110001111 +
#800000
b10110111 !
b10110111 .
b11110011010110000010110111 "
b11110011010110000010110111 ,
b1001101 &
b1010000 '
b11011011010100111111000 0
b1111111111111111111111111111111111111111111111111111100111111000 /
b1111111111111111111111111111111111111111111111111111100111111000 $
b11011011010100111111000 +
#810000
b11010011111 !
b11010011111 .
b11110001000101011010011111 "
b11110001000101011010011111 ,
b1001110 &
b1010001 '
b11110011010110000010110111 0
b10110111 /
b10110111 $
b11110011010110000010110111 +
#820000
b10001011100 !
b10001011100 .
b10011111011001010001011100 "
b10011111011001010001011100 ,
b1001111 &
b1010010 '
b11110001000101011010011111 0
b11010011111 /
b11010011111 $
b11110001000101011010011111 +
#830000
b1011011 !
b1011011 .
b1110010111100000001011011 "
b1110010111100000001011011 ,
b1010000 &
b1010011 '
b10011111011001010001011100 0
b10001011100 /
b10001011100 $
b10011111011001010001011100 +
#840000
b11110001001 !
b11110001001 .
b110111100011011110001001 "
b110111100011011110001001 ,
b1010001 &
b1010100 '
b1110010111100000001011011 0
b1011011 /
b1011011 $
b1110010111100000001011011 +
